Workbook

Sheet Competitive Analysis
C2: SEASONS AT MERIDIAN — 5-Mile Competitive Supply
B3: 2022–2026 New Construction | 5-mile radius | As of 2026 Q3 QTD
B4: # | C4: Property | D4: Units | E4: Est. Delivery | F4: Occupancy | G4: Avg Mkt Rent | H4: Owner | I4: Proximity | J4: Type | K4: Notes
C5: STABILIZED / STABILIZING (21 properties, 2,519 units)
B6: 1 | C6: The Lost Rapid Townhomes | D6: 72 | E6: Q1 2022 | F6: 0.944444 | G6: — | H6: Baker, Matthew J | I6: 5 | J6: Townhome | M6: =IFERROR(VALUE(RIGHT(E6,4))*4+MATCH(LEFT(E6,2),{"Q1","Q2","Q3","Q4"},0)-1,"")
B7: 2 | C7: South Ridge I | D7: 476 | E7: Q2 2022 | F7: 0.994 | G7: — | H7: Privately Owned | I7: 3.1 | J7: Garden | K7: Delivery quarter estimated; RealPage-only — not in CoStar's 5-mi series | M7: =IFERROR(VALUE(RIGHT(E7,4))*4+MATCH(LEFT(E7,2),{"Q1","Q2","Q3","Q4"},0)-1,"")
B8: 3 | C8: Meritage West | D8: 83 | E8: Q2 2022 | F8: 0.987952 | G8: 1651.435 | H8: Pacific West Communities, Inc. | I8: 3.2 | J8: Mid-Rise | M8: =IFERROR(VALUE(RIGHT(E8,4))*4+MATCH(LEFT(E8,2),{"Q1","Q2","Q3","Q4"},0)-1,"")
B9: 4 | C9: Ambleside Townhomes | D9: 67 | E9: Q2 2022 | F9: 0.970149 | G9: 2130 | H9: Open Door Rentals Llc | I9: 2.8 | J9: Townhome | M9: =IFERROR(VALUE(RIGHT(E9,4))*4+MATCH(LEFT(E9,2),{"Q1","Q2","Q3","Q4"},0)-1,"")
B10: 5 | C10: Celebration Acres | D10: 28 | E10: Q2 2022 | F10: 0.964286 | G10: — | H10: El Ada Comm Action Agency Inc | I10: 2.7 | J10: Low-Rise | M10: =IFERROR(VALUE(RIGHT(E10,4))*4+MATCH(LEFT(E10,2),{"Q1","Q2","Q3","Q4"},0)-1,"")
B11: 6 | C11: Pine 43 | D11: 25 | E11: Q2 2022 | F11: 1 | G11: 2236 | H11: Bruce M Reichard | I11: 1.7 | J11: Garden | M11: =IFERROR(VALUE(RIGHT(E11,4))*4+MATCH(LEFT(E11,2),{"Q1","Q2","Q3","Q4"},0)-1,"")
B12: 7 | C12: Old Town Lofts | D12: 102 | E12: Q3 2022 | F12: 0.990196 | G12: 1665.5116 | H12: Pacific West Communities, Inc. | I12: 2.1 | J12: Townhome | K12: Year built: 2022/2023 | M12: =IFERROR(VALUE(RIGHT(E12,4))*4+MATCH(LEFT(E12,2),{"Q1","Q2","Q3","Q4"},0)-1,"")
B13: 8 | C13: Lavender Village | D13: 6 | E13: Q3 2022 | F13: 1 | G13: 1747.5137 | H13: — | I13: 3.9 | J13: Garden | K13: Rent: HD mix-wtd $1,748 vs CoStar ask $2,110 | M13: =IFERROR(VALUE(RIGHT(E13,4))*4+MATCH(LEFT(E13,2),{"Q1","Q2","Q3","Q4"},0)-1,"")
B14: 9 | C14: The Prospect | D14: 91 | E14: Q4 2022 | F14: 0.989011 | G14: 1165.5556 | H14: Ke Holdings Llc | I14: 3.9 | J14: Garden | M14: =IFERROR(VALUE(RIGHT(E14,4))*4+MATCH(LEFT(E14,2),{"Q1","Q2","Q3","Q4"},0)-1,"")
B15: 10 | C15: Etheridge Lane | D15: 12 | E15: Q4 2022 | F15: 1 | G15: — | H15: Visser Building Co | I15: 4.4 | J15: Garden | M15: =IFERROR(VALUE(RIGHT(E15,4))*4+MATCH(LEFT(E15,2),{"Q1","Q2","Q3","Q4"},0)-1,"")
B16: 11 | C16: Modern Craftsman Ten Mile | D16: 135 | E16: Q1 2023 | F16: 0.948148 | G16: 2164.3198 | H16: Baron Properties | I16: 3.9 | J16: Single Family | K16: Year built: 2022/2023; Occ: CoStar 95% vs RealPage 99% | M16: =IFERROR(VALUE(RIGHT(E16,4))*4+MATCH(LEFT(E16,2),{"Q1","Q2","Q3","Q4"},0)-1,"")
B17: 12 | C17: WaterWalk Boise – Meridian | D17: 38 | E17: Q1 2023 | F17: 0.947368 | G17: 1655 | H17: WaterWalk Live Stay | I17: 1 | J17: Mid-Rise | M17: =IFERROR(VALUE(RIGHT(E17,4))*4+MATCH(LEFT(E17,2),{"Q1","Q2","Q3","Q4"},0)-1,"")
B18: 13 | C18: Alante Homes at Hazelwood | D18: 32 | E18: Q1 2023 | F18: 0.96875 | G18: 2276 | H18: PEG Companies | I18: 3.8 | J18: Garden | M18: =IFERROR(VALUE(RIGHT(E18,4))*4+MATCH(LEFT(E18,2),{"Q1","Q2","Q3","Q4"},0)-1,"")
B19: 14 | C19: Altair | D19: 240 | E19: Q2 2023 | F19: 0.945833 | G19: 1624.4078 | H19: Brighton | I19: 3.4 | J19: Mid-Rise | K19: Occ: CoStar 95% vs RealPage 100% | M19: =IFERROR(VALUE(RIGHT(E19,4))*4+MATCH(LEFT(E19,2),{"Q1","Q2","Q3","Q4"},0)-1,"")
B20: 15 | C20: Dovetail | D20: 240 | E20: Q2 2023 | F20: 0.958333 | G20: 1832 | H20: Kennedy Wilson, Inc. | I20: 1.8 | J20: Garden | K20: Units: CoStar 240 vs RealPage 480; Year built: 2020/2023; Occ: CoStar 96% vs RealPage 99% | M20: =IFERROR(VALUE(RIGHT(E20,4))*4+MATCH(LEFT(E20,2),{"Q1","Q2","Q3","Q4"},0)-1,"")
B21: 16 | C21: Yellowstone Apartments | D21: 216 | E21: Q2 2023 | F21: 0.763889 | G21: 1735.4694 | H21: CBH Homes | I21: 4.1 | J21: Garden | K21: Year built: 2023/2025; Occ: CoStar 76% vs RealPage 94% | M21: =IFERROR(VALUE(RIGHT(E21,4))*4+MATCH(LEFT(E21,2),{"Q1","Q2","Q3","Q4"},0)-1,"")
B22: 17 | C22: Telluride | D22: 102 | E22: Q2 2023 | F22: 0.990196 | G22: 1884.4468 | H22: Albert Meier | I22: 3.5 | J22: Low-Rise | M22: =IFERROR(VALUE(RIGHT(E22,4))*4+MATCH(LEFT(E22,2),{"Q1","Q2","Q3","Q4"},0)-1,"")
B23: 18 | C23: Movado Village | D23: 60 | E23: Q1 2024 | F23: 0.933333 | G23: 1995 | H23: Realty Asset Management, Inc. | I23: 1 | J23: Garden | M23: =IFERROR(VALUE(RIGHT(E23,4))*4+MATCH(LEFT(E23,2),{"Q1","Q2","Q3","Q4"},0)-1,"")
B24: 19 | C24: Viera at Pinnacle | D24: 56 | E24: Q1 2024 | F24: 1 | G24: 2489.375 | H24: Brighton | I24: 3.2 | J24: Garden | M24: =IFERROR(VALUE(RIGHT(E24,4))*4+MATCH(LEFT(E24,2),{"Q1","Q2","Q3","Q4"},0)-1,"")
B25: 20 | C25: The Aren | D25: 396 | E25: Q2 2024 | F25: 0.969697 | G25: 1739.209 | H25: Brighton | I25: 0.9 | J25: Garden | K25: Year built: 2024/2025; Occ: CoStar 97% vs RealPage 100% | M25: =IFERROR(VALUE(RIGHT(E25,4))*4+MATCH(LEFT(E25,2),{"Q1","Q2","Q3","Q4"},0)-1,"")
B26: 21 | C26: Springtree Apartments | D26: 42 | E26: Q4 2024 | F26: 0.952381 | G26: 1514 | H26: Commercial Northwest Property Management | I26: 4.8 | J26: Low-Rise | M26: =IFERROR(VALUE(RIGHT(E26,4))*4+MATCH(LEFT(E26,2),{"Q1","Q2","Q3","Q4"},0)-1,"")
C28: LEASING UP (5 properties, 815 units)
B29: 22 | C29: Village Apartments | D29: 336 | E29: Q2 2024 | F29: 0.11904762 | G29: 1747.5137 | H29: Rockworth Companies | I29: 2.6 | J29: Mid-Rise | K29: Occ: CoStar 80% vs RealPage 11%; Occ: HD ~12% (CoStar/RP showed 80%); HD (90d): occ ~12% (units leased), ~13 leases/mo | M29: =IFERROR(VALUE(RIGHT(E29,4))*4+MATCH(LEFT(E29,2),{"Q1","Q2","Q3","Q4"},0)-1,"")
B30: 23 | C30: Wesley Apartments and Townhomes | D30: 191 | E30: Q2 2024 | F30: 0.47643979 | G30: 1994.4847 | H30: Executive Management Services, LLC | I30: 3.5 | J30: Townhome | K30: Occ: CoStar 28% vs RealPage 84%; Rent: CoStar ask $1,716 vs RealPage eff $2,004; Rent: HD mix-wtd $1,994 vs CoStar ask $1,716; Occ: HD ~48% (CoStar/RP showed 28%); HD (90d): occ ~48% (units leased), ~22 leases/mo | M30: =IFERROR(VALUE(RIGHT(E30,4))*4+MATCH(LEFT(E30,2),{"Q1","Q2","Q3","Q4"},0)-1,"")
B31: 24 | C31: Shamrock Apartments | D31: 48 | E31: Q2 2025 | F31: 0.833333 | G31: — | H31: Dc Fairview Llc | I31: 2.6 | J31: Low-Rise | K31: Verify rent/occ w/ HelloData | M31: =IFERROR(VALUE(RIGHT(E31,4))*4+MATCH(LEFT(E31,2),{"Q1","Q2","Q3","Q4"},0)-1,"")
B32: 25 | C32: Tauri Apartments | D32: 156 | E32: Q2 2026 | F32: 1 | G32: 1833.7261 | H32: Brighton | I32: 4.6 | J32: Townhome | K32: Units: CoStar 156 vs RealPage 128; Year built: 2026/2027; Occ: CoStar 25% vs RealPage 18%; Rent: CoStar ask $1,862 vs RealPage eff $1,684; Occ: HD ~100% (CoStar/RP showed 25%); HD (90d): occ ~100% (units leased), ~20 leases/mo | M32: =IFERROR(VALUE(RIGHT(E32,4))*4+MATCH(LEFT(E32,2),{"Q1","Q2","Q3","Q4"},0)-1,"")
B33: 26 | C33: Delano | D33: 84 | E33: Q2 2026 | F33: 0.452 | G33: — | H33: CBH Homes | I33: 3.3 | J33: Garden | K33: Delivery quarter estimated; Verify rent/occ w/ HelloData; RealPage-only — not in CoStar's 5-mi series | M33: =IFERROR(VALUE(RIGHT(E33,4))*4+MATCH(LEFT(E33,2),{"Q1","Q2","Q3","Q4"},0)-1,"")
C35: UNDER CONSTRUCTION (2 properties, 716 units)
B36: 27 | C36: South Ridge II | D36: 164 | E36: Q2 2027 | G36: — | H36: — | I36: 3.1 | J36: Garden | M36: =IFERROR(VALUE(RIGHT(E36,4))*4+MATCH(LEFT(E36,2),{"Q1","Q2","Q3","Q4"},0)-1,"")
B37: 28 | C37: Vanguard Village | D37: 552 | E37: Q1 2028 | G37: — | H37: — | I37: 4.3 | J37: Mid-Rise | M37: =IFERROR(VALUE(RIGHT(E37,4))*4+MATCH(LEFT(E37,2),{"Q1","Q2","Q3","Q4"},0)-1,"")
C39: PROPOSED (13 properties, 3,176 units)
B40: 29 | C40: Union 93 | D40: 350 | E40: Q3 2026 | G40: — | H40: Grey Owl Holdings Llc | I40: 1.9 | J40: Mid-Rise | K40: Diligence: stalled - foreclosure since Nov 2022; no restart as of Jul 2026 | M40: =IFERROR(VALUE(RIGHT(E40,4))*4+MATCH(LEFT(E40,2),{"Q1","Q2","Q3","Q4"},0)-1,"")
B41: 30 | C41: The Judy (Maple Grove & Overland) | D41: 162 | E41: Q1 2028 | G41: — | H41: — | I41: 3.4 | K41: Analyst-sourced deal (not in CoStar/RealPage); Diligence: proposed - equity raise underway; construction targeted Q3 2026 | M41: =IFERROR(VALUE(RIGHT(E41,4))*4+MATCH(LEFT(E41,2),{"Q1","Q2","Q3","Q4"},0)-1,"")
B42: 31 | C42: Victory Flats | D42: 301 | E42: Q3 2028 | G42: — | H42: Welltower Inc. | I42: 3.9 | J42: Townhome | K42: Diligence: proposed | M42: =IFERROR(VALUE(RIGHT(E42,4))*4+MATCH(LEFT(E42,2),{"Q1","Q2","Q3","Q4"},0)-1,"")
B43: 32 | C43: The Gateway at Ten Mile | D43: 390 | E43: Q4 2028 | G43: — | H43: TGI Corp | I43: 3.7 | J43: Mid-Rise | K43: Diligence: proposed | M43: =IFERROR(VALUE(RIGHT(E43,4))*4+MATCH(LEFT(E43,2),{"Q1","Q2","Q3","Q4"},0)-1,"")
B44: 33 | C44: Ascent Overland | D44: 138 | E44: Q1 2029 | G44: — | H44: — | I44: 1.5 | J44: Mid-Rise | K44: Diligence: proposed | M44: =IFERROR(VALUE(RIGHT(E44,4))*4+MATCH(LEFT(E44,2),{"Q1","Q2","Q3","Q4"},0)-1,"")
B45: 34 | C45: Record | D45: 472 | E45: TBD | G45: — | H45: — | I45: 1.9 | J45: Mid-Rise | K45: RealPage pipeline (not yet in CoStar); Diligence: proposed | M45: =IFERROR(VALUE(RIGHT(E45,4))*4+MATCH(LEFT(E45,2),{"Q1","Q2","Q3","Q4"},0)-1,"")
B46: 35 | C46: Syringa Crossing | D46: 322 | E46: TBD | G46: — | H46: — | I46: 2.8 | J46: Mid-Rise | K46: RealPage pipeline (not yet in CoStar); Diligence: proposed | M46: =IFERROR(VALUE(RIGHT(E46,4))*4+MATCH(LEFT(E46,2),{"Q1","Q2","Q3","Q4"},0)-1,"")
B47: 36 | C47: 12565 West Fairview Avenue | D47: 275 | E47: TBD | G47: — | H47: — | I47: 2.1 | J47: Mid-Rise | K47: RealPage pipeline (not yet in CoStar); Diligence: proposed | M47: =IFERROR(VALUE(RIGHT(E47,4))*4+MATCH(LEFT(E47,2),{"Q1","Q2","Q3","Q4"},0)-1,"")
B48: 37 | C48: Cobalt Point | D48: 264 | E48: TBD | G48: — | H48: — | I48: 0.6 | J48: Garden | K48: RealPage pipeline (not yet in CoStar); Diligence: proposed | M48: =IFERROR(VALUE(RIGHT(E48,4))*4+MATCH(LEFT(E48,2),{"Q1","Q2","Q3","Q4"},0)-1,"")
B49: 38 | C49: 12548 West Overland Road | D49: 156 | E49: TBD | G49: — | H49: — | I49: 1.1 | J49: Mid-Rise | K49: RealPage pipeline (not yet in CoStar); Diligence: proposed | M49: =IFERROR(VALUE(RIGHT(E49,4))*4+MATCH(LEFT(E49,2),{"Q1","Q2","Q3","Q4"},0)-1,"")
B50: 39 | C50: Fairview | D50: 150 | E50: TBD | G50: — | H50: — | I50: 2.1 | J50: Townhome | K50: RealPage pipeline (not yet in CoStar); Diligence: proposed | M50: =IFERROR(VALUE(RIGHT(E50,4))*4+MATCH(LEFT(E50,2),{"Q1","Q2","Q3","Q4"},0)-1,"")
B51: 40 | C51: The Cole Denton | D51: 136 | E51: TBD | G51: — | H51: — | I51: 4.5 | J51: Mid-Rise | K51: RealPage pipeline (not yet in CoStar); Diligence: proposed | M51: =IFERROR(VALUE(RIGHT(E51,4))*4+MATCH(LEFT(E51,2),{"Q1","Q2","Q3","Q4"},0)-1,"")
B52: 41 | C52: Meridian OZ Apartments | D52: 60 | E52: TBD | G52: — | H52: Peak Capital Investments Llc | I52: 1.1 | J52: Garden | K52: Diligence: proposed | M52: =IFERROR(VALUE(RIGHT(E52,4))*4+MATCH(LEFT(E52,2),{"Q1","Q2","Q3","Q4"},0)-1,"")
B55: * 5-Mile radius. Rent ($) = HelloData mix-weighted asking where covered, else market asking (CoStar). Proximity (mi) = straight-line distance from the subject. Est. Delivery drives the Supply & Absorption tab's per-window supply (edit it there or here — they are linked). See the 'Supply & Absorption' tab for the forward supply / absorption / overall-occupancy forecast.

Sheet Supply & Absorption
Z1: 8105
B2: SUPPLY & ABSORPTION — 5-MILE MARKET (relative-year / TTM) | Z2: =IFERROR(VALUE(RIGHT($C$5,4))*4+MATCH(LEFT($C$5,2),{"Q1","Q2","Q3","Q4"},0)-1,0)
R3: UNDER CONSTRUCTION (linked from Competitive Analysis) | Z3: =IF($C$7="Bear",3,IF($C$7="Base",2,1))
B4: As-of Quarter (Y0 end) | C4: Q2 2026 | D4: ◂ Y0 = the trailing-12-months ending here (latest complete CoStar quarter); -Y1…-Y6 step back a year each. | R4: Property | S4: Units | T4: Est. Delivery
B5: Close Quarter (Y1 start) | C5: Q4 2026 | D5: ◂ Expected deal close. Y1 = the 12 months starting here; pipeline deliveries bucket into hold years off this anchor — edit it and the Y1–Y6 windows & supply shift. | R5: ='Competitive Analysis'!C37 | S5: ='Competitive Analysis'!D37 | T5: ='Competitive Analysis'!E37 | V5: =IFERROR(VALUE(RIGHT(T5,4))*4+MATCH(LEFT(T5,2),{"Q1","Q2","Q3","Q4"},0)-1,"") | W5: =IF(V5="","",IF(V5<=$Z$1,0,MAX(1,INT((V5-$Z$2)/4)+1)))
B6: Stabilization Target | C6: 0.95 | R6: ='Competitive Analysis'!C36 | S6: ='Competitive Analysis'!D36 | T6: ='Competitive Analysis'!E36 | V6: =IFERROR(VALUE(RIGHT(T6,4))*4+MATCH(LEFT(T6,2),{"Q1","Q2","Q3","Q4"},0)-1,"") | W6: =IF(V6="","",IF(V6<=$Z$1,0,MAX(1,INT((V6-$Z$2)/4)+1)))
B7: Demand Scenario | C7: Base
B8: Bear Annual Absorption | C8: 425 | R8: PROPOSED PIPELINE (scenario toggle)
B9: Base Annual Absorption | C9: 850 | R9: Property | S9: Units | T9: Est. Delivery | U9: Built In
B10: Bull Annual Absorption | C10: 1275 | D10: ◂ Base = trailing-3-yr CoStar average (annualized, complete quarters). | R10: Record | S10: 472 | U10: Bear only | V10: =IFERROR(VALUE(RIGHT(T10,4))*4+MATCH(LEFT(T10,2),{"Q1","Q2","Q3","Q4"},0)-1,"") | W10: =IF(V10="","",IF(V10<=$Z$1,0,MAX(1,INT((V10-$Z$2)/4)+1))) | X10: =IF(U10="All",1,IF(U10="Bear+Base",IF($Z$3>=2,1,0),IF(U10="Bear only",IF($Z$3>=3,1,0),0)))
B11: Selected Annual Demand | C11: =IF($C$7="Bear",$C$8,IF($C$7="Bull",$C$10,$C$9)) | R11: The Gateway at Ten Mile | S11: 390 | T11: Q4 2028 | U11: Bear only | V11: =IFERROR(VALUE(RIGHT(T11,4))*4+MATCH(LEFT(T11,2),{"Q1","Q2","Q3","Q4"},0)-1,"") | W11: =IF(V11="","",IF(V11<=$Z$1,0,MAX(1,INT((V11-$Z$2)/4)+1))) | X11: =IF(U11="All",1,IF(U11="Bear+Base",IF($Z$3>=2,1,0),IF(U11="Bear only",IF($Z$3>=3,1,0),0)))
R12: Union 93 | S12: 350 | T12: Q3 2026 | U12: Bear only | V12: =IFERROR(VALUE(RIGHT(T12,4))*4+MATCH(LEFT(T12,2),{"Q1","Q2","Q3","Q4"},0)-1,"") | W12: =IF(V12="","",IF(V12<=$Z$1,0,MAX(1,INT((V12-$Z$2)/4)+1))) | X12: =IF(U12="All",1,IF(U12="Bear+Base",IF($Z$3>=2,1,0),IF(U12="Bear only",IF($Z$3>=3,1,0),0)))
R13: Syringa Crossing | S13: 322 | U13: Bear only | V13: =IFERROR(VALUE(RIGHT(T13,4))*4+MATCH(LEFT(T13,2),{"Q1","Q2","Q3","Q4"},0)-1,"") | W13: =IF(V13="","",IF(V13<=$Z$1,0,MAX(1,INT((V13-$Z$2)/4)+1))) | X13: =IF(U13="All",1,IF(U13="Bear+Base",IF($Z$3>=2,1,0),IF(U13="Bear only",IF($Z$3>=3,1,0),0)))
R14: Victory Flats | S14: 301 | T14: Q3 2028 | U14: Bear only | V14: =IFERROR(VALUE(RIGHT(T14,4))*4+MATCH(LEFT(T14,2),{"Q1","Q2","Q3","Q4"},0)-1,"") | W14: =IF(V14="","",IF(V14<=$Z$1,0,MAX(1,INT((V14-$Z$2)/4)+1))) | X14: =IF(U14="All",1,IF(U14="Bear+Base",IF($Z$3>=2,1,0),IF(U14="Bear only",IF($Z$3>=3,1,0),0)))
R15: 12565 West Fairview Avenue | S15: 275 | U15: Bear only | V15: =IFERROR(VALUE(RIGHT(T15,4))*4+MATCH(LEFT(T15,2),{"Q1","Q2","Q3","Q4"},0)-1,"") | W15: =IF(V15="","",IF(V15<=$Z$1,0,MAX(1,INT((V15-$Z$2)/4)+1))) | X15: =IF(U15="All",1,IF(U15="Bear+Base",IF($Z$3>=2,1,0),IF(U15="Bear only",IF($Z$3>=3,1,0),0)))
R16: Cobalt Point | S16: 264 | U16: Bear only | V16: =IFERROR(VALUE(RIGHT(T16,4))*4+MATCH(LEFT(T16,2),{"Q1","Q2","Q3","Q4"},0)-1,"") | W16: =IF(V16="","",IF(V16<=$Z$1,0,MAX(1,INT((V16-$Z$2)/4)+1))) | X16: =IF(U16="All",1,IF(U16="Bear+Base",IF($Z$3>=2,1,0),IF(U16="Bear only",IF($Z$3>=3,1,0),0)))
B17: 5-MILE MARKET | C17: -Y6 | D17: -Y5 | E17: -Y4 | F17: -Y3 | G17: -Y2 | H17: -Y1 | I17: Y0 | J17: Y1 | K17: Y2 | L17: Y3 | M17: Y4 | N17: Y5 | O17: Y6 | R17: The Judy (Maple Grove & Overland) | S17: 162 | T17: Q1 2028 | U17: Bear only | V17: =IFERROR(VALUE(RIGHT(T17,4))*4+MATCH(LEFT(T17,2),{"Q1","Q2","Q3","Q4"},0)-1,"") | W17: =IF(V17="","",IF(V17<=$Z$1,0,MAX(1,INT((V17-$Z$2)/4)+1))) | X17: =IF(U17="All",1,IF(U17="Bear+Base",IF($Z$3>=2,1,0),IF(U17="Bear only",IF($Z$3>=3,1,0),0)))
C18: Q3'19-Q2'20 | D18: Q3'20-Q2'21 | E18: Q3'21-Q2'22 | F18: Q3'22-Q2'23 | G18: Q3'23-Q2'24 | H18: Q3'24-Q2'25 | I18: Q3'25-Q2'26 | J18: ="Q"&(MOD(($Z$2+0),4)+1)&"'"&RIGHT(INT(($Z$2+0)/4),2)&"-Q"&(MOD(($Z$2+3),4)+1)&"'"&RIGHT(INT(($Z$2+3)/4),2) | K18: ="Q"&(MOD(($Z$2+4),4)+1)&"'"&RIGHT(INT(($Z$2+4)/4),2)&"-Q"&(MOD(($Z$2+7),4)+1)&"'"&RIGHT(INT(($Z$2+7)/4),2) | L18: ="Q"&(MOD(($Z$2+8),4)+1)&"'"&RIGHT(INT(($Z$2+8)/4),2)&"-Q"&(MOD(($Z$2+11),4)+1)&"'"&RIGHT(INT(($Z$2+11)/4),2) | M18: ="Q"&(MOD(($Z$2+12),4)+1)&"'"&RIGHT(INT(($Z$2+12)/4),2)&"-Q"&(MOD(($Z$2+15),4)+1)&"'"&RIGHT(INT(($Z$2+15)/4),2) | N18: ="Q"&(MOD(($Z$2+16),4)+1)&"'"&RIGHT(INT(($Z$2+16)/4),2)&"-Q"&(MOD(($Z$2+19),4)+1)&"'"&RIGHT(INT(($Z$2+19)/4),2) | O18: ="Q"&(MOD(($Z$2+20),4)+1)&"'"&RIGHT(INT(($Z$2+20)/4),2)&"-Q"&(MOD(($Z$2+23),4)+1)&"'"&RIGHT(INT(($Z$2+23)/4),2) | R18: 12548 West Overland Road | S18: 156 | U18: Bear only | V18: =IFERROR(VALUE(RIGHT(T18,4))*4+MATCH(LEFT(T18,2),{"Q1","Q2","Q3","Q4"},0)-1,"") | W18: =IF(V18="","",IF(V18<=$Z$1,0,MAX(1,INT((V18-$Z$2)/4)+1))) | X18: =IF(U18="All",1,IF(U18="Bear+Base",IF($Z$3>=2,1,0),IF(U18="Bear only",IF($Z$3>=3,1,0),0)))
B19: NEW SUPPLY (5-mi) | C19: 1227 | D19: 1575 | E19: 629 | F19: 1232 | G19: 1049 | H19: 450 | I19: =SUMIFS('Competitive Analysis'!$D$5:$D$52,'Competitive Analysis'!$M$5:$M$52,">="&8102,'Competitive Analysis'!$M$5:$M$52,"<="&8105) | J19: =SUMIFS($S$5:$S$6,$W$5:$W$6,1)+SUMIFS($S$10:$S$22,$W$10:$W$22,1,$X$10:$X$22,1) | K19: =SUMIFS($S$5:$S$6,$W$5:$W$6,2)+SUMIFS($S$10:$S$22,$W$10:$W$22,2,$X$10:$X$22,1) | L19: =SUMIFS($S$5:$S$6,$W$5:$W$6,3)+SUMIFS($S$10:$S$22,$W$10:$W$22,3,$X$10:$X$22,1) | M19: =SUMIFS($S$5:$S$6,$W$5:$W$6,4)+SUMIFS($S$10:$S$22,$W$10:$W$22,4,$X$10:$X$22,1) | N19: =SUMIFS($S$5:$S$6,$W$5:$W$6,5)+SUMIFS($S$10:$S$22,$W$10:$W$22,5,$X$10:$X$22,1) | O19: =SUMIFS($S$5:$S$6,$W$5:$W$6,6)+SUMIFS($S$10:$S$22,$W$10:$W$22,6,$X$10:$X$22,1) | R19: Fairview | S19: 150 | U19: Bear only | V19: =IFERROR(VALUE(RIGHT(T19,4))*4+MATCH(LEFT(T19,2),{"Q1","Q2","Q3","Q4"},0)-1,"") | W19: =IF(V19="","",IF(V19<=$Z$1,0,MAX(1,INT((V19-$Z$2)/4)+1))) | X19: =IF(U19="All",1,IF(U19="Bear+Base",IF($Z$3>=2,1,0),IF(U19="Bear only",IF($Z$3>=3,1,0),0)))
B20: ABSORPTION (5-mi) | C20: 1334 | D20: 1532 | E20: 736 | F20: 44 | G20: 852 | H20: 1144 | I20: 585 | J20: =J31-I31 | K20: =K31-J31 | L20: =L31-K31 | M20: =M31-L31 | N20: =N31-M31 | O20: =O31-N31 | R20: Ascent Overland | S20: 138 | T20: Q1 2029 | U20: Bear only | V20: =IFERROR(VALUE(RIGHT(T20,4))*4+MATCH(LEFT(T20,2),{"Q1","Q2","Q3","Q4"},0)-1,"") | W20: =IF(V20="","",IF(V20<=$Z$1,0,MAX(1,INT((V20-$Z$2)/4)+1))) | X20: =IF(U20="All",1,IF(U20="Bear+Base",IF($Z$3>=2,1,0),IF(U20="Bear only",IF($Z$3>=3,1,0),0)))
B21: OCCUPANCY (5-mi) | C21: 0.935 | D21: 0.94 | E21: 0.953 | F21: 0.865 | G21: 0.861 | H21: 0.914 | I21: =IFERROR(I31/I30,"") | J21: =IFERROR(J31/J30,0) | K21: =IFERROR(K31/K30,0) | L21: =IFERROR(L31/L30,0) | M21: =IFERROR(M31/M30,0) | N21: =IFERROR(N31/N30,0) | O21: =IFERROR(O31/O30,0) | R21: The Cole Denton | S21: 136 | U21: Bear only | V21: =IFERROR(VALUE(RIGHT(T21,4))*4+MATCH(LEFT(T21,2),{"Q1","Q2","Q3","Q4"},0)-1,"") | W21: =IF(V21="","",IF(V21<=$Z$1,0,MAX(1,INT((V21-$Z$2)/4)+1))) | X21: =IF(U21="All",1,IF(U21="Bear+Base",IF($Z$3>=2,1,0),IF(U21="Bear only",IF($Z$3>=3,1,0),0)))
B22: SUBJECT (Seasons at Meridian) | R22: Meridian OZ Apartments | S22: 60 | U22: Bear only | V22: =IFERROR(VALUE(RIGHT(T22,4))*4+MATCH(LEFT(T22,2),{"Q1","Q2","Q3","Q4"},0)-1,"") | W22: =IF(V22="","",IF(V22<=$Z$1,0,MAX(1,INT((V22-$Z$2)/4)+1))) | X22: =IF(U22="All",1,IF(U22="Bear+Base",IF($Z$3>=2,1,0),IF(U22="Bear only",IF($Z$3>=3,1,0),0)))
B23: Market Rent (CoStar→HD) | C23: 1660 | D23: 1703 | E23: 1759 | F23: 1802 | G23: 1835 | H23: 1777 | I23: =IFERROR('Cash Flow (Annual)'!$F$4,1735) | J23: =IFERROR('Cash Flow (Annual)'!$K$4,"") | K23: =IFERROR('Cash Flow (Annual)'!$L$4,"") | L23: =IFERROR('Cash Flow (Annual)'!$M$4,"") | M23: =IFERROR('Cash Flow (Annual)'!$N$4,"") | N23: =IFERROR('Cash Flow (Annual)'!$O$4,"") | O23: =IFERROR('Cash Flow (Annual)'!$P$4,"")
B24: Market Rent YoY % | D24: =IFERROR(D23/C23-1,"") | E24: =IFERROR(E23/D23-1,"") | F24: =IFERROR(F23/E23-1,"") | G24: =IFERROR(G23/F23-1,"") | H24: =IFERROR(H23/G23-1,"") | I24: =IFERROR(I23/H23-1,"") | J24: =IFERROR(J23/I23-1,"") | K24: =IFERROR(K23/J23-1,"") | ... O24: =IFERROR(O23/N23-1,"")
B25: Effective Rent | C25: 1643 | D25: 1691 | E25: 1742 | F25: 1785 | G25: 1835 | H25: 1619 | I25: =IFERROR('Cash Flow (Annual)'!$F$5,1578) | J25: =IFERROR('Cash Flow (Annual)'!$K$5,"") | K25: =IFERROR('Cash Flow (Annual)'!$L$5,"") | L25: =IFERROR('Cash Flow (Annual)'!$M$5,"") | M25: =IFERROR('Cash Flow (Annual)'!$N$5,"") | N25: =IFERROR('Cash Flow (Annual)'!$O$5,"") | O25: =IFERROR('Cash Flow (Annual)'!$P$5,"")
B26: Effective Rent YoY % | D26: =IFERROR(D25/C25-1,"") | E26: =IFERROR(E25/D25-1,"") | F26: =IFERROR(F25/E25-1,"") | G26: =IFERROR(G25/F25-1,"") | H26: =IFERROR(H25/G25-1,"") | I26: =IFERROR(I25/H25-1,"") | J26: =IFERROR(J25/I25-1,"") | K26: =IFERROR(K25/J25-1,"") | ... O26: =IFERROR(O25/N25-1,"")
B27: Occupancy (financials / CoStar) | H27: 0.52394281 | I27: =IFERROR('Cash Flow (Annual)'!$F$14,0.8290265063352064) | J27: =IFERROR('Cash Flow (Annual)'!$K$14,"") | K27: =IFERROR('Cash Flow (Annual)'!$L$14,"") | L27: =IFERROR('Cash Flow (Annual)'!$M$14,"") | M27: =IFERROR('Cash Flow (Annual)'!$N$14,"") | N27: =IFERROR('Cash Flow (Annual)'!$O$14,"") | O27: =IFERROR('Cash Flow (Annual)'!$P$14,"")
B28: Concession % | C28: =IFERROR((C23-C25)/C23,"") | D28: =IFERROR((D23-D25)/D23,"") | E28: =IFERROR((E23-E25)/E23,"") | F28: =IFERROR((F23-F25)/F23,"") | G28: =IFERROR((G23-G25)/G23,"") | H28: =IFERROR((H23-H25)/H23,"") | I28: =IFERROR((I23-I25)/I23,"") | J28: =IFERROR((J23-J25)/J23,"") | ... O28: =IFERROR((O23-O25)/O23,"")
B30: inventory | C30: 9402 | D30: 10977 | E30: 11606 | F30: 12838 | G30: 13887 | H30: 14337 | I30: =H30+I19 | J30: =I30+J19 | K30: =J30+K19 | L30: =K30+L19 | M30: =L30+M19 | N30: =M30+N19 | O30: =N30+O19
B31: occupied | C31: 8789 | D31: 10320 | E31: 11057 | F31: 11105 | G31: 11956 | H31: 13099 | I31: =H31+I20 | J31: =MIN($C$6*J30,I31+$C$11) | K31: =MIN($C$6*K30,J31+$C$11) | L31: =MIN($C$6*L30,K31+$C$11) | M31: =MIN($C$6*M30,L31+$C$11) | N31: =MIN($C$6*N30,M31+$C$11) | O31: =MIN($C$6*O30,N31+$C$11)
B33: MARKET-RENT GROWTH — TMG vs 3RD-PARTY FORECAST | J33: Y1 | K33: Y2 | L33: Y3 | M33: Y4 | N33: Y5 | O33: Y6 | P33: AVG
B34: CoStar | J34: =IFERROR('Rent & Occ Data'!$C$31,"") | K34: =IFERROR('Rent & Occ Data'!$D$31,"") | L34: =IFERROR('Rent & Occ Data'!$E$31,"") | M34: =IFERROR('Rent & Occ Data'!$F$31,"") | N34: =IFERROR('Rent & Occ Data'!$G$31,"") | O34: =IFERROR('Rent & Occ Data'!$H$31,"") | P34: =IFERROR(AVERAGE(J34:O34),"")
B35: RealPage | J35: =IFERROR('Rent & Occ Data'!$C$32,"") | K35: =IFERROR('Rent & Occ Data'!$D$32,"") | L35: =IFERROR('Rent & Occ Data'!$E$32,"") | M35: =IFERROR('Rent & Occ Data'!$F$32,"") | N35: =IFERROR('Rent & Occ Data'!$G$32,"") | O35: =IFERROR('Rent & Occ Data'!$H$32,"") | P35: =IFERROR(AVERAGE(J35:O35),"")
B36: Yardi | J36: =IFERROR('Rent & Occ Data'!$C$33,"") | K36: =IFERROR('Rent & Occ Data'!$D$33,"") | L36: =IFERROR('Rent & Occ Data'!$E$33,"") | M36: =IFERROR('Rent & Occ Data'!$F$33,"") | N36: =IFERROR('Rent & Occ Data'!$G$33,"") | O36: =IFERROR('Rent & Occ Data'!$H$33,"") | P36: =IFERROR(AVERAGE(J36:O36),"")
B37: GreenStreet | J37: =IFERROR('Rent & Occ Data'!$C$34,"") | K37: =IFERROR('Rent & Occ Data'!$D$34,"") | L37: =IFERROR('Rent & Occ Data'!$E$34,"") | M37: =IFERROR('Rent & Occ Data'!$F$34,"") | N37: =IFERROR('Rent & Occ Data'!$G$34,"") | O37: =IFERROR('Rent & Occ Data'!$H$34,"") | P37: =IFERROR(AVERAGE(J37:O37),"")
B38: Consensus (4-source avg) | J38: =IFERROR(AVERAGE(J34:J37),"") | K38: =IFERROR(AVERAGE(K34:K37),"") | L38: =IFERROR(AVERAGE(L34:L37),"") | M38: =IFERROR(AVERAGE(M34:M37),"") | N38: =IFERROR(AVERAGE(N34:N37),"") | O38: =IFERROR(AVERAGE(O34:O37),"") | P38: =IFERROR(AVERAGE(P34:P37),"")
B39: TMG — our market-rent growth ◄ | J39: =IFERROR(J24,"") | K39: =IFERROR(K24,"") | L39: =IFERROR(L24,"") | M39: =IFERROR(M24,"") | N39: =IFERROR(N24,"") | O39: =IFERROR(O24,"") | P39: =IFERROR(AVERAGE(J39:O39),"")
B41: ▸ SCENARIO INPUTS — Bear / Base / Bull (implied occupancy, rent-growth & concession assumptions — click + to expand)
B42: IMPLIED 5-MI OCCUPANCY BY DEMAND SCENARIO | J42: Y1 | K42: Y2 | L42: Y3 | M42: Y4 | N42: Y5 | O42: Y6
B43: Bear | J43: =MIN($C$6,($I$31+$C$8*1)/J30) | K43: =MIN($C$6,($I$31+$C$8*2)/K30) | L43: =MIN($C$6,($I$31+$C$8*3)/L30) | M43: =MIN($C$6,($I$31+$C$8*4)/M30) | N43: =MIN($C$6,($I$31+$C$8*5)/N30) | O43: =MIN($C$6,($I$31+$C$8*6)/O30)
B44: Base | J44: =MIN($C$6,($I$31+$C$9*1)/J30) | K44: =MIN($C$6,($I$31+$C$9*2)/K30) | L44: =MIN($C$6,($I$31+$C$9*3)/L30) | M44: =MIN($C$6,($I$31+$C$9*4)/M30) | N44: =MIN($C$6,($I$31+$C$9*5)/N30) | O44: =MIN($C$6,($I$31+$C$9*6)/O30)
B45: Bull | J45: =MIN($C$6,($I$31+$C$10*1)/J30) | K45: =MIN($C$6,($I$31+$C$10*2)/K30) | L45: =MIN($C$6,($I$31+$C$10*3)/L30) | M45: =MIN($C$6,($I$31+$C$10*4)/M30) | N45: =MIN($C$6,($I$31+$C$10*5)/N30) | O45: =MIN($C$6,($I$31+$C$10*6)/O30)
B47: MARKET RENT GROWTH (editable assumptions) | J47: Y1 | K47: Y2 | L47: Y3 | M47: Y4 | N47: Y5 | O47: Y6
B48: Bear | J48: -0.0025 | K48: 0.0175 | L48: 0.0275 | M48: 0.0375 | N48: 0.0275 | O48: 0.0175
B49: Base | J49: 0.01 | K49: 0.03 | L49: 0.04 | M49: 0.05 | N49: 0.04 | O49: 0.03
B50: Bull | J50: 0.02 | K50: 0.04 | L50: 0.05 | M50: 0.06 | N50: 0.05 | O50: 0.04
B51: CONCESSIONS % — forward assumption (editable)
B52: Bear | J52: 0.06 | K52: 0.045 | L52: 0.035 | M52: 0.035 | N52: 0.035 | O52: 0.035
B53: Base | J53: 0.03 | K53: 0.015 | L53: 0.005 | M53: 0.005 | N53: 0.005 | O53: 0.005
B54: Bull | J54: 0.02 | K54: 0.005 | L54: 0 | M54: 0 | N54: 0 | O54: 0
B55: EFFECTIVE RENT GROWTH (derived)
B56: Bear | J56: =(1+J48)*(1-J52)-1 | K56: =(1+K48)*(1-K52)/(1-J52)-1 | L56: =(1+L48)*(1-L52)/(1-K52)-1 | M56: =(1+M48)*(1-M52)/(1-L52)-1 | N56: =(1+N48)*(1-N52)/(1-M52)-1 | O56: =(1+O48)*(1-O52)/(1-N52)-1
B57: Base | J57: =(1+J49)*(1-J53)-1 | K57: =(1+K49)*(1-K53)/(1-J53)-1 | L57: =(1+L49)*(1-L53)/(1-K53)-1 | M57: =(1+M49)*(1-M53)/(1-L53)-1 | N57: =(1+N49)*(1-N53)/(1-M53)-1 | O57: =(1+O49)*(1-O53)/(1-N53)-1
B58: Bull | J58: =(1+J50)*(1-J54)-1 | K58: =(1+K50)*(1-K54)/(1-J54)-1 | L58: =(1+L50)*(1-L54)/(1-K54)-1 | M58: =(1+M50)*(1-M54)/(1-L54)-1 | N58: =(1+N50)*(1-N54)/(1-M54)-1 | O58: =(1+O50)*(1-O54)/(1-N54)-1
B60: ▸ DETAIL: subject rent source by year, delivered-units tie-out & reconciliation (grouped — click + to expand)
B61: -Y6 Q3 2019–Q2 2020 | E61: CoStar
B62: -Y5 Q3 2020–Q2 2021 | E62: CoStar
B63: -Y4 Q3 2021–Q2 2022 | E63: CoStar
B64: -Y3 Q3 2022–Q2 2023 | E64: CoStar
B65: -Y2 Q3 2023–Q2 2024 | E65: CoStar
B66: -Y1 Q3 2024–Q2 2025 | E66: HD
B67: Y0 Q3 2025–Q2 2026 | E67: HD
B68: UC scheduled vs CoStar UC | E68: 716 / 552
B69: Delivered units — roster vs CoStar 5-mi series:
B70: -Y4: roster (CoStar-tracked) 275 vs CoStar 629 (+354 sub-50/unnamed; roster also carries +476 RealPage-only supply CoStar misses)
B71: -Y3: roster (CoStar-tracked) 1,214 vs CoStar 1,232 (+18 sub-50/unnamed)
B72: -Y2: roster (CoStar-tracked) 1,039 vs CoStar 1,049 (+10 sub-50/unnamed)
B73: -Y1: roster (CoStar-tracked) 90 + subj 360 vs CoStar 450 (tie ✓)
B74: Y0: roster (CoStar-tracked) 156 vs CoStar 156 (tie ✓; roster also carries +84 RealPage-only supply CoStar misses)
B75: Newest CoStar row (2026 Q3 QTD) is partial (QTD) — excluded from TTM sums; Y0 anchors to the latest complete quarter.

Sheet Reconciliation Log
A1: Property | B1: Address | C1: Units | D1: Year Built | E1: Est. Delivery | F1: Deliv. Source | G1: Bucket | H1: CoStar Occ | I1: RealPage Occ | J1: HD Occ | K1: CoStar Ask Rent | L1: RealPage Eff Rent | M1: HD Ask (mix-wtd) | N1: HD Eff (mix-wtd) | O1: Sources | P1: Notes
A2: Springtree Apartments | B2: 121 S Springtree Ln | C2: 42 | D2: 2024 | E2: Q4 2024 | F2: CoStar property analytics | G2: STABILIZED / STABILIZING | H2: 0.952381 | K2: 1514 | O2: CoStar
A3: The Aren | B3: 1066 S Silverstone Way | C3: 396 | D3: 2024 | E3: Q2 2024 | F3: CoStar property analytics | G3: STABILIZED / STABILIZING | H3: 0.969697 | I3: 0.998 | K3: 1762 | L3: 1841 | M3: 1739.209 | N3: 1663.8122 | O3: CoStar+RealPage | P3: Year built: 2024/2025; Occ: CoStar 97% vs RealPage 100%
A4: Viera at Pinnacle | B4: 6269 S Aspiration Ave | C4: 56 | D4: 2024 | E4: Q1 2024 | F4: CoStar property analytics | G4: STABILIZED / STABILIZING | H4: 1 | K4: 2595 | M4: 2489.375 | N4: 2395.8958 | O4: CoStar
A5: Movado Village | B5: 1711 S Movado Way | C5: 60 | D5: 2024 | E5: Q1 2024 | F5: CoStar property analytics | G5: STABILIZED / STABILIZING | H5: 0.933333 | K5: 2070 | M5: 1995 | N5: 1995 | O5: CoStar
A6: Telluride | B6: 597 N Maple Grove Rd | C6: 102 | D6: 2023 | E6: Q2 2023 | F6: CoStar property analytics | G6: STABILIZED / STABILIZING | H6: 0.990196 | K6: 1898 | M6: 1884.4468 | N6: 1884.4468 | O6: CoStar
A7: Altair | B7: 2743 W Peak Cloud Ln | C7: 240 | D7: 2023 | E7: Q2 2023 | F7: CoStar property analytics | G7: STABILIZED / STABILIZING | H7: 0.945833 | I7: 0.996 | K7: 1689 | L7: 1754 | M7: 1624.4078 | N7: 1573.1923 | O7: CoStar+RealPage | P7: Occ: CoStar 95% vs RealPage 100%
A8: Dovetail | B8: 1350 N Webb Way | C8: 240 | D8: 2023 | E8: Q2 2023 | F8: CoStar property analytics | G8: STABILIZED / STABILIZING | H8: 0.958333 | I8: 0.992 | K8: 1832 | L8: 1856 | O8: CoStar+RealPage | P8: Units: CoStar 240 vs RealPage 480; Year built: 2020/2023; Occ: CoStar 96% vs RealPage 99%
A9: Yellowstone Apartments | B9: 3500 West Pine Avenue | C9: 216 | D9: 2023 | E9: Q2 2023 | F9: CoStar property analytics | G9: STABILIZED / STABILIZING | H9: 0.763889 | I9: 0.944 | K9: 1707 | L9: 1691 | M9: 1735.4694 | N9: 1735.4694 | O9: CoStar+RealPage | P9: Year built: 2023/2025; Occ: CoStar 76% vs RealPage 94%
A10: Alante Homes at Hazelwood | B10: 6222 S Gloriosa Ln | C10: 32 | D10: 2023 | E10: Q1 2023 | F10: CoStar property analytics | G10: STABILIZED / STABILIZING | H10: 0.96875 | K10: 2276 | O10: CoStar
A11: Modern Craftsman Ten Mile | B11: 3233 W Littleton Ln | C11: 135 | D11: 2023 | E11: Q1 2023 | F11: CoStar property analytics | G11: STABILIZED / STABILIZING | H11: 0.948148 | I11: 0.993 | K11: 2229 | L11: 2243 | M11: 2164.3198 | N11: 2140.342 | O11: CoStar+RealPage | P11: Year built: 2022/2023; Occ: CoStar 95% vs RealPage 99%
A12: WaterWalk Boise – Meridian | B12: 88 n Olson Ave | C12: 38 | D12: 2023 | E12: Q1 2023 | F12: CoStar property analytics | G12: STABILIZED / STABILIZING | H12: 0.947368 | K12: 1655 | O12: CoStar
A13: The Prospect | B13: 8002 W Overland Rd | C13: 91 | D13: 2022 | E13: Q4 2022 | F13: CoStar property analytics | G13: STABILIZED / STABILIZING | H13: 0.989011 | K13: 1189 | M13: 1165.5556 | N13: 1156.3266 | O13: CoStar
A14: Etheridge Lane | B14: 1428 N Etheridge Ln | C14: 12 | D14: 2022 | E14: Q4 2022 | F14: CoStar property analytics | G14: STABILIZED / STABILIZING | O14: CoStar
A15: Old Town Lofts | B15: 33 E Idaho Ave | C15: 102 | D15: 2022 | E15: Q3 2022 | F15: CoStar property analytics | G15: STABILIZED / STABILIZING | H15: 0.990196 | I15: 0.99 | K15: 1683 | L15: 1661 | M15: 1665.5116 | N15: 1665.5116 | O15: CoStar+RealPage | P15: Year built: 2022/2023
A16: Lavender Village | B16: 2607-2615 N Linda Vista Ln | C16: 6 | D16: 2022 | E16: Q3 2022 | F16: CoStar property analytics | G16: STABILIZED / STABILIZING | K16: 2110 | M16: 1747.5137 | N16: 1747.5137 | O16: CoStar | P16: Rent: HD mix-wtd $1,748 vs CoStar ask $2,110
A17: Meritage West | B17: 13450 W Baldcypress St | C17: 83 | D17: 2022 | E17: Q2 2022 | F17: CoStar property analytics | G17: STABILIZED / STABILIZING | H17: 0.987952 | I17: 0.976 | K17: 1664 | L17: 1641 | M17: 1651.435 | N17: 1651.435 | O17: CoStar+RealPage
A18: Celebration Acres | B18: 10881 W Florence Dr | C18: 28 | D18: 2022 | E18: Q2 2022 | F18: CoStar property analytics | G18: STABILIZED / STABILIZING | H18: 0.964286 | O18: CoStar
A19: Ambleside Townhomes | B19: 1890 N Shamrock Ave | C19: 67 | D19: 2022 | E19: Q2 2022 | F19: CoStar property analytics | G19: STABILIZED / STABILIZING | H19: 0.970149 | K19: 2130 | O19: CoStar
A20: Pine 43 | B20: 1301 N Meadowglen Ave | C20: 25 | D20: 2022 | E20: Q2 2022 | F20: CoStar property analytics | G20: STABILIZED / STABILIZING | K20: 2236 | O20: CoStar
A21: South Ridge I | B21: 1703 S Grand Frk Wy | C21: 476 | D21: 2022 | E21: Q2 2022 | G21: STABILIZED / STABILIZING | I21: 0.994 | L21: 1672 | O21: RealPage | P21: Delivery quarter estimated; RealPage-only — not in CoStar's 5-mi series
A22: The Lost Rapid Townhomes | B22: 3400 W Chinden Blvd | C22: 72 | D22: 2022 | E22: Q1 2022 | F22: CoStar property analytics | G22: STABILIZED / STABILIZING | H22: 0.944444 | O22: CoStar
A23: Tauri Apartments | B23: 12673 W Ashcreek St | C23: 156 | D23: 2026 | E23: Q2 2026 | F23: CoStar property analytics | G23: LEASING UP | H23: 0.25 | I23: 0.18 | J23: 1 | K23: 1862 | L23: 1684 | M23: 1833.7261 | N23: 1813.1546 | O23: CoStar+RealPage | P23: Units: CoStar 156 vs RealPage 128; Year built: 2026/2027; Occ: CoStar 25% vs RealPage 18%; Rent: CoStar ask $1,862 vs RealPage eff $1,684; Occ: HD ~100% (CoStar/RP showed 25%); HD (90d): occ ~100% (units leased), ~20 leases/mo
A24: Delano | B24: 3858 N Centrepoint Way | C24: 84 | D24: 2026 | E24: Q2 2026 | G24: LEASING UP | I24: 0.452 | L24: 1491 | O24: RealPage | P24: Delivery quarter estimated; Verify rent/occ w/ HelloData; RealPage-only — not in CoStar's 5-mi series
A25: Shamrock Apartments | B25: 1590 N Shamrock St | C25: 48 | D25: 2025 | E25: Q2 2025 | F25: CoStar property analytics | G25: LEASING UP | H25: 0.833333 | O25: CoStar | P25: Verify rent/occ w/ HelloData
A26: Village Apartments | B26: 2651 N Records Ave | C26: 336 | D26: 2024 | E26: Q2 2024 | F26: CoStar property analytics | G26: LEASING UP | H26: 0.803571 | I26: 0.113 | J26: 0.11904762 | K26: 1742 | L26: 1677 | M26: 1747.5137 | N26: 1747.5137 | O26: CoStar+RealPage | P26: Occ: CoStar 80% vs RealPage 11%; Occ: HD ~12% (CoStar/RP showed 80%); HD (90d): occ ~12% (units leased), ~13 leases/mo
A27: Wesley Apartments and Townhomes | B27: 3104 N Venable Ln | C27: 191 | D27: 2024 | E27: Q2 2024 | F27: CoStar property analytics | G27: LEASING UP | H27: 0.277487 | I27: 0.838 | J27: 0.47643979 | K27: 1716 | L27: 2004 | M27: 1994.4847 | N27: 1994.4847 | O27: CoStar+RealPage | P27: Occ: CoStar 28% vs RealPage 84%; Rent: CoStar ask $1,716 vs RealPage eff $2,004; Rent: HD mix-wtd $1,994 vs CoStar ask $1,716; Occ: HD ~48% (CoStar/RP showed 28%); HD (90d): occ ~48% (units leased), ~22 leases/mo
A28: Vanguard Village | B28: 1085 S 10 Mile Rd | C28: 552 | D28: 2027 | E28: Q1 2028 | G28: UNDER CONSTRUCTION | M28: 1747.5137 | N28: 1747.5137 | O28: CoStar
A29: South Ridge II | B29: 1703 S Grand Frk Wy | C29: 164 | D29: 2027 | E29: Q2 2027 | G29: UNDER CONSTRUCTION | O29: RealPage
A30: Ascent Overland | B30: 11101 W Overland Rd | C30: 138 | D30: 2028 | E30: Q1 2029 | G30: PROPOSED | O30: CoStar | P30: Diligence: proposed
A31: The Gateway at Ten Mile | B31: 2954 W Franklin Rd | C31: 390 | D31: 2027 | E31: Q4 2028 | G31: PROPOSED | O31: CoStar | P31: Diligence: proposed
A32: Victory Flats | B32: 8373 West Victory Rd | C32: 301 | D32: 2027 | E32: Q3 2028 | G32: PROPOSED | O32: CoStar+RealPage | P32: Diligence: proposed
A33: The Judy (Maple Grove & Overland) | B33: 1770 S Maple Grove Rd, Boise 83704 | C33: 162 | E33: Q1 2028 | G33: PROPOSED | O33: Diligence | P33: Analyst-sourced deal (not in CoStar/RealPage); Diligence: proposed - equity raise underway; construction targeted Q3 2026
A34: Union 93 | B34: 221-225 E Broadway Ave | C34: 350 | D34: 2026 | E34: Q3 2026 | G34: PROPOSED | O34: CoStar+RealPage | P34: Diligence: stalled - foreclosure since Nov 2022; no restart as of Jul 2026
A35: Meridian OZ Apartments | B35: 1475 E Franklin Rd | C35: 60 | G35: PROPOSED | O35: CoStar+RealPage | P35: Diligence: proposed
A36: The Cole Denton | B36: 580 N Cole Rd | C36: 136 | G36: PROPOSED | O36: RealPage | P36: RealPage pipeline (not yet in CoStar); Diligence: proposed
A37: Record | B37: E Fairview Ave & N Records Way | C37: 472 | G37: PROPOSED | O37: RealPage | P37: RealPage pipeline (not yet in CoStar); Diligence: proposed
A38: Cobalt Point | B38: S Cobalt Point Way & E Copper Point Dr | C38: 264 | G38: PROPOSED | O38: RealPage | P38: RealPage pipeline (not yet in CoStar); Diligence: proposed
A39: Fairview | B39: 1005 E Fairview Ave | C39: 150 | G39: PROPOSED | M39: 1837.581 | N39: 1837.581 | O39: RealPage | P39: RealPage pipeline (not yet in CoStar); Diligence: proposed
A40: 12548 West Overland Road | B40: 12548 W Overland Rd | C40: 156 | G40: PROPOSED | O40: RealPage | P40: RealPage pipeline (not yet in CoStar); Diligence: proposed
A41: 12565 West Fairview Avenue | B41: 12565 W Fairview Ave | C41: 275 | G41: PROPOSED | O41: RealPage | P41: RealPage pipeline (not yet in CoStar); Diligence: proposed
A42: Syringa Crossing | B42: Amity Ave & Meridian Rd | C42: 322 | G42: PROPOSED | O42: RealPage | P42: RealPage pipeline (not yet in CoStar); Diligence: proposed

Sheet Diligence
B2: PIPELINE DILIGENCE
B3: Property / Site | C3: Units | D3: Est. Delivery | E3: Status | F3: Leasing Pace | G3: Notes | H3: Source
B4: The 10 | E4: withdrawn - superseded by The Gateway at Ten Mile | G4: Original 559-unit 'The 10' (Elk Ventures, 2021) never proceeded; the site was re-entitled as The Gateway at Ten Mile (H-2024-0010) for 390 units, approved Nov 2024. Removed to avoid double-counting the same site as two deals — the Gateway row carries the live entitlement. | H4: https://boisedev.com/news/2024/11/20/the-gateway-at-10-mile-meridian/
B5: Record | C5: 472 | E5: proposed | G5: Brighton Corporation's 'Records': 472 urban-style units (84 studio/208 1BR/168 2BR/12 3BR) on ~10 ac at the NE corner of Fairview Ave & Records Way adjacent to CarMax, proposed Feb 2022, two phases; Brighton's leasing site lists it 'coming soon' but no construction start could be independently confirmed. | H5: https://www.brighton.co/brighton-place/records-way-the-village-at-meridian/
B6: Centrepoint | E6: withdrawn - entitlements terminated (financing) | G6: A 2024 CUP/DA modification approved a 239-unit deed-restricted affordable/workforce development at Centrepoint Way near Eagle & Ustick (earlier iterations 215-295 units), but per the Meridian staff report the applicant terminated entitlements and withdrew due to state-level financing complications — dead. Its parcel (S1105110111) reverts to latent land-use supply. | H6: https://boisedev.com/news/2024/05/30/centrepoint-apartments-meridian-village/
B7: Cobalt Point | C7: 264 | E7: proposed | G7: 264 units on ~13 ac east of E Copper Point Dr & S Cobalt Point Way (Silverstone Park area near Eagle/Overland — NOT Ten Mile Crossing as RealPage implies), application prepared by The Land Group (BoiseDev June 2022); a marketing domain is indexed but the current stage could not be verified. | H7: https://boisedev.com/news/2022/06/13/cobalt-point-meridian/
B8: Madison Town Square | E8: dead - plan pulled June 2024; site for sale | G8: Madison Capital Group (MCG Boise Owner LLC) bought the old Sears at 460 N Milwaukee in 2021 and proposed 251 units, but pulled its design-review request and the plan was reported dead June 2024; site listed for sale at $8M (later $7.5M), still unsold. | H8: https://boisedev.com/news/2024/06/04/boise-sears-sale/
B9: Syringa Crossing | C9: 322 | E9: proposed | G9: Hawkins Companies' plan at Amity & Meridian Rd is still in hearings: P&Z recommended denial April 2026, and on June 17 2026 City Council unanimously remanded the revised plan (more office/retail, fewer homes) back to P&Z — no final approval; the 322-unit count may shrink. Bear-case supply only. Land-use dossier SM-12 covers the adjacent block. | H9: https://boisedev.com/news/2026/06/17/a-developer-made-changes-to-a-proposed-400-home-mixed-use-project-meridian-gives-commission-another-vote-on-it/
B10: The Cole Denton | C10: 136 | E10: proposed | G10: 136-unit five-story mixed-use (retail/self-storage/apartments) approved May 2021 as Boise's first Housing Bonus Ordinance project; the building permit submitted Sept 2022 was still 'in corrections' Jan 2023 and the 2.13-ac site is now listed for sale — stalled. Distinct from the delivered 191-unit Denton Apartments (Pacific Companies, Curtis Rd, opened Dec 2025). | H10: https://boisedev.com/news/2021/05/04/five-story-apartment-building-coming-to-lot-across-from-boise-town-square/
B11: 12565 West Fairview Avenue | C11: 275 | E11: proposed | G11: 275 units in 4-5 story buildings over a ground-floor garage proposed on the 4.7-ac stalled AutoNation USA dealership site (AutoNation still owner; PivotNorth architect); early application / neighborhood-meeting stage per April 2025 reporting — no approval, permit, or construction as of July 2026. Sits on land-use developable parcel S1109110516. | H11: https://boisedev.com/news/2025/04/23/boise-fairview-apartments/
B12: 12548 West Overland Road | C12: 156 | E12: proposed | G12: Hook Family Trust (San Clemente CA) won PUD approval ~March 2024 to replace Overland RV Storage with five 4-story buildings, 156 units (84 1BR/72 2BR) + ~6,000 sf retail; as of mid-2026 the RV storage still operates and the entitled site is marketed for sale on LoopNet — no construction start. | H12: https://boisedev.com/news/2023/11/29/hook-trust-boise/
B13: 10975 West Lake Hazel Road | E13: exclude - unverifiable / likely misidentified | G13: No development application found at this address (an 11.85-ac parcel with a 1994 single-family home per county records); the nearest real deal — PEG Companies' 118-unit proposal at Five Mile & Lake Hazel — was denied twice by Ada County commissioners (2022 and May 2024). RealPage entry cannot be tied to any live project. | H13: https://boisedev.com/news/2024/05/22/southwest-boise-commercial/
B14: Cole Road | E14: exclude - existing 1978-82 asset (76u Ridgeline Apartments); not new supply | G14: 709 N Cole Rd is the EXISTING 76-unit Ridgeline Apartments (built 1978-1982), marketed for sale by Berkadia — a misidentified pipeline entry; no evidence of any new 61-unit multifamily proposal or rezone at this address. | H14: https://properties.berkadia.com/cole-road-469858/
B15: Villas at Twelve Oaks East | E15: exclude - likely duplicate of existing built Twelve Oaks community | G15: Could not confirm a distinct 64-unit 'East' phase at 115 S Linder Rd; Meridian records show only ZV-2021-0055 'Twelve Oaks Apartments' and the existing CBH Twelve Oaks (~106u) is built and leasing — the RealPage entry likely duplicates or misidentifies it. | H15: https://weblink.meridiancity.org/WebLink/Browse.aspx?id=244917&dbid=0&repo=MeridianCity&cr=1
B16: Promenade Cottages I | E16: not multifamily - for-sale townhomes/cottages | G16: Per BuildIdaho and a City of Meridian site plan, Promenade Cottages at the SE corner of Fairview Ave & 3rd St (A-Team Consultants) is a 30-unit mix of FOR-SALE townhomes and single-family alley-load cottage homes — not a rental apartment community. | H16: https://www.buildidaho.com/meridian-homes-for-sale/promenade-cottages/
B17: Meridian OZ Apartments | C17: 60 | E17: proposed | G17: CUP H-2022-0073 (Realm Venture Group): 60 units (30x1BR + 30x2BR) in five 3-story 12-plexes at 1475 E Franklin Rd, SWC Franklin & Locust Grove; hearing record indicates the approval motion carried (early 2023) but no construction evidence found. Land-use dossier SM-155. | H17: https://boisedev.com/news/2023/01/23/meridian-oz-apartments/
B18: Union 93 | E18: stalled - foreclosure since Nov 2022; no restart as of Jul 2026 | G18: Galena Opportunity Fund's two-building ~385-unit Union 93 East/West at Main & Broadway (downtown Meridian) stalled Nov 2022 after contractors went unpaid; the project entered foreclosure amid litigation and no evidence shows construction resumed — CoStar's 'under construction / Q3 2026 delivery' is stale. Demoted to proposed (Bear-case toggle); monitor for a post-foreclosure restart. | H18: https://www.yahoo.com/news/ambitious-downtown-meridian-development-foreclosure-160323894.html
B19: Victory Flats | C19: 301 | E19: proposed | G19: Welltower's 301-unit apartment/townhome/SFR rental project at 8373 W Victory Rd (former Boise School District land, SW Boise) approved by Boise City Council March 8 2022 with first units once hoped for late 2023; no groundbreaking, permits, or leasing evidence through mid-2026 — CoStar's Q3 2028 delivery is unsupported. | H19: https://boisedev.com/news/2022/03/11/mix-of-hundreds-of-housing-units-approved-on-former-school-district-site-in-southwest-boise/
B20: The Hummingbird | E20: dead - approval expired spring 2025 | G20: Approved 2023 at 170 units (reworked from ~200) on the Aquarium of Boise site at Franklin & Cole (60 N Cole Rd); the two-year approval expired spring 2025 and the owner instead proposed an aquarium expansion on the site (Aug 2025) — CoStar's Q3 2028 delivery is not supported. | H20: https://boisedev.com/news/2025/08/18/aquarium-boise-expansion/
B21: The Gateway at Ten Mile | C21: 390 | E21: proposed | G21: Approved unanimously Nov 2024 (H-2024-0010): 390 units (200 1BR/174 2BR/16 3BR) in six 4-story buildings plus townhomes and 15 commercial buildings at Ten Mile & Franklin; the developer said commercial phases come first and residential is 5-7 years out — CoStar's Q4 2028 delivery looks optimistic. Supersedes the old 559-unit 'The 10' on the same site. | H21: https://boisedev.com/news/2024/11/20/the-gateway-at-10-mile-meridian/
B22: Ascent Overland | C22: 138 | E22: proposed | G22: MVRK Development (Denver) 138-unit two-building project near Overland & Cloverdale (West Boise, not Meridian) approved 5-1 by Boise City Council Nov 2023; MVRK's own projects page (July 2026) still lists planning-stage 'TBD' timing — no construction reported. | H22: https://boisedev.com/news/2023/11/15/boise-city-council-approves-overland-road-apartment-project-over-some-neighborhood-opposition/
B23: Fairview | C23: 150 | E23: proposed | G23: Biltmore Co. / Pivot North Architecture application (Jan 2023) for 150 market-rate units (1-3BR, 797-1,872 sf, 2-3 story buildings) at 1005 E Fairview Ave; still needs Meridian P&Z and City Council approval — no hearing date found, no construction. | H23: https://boisedev.com/news/2023/01/11/fairview-apartments-meridian/
B24: Promenade Cottages II | E24: not multifamily - for-sale townhomes/cottages (same community as Phase I) | G24: Phase II of the Promenade Cottages for-sale townhome/cottage community at Fairview & 3rd (A-Team Consultants) — same for-sale product as Phase I; not rental apartment supply. | H24: https://www.buildidaho.com/meridian-homes-for-sale/promenade-cottages/
B25: The Judy (Maple Grove & Overland) | C25: 162 | D25: Q1 2028 | E25: proposed - equity raise underway; construction targeted Q3 2026 | G25: Hawkins Companies OM (July 2026, research/oms/): 162-unit Class A garden (75x1BR $1,615 / 60x2BR / 27x3BR, avg $1,787 at 908sf) on 6.13 ac at 1770 S Maple Grove Rd, Boise — 3.4 mi from subject, inside the 5-mi ring. $41.7M TPC, GMP contract, construction targeted Q3 2026; OM lease-up: first occupancy month ~18 (=> ~Q1 2028 first units), 20 units/mo absorption, ~42% occupied Yr 2. NOT tracked by CoStar or RealPage. Land-use analysis site 177: parcel S1124223215 in the developable-vacant set but zoned R-2 (Medium MF-threat, conditional) with 'single-family oriented' FLU — the OM proves the conditional path being exercised; reclassify from latent to tracked pipeline. | H25: Hawkins Capital Markets OM — research/oms/Maple_Grove_Overland_Equity_Hawkins_OM.pdf
B27: SHADOW SUPPLY (latent / untracked — watch list)
B28: Property / Site | C28: Units | D28: Est. Delivery | E28: Status | F28: Leasing Pace | G28: Notes | H28: Source
B29: Emblem Meridian (Quarterra) / Artisan Victory Market site | C29: 250 | G29: Land-use analysis site SM-76: ~12-ac BPS Eagle Road LLC assemblage on S Eagle Rd. 'Artisan Victory Market' (H-2022-0066) approved 2023 for 131 build-to-rent units + commercial but never built; superseded by Quarterra's 'Emblem Meridian' ~250-unit concept (pre-application June 2026). Closest large latent MF site to the subject (~1 mi). | H29: https://boisedev.com/news/2026/06/10/meridian-emblem-victory-eagle-homes-apartment/
B30: Tanner Creek apartments (Waltman/Johnson Ln) | C30: 280 | G30: Land-use analysis site SM-15: Tanner Creek (heard Nov 2023; moved forward) — 83 SF homes + 45 townhomes + 280 phased apartments on ~38 ac, paired with ~30-ac Hawkins commercial between I-84 and Waltman Ln. Residential now being built by CBH Homes; the 280-unit apartment component is latent supply not yet in the CoStar/RealPage pipeline. | H30: https://boisedev.com/news/2023/11/28/plans-for-two-large-developments-off-i-84-and-meridian-rd-move-forward/
B31: Graycliff Estates R-40 block | C31: 224 | G31: Land-use analysis site SM-3: Graycliff Estates (Star Development) approved preliminary plat of ~200 SF homes PLUS 224 apartments (R-40 high-density block) on ~52 ac; SF portion building since 2021. The 224-unit apartment block remains unbuilt latent supply. | H31: https://www.weknowboise.com/graycliff-estates.php
B32: Touchmark Meadow Lake Village expansion | G32: Land-use analysis site SM-9: ~64 undeveloped ac of Touchmark's ~121-ac senior community. July 2025 development-modification agreement + rezone + PUD in progress to a broader 'Touchmark Mixed Use' (mixed housing types). Senior-oriented, but adds rental housing capacity 1.5 mi from subject. | H32: https://boisedev.com/news/2025/07/14/touchmark-meridian-meadowlake-mixed-use/
B33: Ten Mile Crossing residual HDR parcels | G33: Land-use analysis site SM-4: residential portion (R-15/R-8) of Brighton's Ten Mile Crossing at SW Overland & Ten Mile — partially built (Cortland South Meridian + CBH SF); remaining High-Density Residential parcels planned/dormant, including an 8.6-ac and a 14.4-ac R-15 vacant parcel (highest-interest sites in the land-use ranking). Note: South Ridge II (164u UC, tracked in the chart) is rising in this same corridor. | H33: https://www.brighton.co/brighton-place/ten-mile-crossing/
B34: Brighton Apex R-15 parcel (Lake Hazel) | G34: Land-use analysis site SM-61: 15.1-ac R-15 (med-high-density) parcel on E Lake Hazel Rd inside Brighton's approved Apex/Pinnacle master-plan footprint; adjacent phases actively building. Latent MF-capable ground in the fast-growing S Meridian corridor. | H34: https://boisedev.com/news/2024/12/20/brighton-pinnacle-costco-meridian/
B35: Outer Banks Subdivision (TM Creek / Cobalt Dr) | G35: Land-use analysis site SM-1: Ten Mile/I-84 high-density employment/mixed-use core (TMISAP) with heavy MF already delivered (Flats/Lofts/Cortland at Ten Mile). Outer Banks Subdivision approved 2021; balance of the ~198-ac district planned — further MF phases likely alongside the tracked pipeline. | H35: https://boisedev.com/news/2021/12/17/outer-banks-pera-place/
