Workbook

Sheet READ ME
A1: Canyon Ridge vs Seasons at Meridian — Demographics, Employer & Micron-Exposure Comparison
A3: Prepared | B3: July 20, 2026
A4: Purpose | B4: Apples-to-apples comparison of the two live deals across tenant quality, employer diversification, and Micron exposure, using the same T1–T6 framework as the Canyon Ridge Employer / Micron Analysis (2026.06.24).
A6: SOURCES
A7: Canyon Ridge | B7: Entrata "Resident Data 3.0" as of 06/24/2026 (Primary + Co-Applicant; statuses Future/Current/Notice) · standardized employers/tiers from Canyon Ridge Employer & Micron Analysis (2026.06.24) · move-in timeline from Canyon Ridge Rent Roll Cross-Analysis (2026.06.24). 287 units; 2552 E Gowen Rd, Boise — adjacent to Micron HQ/Triton fab campus.
A8: Seasons at Meridian | B8: Seller "Demographics Report w/Roommates" 07/10/2026 (Yardi; Status=Current) + "Rent Roll with Lease Charges" as of 07/09/2026. 360 units; Meridian, ID (~20 mi from Micron campus).
A9: New work in this book | B9: All 375 raw Seasons employer spellings standardized to 304 canonical employers and classified T1–T6; ~45 ambiguous / Micron-plausible names individually web-researched (July 2026) — see Employers - Seasons & Name Map tabs. Industry coding added to both properties.
A11: TIER FRAMEWORK | B11: T1 = Micron direct · T2 = Micron construction subcontractor (fab build) · T3 = Micron engineering/design/consulting/IT-staffing · T4 = semiconductor equipment/tool/materials vendor serving Micron · T5 = other semiconductor/tech, NOT Micron-related · T6 = unrelated/local. "Micron-related broad" = T1+T2+T3+T4. Confidence scale follows the CR workbook (Confirmed / Strong-inferred / Inferred / Weak-inferred / Weak-unverified / Confirmed-NotMicron).
A12: Alignment notes | B12: Prime Controls and POWER Engineers appear at both properties; Seasons classifications were aligned to the CR workbook (both T3). ESI = Engineered Structures Inc. (Meridian HQ; ENR documents ESI building structures at Micron's Boise HQ campus) — classified T2 Confirmed.
A14: COUNTING RULES
A15: Occupant counting | B15: Occupant level, matching the CR workbook: CR = Primary + Co-Applicant (457 records). Seasons = Primary/Spouse/Roommate/Other, EXCLUDING the 29 Guarantors (604 unique people → 575 resident occupants). Seasons raw export duplicates a person once per pet — collapsed to one row per person.
A16: "Employed" | B16: Occupants with a classified employer. Retired / student / homemaker / alimony (Seasons: 10) and blanks (CR: 119 · Seasons: 122) are excluded from the employed denominator. Self-employed and gig workers count as employed.
A17: Income screens | B17: Seasons per-person incomes exclude: guarantors; $0/blank; 51 rows that are byte-for-byte copies of another occupant in the same unit (same DOB + same salary — children/roommates keyed in from the primary's record); 3 entries ≥$1M (corporate lease entered as a person at $2.49M; two probable monthly-as-annual entry errors). CR incomes used as stated (>0).
A18: Household income | B18: Sum of qualifying occupant incomes per unit. Rent coverage = household income ÷ (12 × contract rent). CR rent = Entrata scheduled rent; Seasons rent = "rentres" contract rent from the rent roll (excludes utility/parking/pet charges).
A19: Coverage gap | B19: Seasons demographics cover 305 of 342 occupied units — the 38 units on notice are absent from the seller export (Status=Current filter). CR data includes notice + future leases. Keep in mind when comparing churn.
A20: Coworker units | B20: Units with 2+ occupants sharing an employer, no spouse relationship, different surnames AND different DOBs (the DOB screen removes copied-record artifacts). CR figure (33) is from the CR cross-analysis workbook.
A22: CONVENTIONS | B22: Blue = value computed from source data in this analysis (medians, sourced counts). Green = linked from another tab. Black = formula on the same tab. Yellow highlight = Micron-related (T1–T4) rows.
A23: Caveats | B23: Employer text is self-reported at application; ~21-26% of occupants at both properties have no employer stated. Web-researched tier calls below "Confirmed" are trade-fit inferences, not documented contracts — see per-employer evidence and confidence columns before leaning on any single name. Income figures are unverified applicant statements.

Sheet Overview
A1: Canyon Ridge vs Seasons at Meridian — Tenant Demographics, Employer & Micron-Exposure Comparison
A2: Data as of: Canyon Ridge 06/24/2026 (Entrata) · Seasons 07/09–07/10/2026 (Yardi rent roll + seller demographics). Green = linked to detail tabs · Blue = computed from source data (see READ ME).
B4: Canyon Ridge | C4: Seasons at Meridian | D4: Comment
A5: PROPERTY SNAPSHOT
A6: Location | B6: 2552 E Gowen Rd, Boise (adjacent to Micron HQ / Triton fab campus) | C6: Meridian, ID (~20 mi W of Micron campus) | D6: Physical proximity to the fab is the root of the exposure difference
A7: Total units | B7: 287 | C7: 360
A8: Opened / first move-ins | B8: Sep-2024 | C8: Aug-2024 | D8: Both are 2024-opened lease-ups — same vintage cohort
A9: Occupied units | B9: ='Lease-Up & Churn'!B18 -> 286 | C9: ='Lease-Up & Churn'!C18 -> 342
A10: Physical occupancy | B10: ='Lease-Up & Churn'!B19 -> 0.99651568 | C10: ='Lease-Up & Churn'!C19 -> 0.95
A11: Units on notice | B11: ='Lease-Up & Churn'!B20 -> 24 | C11: ='Lease-Up & Churn'!C20 -> 38 | D11: CR 6/24/26; Seasons 7/9/26
A12: Notice % of occupied | B12: ='Lease-Up & Churn'!B21 -> 0.083916084 | C12: ='Lease-Up & Churn'!C21 -> 0.11111111
A13: Median contract rent | B13: 1975 | C13: 1714 | D13: Seasons contract ~11% below own asking/market (lease-up LTL)
A15: MICRON EXPOSURE — occupant level (% of employed residents)
A16: Employed occupants (classified T1–T6) | B16: ='Tier Summary'!C11 -> 337 | C16: ='Tier Summary'!E11 -> 443 | D16: Excl. guarantors, retirees, blanks
A17: Micron DIRECT (T1) | B17: ='Tier Summary'!D17 -> 0.26409496 | C17: ='Tier Summary'!F17 -> 0.020316027 | D17: CR: 89 residents · Seasons: 9
A18: Micron-related narrow (T1+T2) | B18: ='Tier Summary'!D18 -> 0.62611276 | C18: ='Tier Summary'!F18 -> 0.047404063
A19: Micron-related mid (T1+T2+T3) | B19: ='Tier Summary'!D19 -> 0.67655786 | C19: ='Tier Summary'!F19 -> 0.054176072
A20: Micron-related BROAD (T1–T4) | B20: ='Tier Summary'!D20 -> 0.71513353 | C20: ='Tier Summary'!F20 -> 0.063205418 | D20: The headline exposure gap: ~72% vs ~6%
A22: MICRON EXPOSURE — unit level (revenue at risk)
A23: Units with ≥1 Micron-related earner (T1–T4) | B23: ='Tier Summary'!D24 -> 0.6958042 | C23: ='Tier Summary'!F24 -> 0.078688525 | D23: CR ~70% of units vs Seasons ~8%
A24: Units with ≥1 Micron DIRECT earner (T1) | B24: ='Tier Summary'!D25 -> 0.25524476 | C24: ='Tier Summary'!F25 -> 0.029508197
A26: INCOME & RENT COVERAGE
A27: Median personal income (stated earners) | B27: ='Income & Coverage'!B14 -> 107000 | C27: ='Income & Coverage'!D14 -> 58020 | D27: CR ≈ 1.8× Seasons
A28: Median household income | B28: ='Income & Coverage'!B26 -> 144600 | C28: ='Income & Coverage'!D26 -> 80160
A29: Median rent-coverage multiple | B29: ='Income & Coverage'!B38 -> 6.14 | C29: ='Income & Coverage'!D38 -> 3.84 | D29: HH income ÷ (12 × rent)
A30: Units ≥ 3x rent | B30: ='Income & Coverage'!B39/'Income & Coverage'!B37 -> 0.93359375 | C30: ='Income & Coverage'!D39/'Income & Coverage'!D37 -> 0.79180887
A31: Units < 2x rent (thin coverage) | B31: ='Income & Coverage'!B31/'Income & Coverage'!B37 -> 0.0078125 | C31: ='Income & Coverage'!D31/'Income & Coverage'!D37 -> 0.081911263 | D31: Seasons carries a real thin-coverage tail; CR nearly none
A33: EMPLOYER DIVERSIFICATION
A34: Distinct employers | B34: 151 | C34: 304 | D34: Seasons has 2× the employer count on a similar base
A35: Top employer share of employed | B35: 0.26409496 | C35: 0.036117381 | D35: CR: Micron 26.4% · Seasons: Amazon 3.6%
A36: Top-5 employer share | B36: 0.38575668 | C36: 0.1241535
A37: Top-10 employer share | B37: 0.47774481 | C37: 0.18510158
A38: Largest industry cluster | B38: ='Industry Mix'!C5+'Industry Mix'!C6+'Industry Mix'!C7+'Industry Mix'!C8 -> 0.71513353 | C38: ='Industry Mix'!E12 -> 0.21670429 | D38: CR: Micron+fab supply chain · Seasons: healthcare (largest at ~22%)
A40: HOUSEHOLD COMPOSITION & STABILITY
A41: Avg occupants per unit (excl. guarantors) | B41: 1.59 | C41: 1.89 | D41: Seasons skews larger households (roommates, spouses, kids)
A42: Single-occupant units | B42: 0.50699301 | C42: 0.39016393
A43: Roommate households | C43: 0.34098361 | D43: CR export doesn't distinguish roommate vs partner co-applicants
A44: Couple / family households | C44: 0.21967213 | D44: Seasons: spouse on lease
A45: Guarantor-backed units | B45: 0 | C45: 0.095081967 | D45: Seasons 29 units (9.5%); CR export shows none
A46: Coworker-roommate units (same employer) | B46: 33 | C46: 14 | D46: CR: 33 units, 15 Micron (per CR cross-analysis). Seasons: 14 genuine, largely non-Micron
A47: Named-employer (W-2 style) share of occupants | B47: 0.73026316 | C47: 0.72
A48: Self-employed / gig / private-party | B48: 0.0087719298 | C48: 0.036521739
A49: Retired / non-employment income | B49: 0 | C49: 0.017391304
A50: No employer stated | B50: 0.26096491 | C50: 0.21217391 | D50: Similar blank rates — data quality comparable
A52: KEY TAKEAWAYS
A53: 1. MICRON EXPOSURE IS THE DEFINING DIFFERENCE. Canyon Ridge is functionally Micron worker housing: ~72% of employed residents (and ~70% of units) are Micron or Micron-fab-related, incl. 26% Micron direct. Seasons at Meridian is a diversified suburban rent roll: ~6% Micron-related broad, ~2% Micron direct, spread across 304 distinct employers (healthcare, retail, government, education, construction).
A54: 2. TENANT INCOMES: Canyon Ridge median personal income ($107K) is ~1.8× Seasons ($58K); household $145K vs $80K; median rent coverage 6.1x vs 3.8x. But CR's premium income is largely fab-build construction wages (often per-diem-inflated, project-tenured), while Seasons income is structurally local. Seasons carries a thin-coverage tail (~8% of units <2x) that CR doesn't have.
A55: 3. SAME VINTAGE, DIFFERENT DEMAND ENGINE. Both opened Aug/Sep-2024 and leased up through 2025-26. CR's lease-up tracked the fab construction ramp (move-in cohorts 67-81% Micron-related since Q3-25); Seasons leased up on general Meridian demand and is at 95.0% with contract rents still ~11% below its own asking rents (lease-up loss-to-lease), with 38 units (11.1%) on notice as first-generation leases roll.
A56: 4. RISK PROFILE: CR = event/concentration risk — one employer decision moves occupancy (the Sept-2025 Exyte termination emptied a handful of CR units within a quarter; construction workforce winds down into first wafers 2H-2027, to be backfilled by fab operations hiring). Seasons = market risk only (Boise-metro supply/demand), plus ordinary churn. CR's upside is the same concentration: it sits adjacent to ~17,000 projected Micron jobs.
A57: 5. HOUSEHOLD STRUCTURE: Seasons looks like a normal suburban asset — 34% roommate households, 22% couples/families, kids, retirees, 9.5% guarantor-backed leases. CR is applicant-pairs and coworker roommates (33 units of same-employer roommates, 15 of them Micron) — corporate-style demand with double-income units but shallower local roots.

Sheet Tier Summary
A1: Micron-Exposure Tier Summary — Canyon Ridge vs Seasons at Meridian
A2: Occupant counts exclude guarantors (Seasons) and use Primary + Co-Applicant (Canyon Ridge). "% of employed" = share of occupants with a classified employer (retired/student/homemaker excluded). All counts are live formulas on the data tabs.
A4: Tier | B4: Description | C4: Canyon Ridge | D4: CR % of employed | E4: Seasons | F4: Seasons % of employed
A5: T1 | B5: Micron (direct employer) | C5: =COUNTIF('CR Data'!K$5:K$460,"T1") -> 89 | D5: =C5/C$11 -> 0.26409496 | E5: =COUNTIFS('Seasons Data'!H$5:H$608,"T1",'Seasons Data'!E$5:E$608,"Y") -> 9 | F5: =E5/E$11 -> 0.020316027
A6: T2 | B6: Micron construction subcontractor (building the fabs) | C6: =COUNTIF('CR Data'!K$5:K$460,"T2") -> 122 | D6: =C6/C$11 -> 0.3620178 | E6: =COUNTIFS('Seasons Data'!H$5:H$608,"T2",'Seasons Data'!E$5:E$608,"Y") -> 12 | F6: =E6/E$11 -> 0.027088036
A7: T3 | B7: Micron engineering / design / consulting / IT-staffing contractor | C7: =COUNTIF('CR Data'!K$5:K$460,"T3") -> 17 | D7: =C7/C$11 -> 0.050445104 | E7: =COUNTIFS('Seasons Data'!H$5:H$608,"T3",'Seasons Data'!E$5:E$608,"Y") -> 3 | F7: =E7/E$11 -> 0.006772009
A8: T4 | B8: Semiconductor equipment / tool / materials vendor serving Micron | C8: =COUNTIF('CR Data'!K$5:K$460,"T4") -> 13 | D8: =C8/C$11 -> 0.038575668 | E8: =COUNTIFS('Seasons Data'!H$5:H$608,"T4",'Seasons Data'!E$5:E$608,"Y") -> 4 | F8: =E8/E$11 -> 0.0090293454
A9: T5 | B9: Other semiconductor / tech company — NOT Micron-related | C9: =COUNTIF('CR Data'!K$5:K$460,"T5") -> 5 | D9: =C9/C$11 -> 0.014836795 | E9: =COUNTIFS('Seasons Data'!H$5:H$608,"T5",'Seasons Data'!E$5:E$608,"Y") -> 2 | F9: =E9/E$11 -> 0.0045146727
A10: T6 | B10: Unrelated / local | C10: =COUNTIF('CR Data'!K$5:K$460,"T6") -> 91 | D10: =C10/C$11 -> 0.27002967 | E10: =COUNTIFS('Seasons Data'!H$5:H$608,"T6",'Seasons Data'!E$5:E$608,"Y") -> 413 | F10: =E10/E$11 -> 0.93227991
B11: Employed occupants (T1–T6) | C11: =SUM(C5:C10) -> 337 | D11: 1 | E11: =SUM(E5:E10) -> 443 | F11: 1
B12: Not employed (retired / student / homemaker / other income) | C12: 0 | E12: =COUNTIFS('Seasons Data'!H$5:H$608,"",'Seasons Data'!E$5:E$608,"Y",'Seasons Data'!G$5:G$608,"<>") -> 10
B13: No employer stated (blank) | C13: =COUNTIFS('CR Data'!K$5:K$460,"",'CR Data'!A$5:A$460,"<>") -> 119 | E13: =COUNTIFS('Seasons Data'!G$5:G$608,"",'Seasons Data'!E$5:E$608,"Y") -> 122
B14: Total occupant records (excl. guarantors) | C14: =SUM(C11:C13) -> 456 | E14: =SUM(E11:E13) -> 575
A16: MICRON-EXPOSURE ROLL-UPS — occupant level
B17: MICRON DIRECT (T1) | C17: =C5 -> 89 | D17: =C17/C$11 -> 0.26409496 | E17: =E5 -> 9 | F17: =E17/E$11 -> 0.020316027
B18: MICRON-RELATED narrow (T1+T2) | C18: =C5+C6 -> 211 | D18: =C18/C$11 -> 0.62611276 | E18: =E5+E6 -> 21 | F18: =E18/E$11 -> 0.047404063
B19: MICRON-RELATED mid (T1+T2+T3) | C19: =C5+C6+C7 -> 228 | D19: =C19/C$11 -> 0.67655786 | E19: =E5+E6+E7 -> 24 | F19: =E19/E$11 -> 0.054176072
B20: MICRON-RELATED broad (T1+T2+T3+T4) | C20: =SUM(C5:C8) -> 241 | D20: =C20/C$11 -> 0.71513353 | E20: =SUM(E5:E8) -> 28 | F20: =E20/E$11 -> 0.063205418
A22: MICRON-EXPOSURE — unit level (revenue-at-risk lens)
B23: Units with demographic data | C23: =COUNTIF('Unit Coverage Detail'!A$5:A$595,"Canyon Ridge") -> 286 | E23: =COUNTIF('Unit Coverage Detail'!A$5:A$595,"Seasons") -> 305
B24: Units with ≥1 Micron-related earner (T1–T4) | C24: =COUNTIFS('Unit Coverage Detail'!A$5:A$595,"Canyon Ridge",'Unit Coverage Detail'!G$5:G$595,"Y") -> 199 | D24: =C24/C23 -> 0.6958042 | E24: =COUNTIFS('Unit Coverage Detail'!A$5:A$595,"Seasons",'Unit Coverage Detail'!G$5:G$595,"Y") -> 24 | F24: =E24/E23 -> 0.078688525
B25: Units with ≥1 Micron DIRECT earner (T1) | C25: =COUNTIFS('Unit Coverage Detail'!A$5:A$595,"Canyon Ridge",'Unit Coverage Detail'!H$5:H$595,"Y") -> 73 | D25: =C25/C23 -> 0.25524476 | E25: =COUNTIFS('Unit Coverage Detail'!A$5:A$595,"Seasons",'Unit Coverage Detail'!H$5:H$595,"Y") -> 9 | F25: =E25/E23 -> 0.029508197
A27: Note: Seasons demographics cover 305 of 342 occupied units (the 38 units on notice are excluded from the seller export). Canyon Ridge covers 286 units incl. notice & future leases. Guarantor employers (e.g., a Micron guarantor at Seasons unit B208) are excluded.

Sheet Income & Coverage
A1: Income Distributions & Rent Coverage
A2: Personal income: occupants with a qualifying stated income (excl. guarantors, $0, copied records, ≥$1M outliers). Household income: sum of qualifying occupant incomes per unit. Coverage = HH income ÷ (12 × contract rent). Band counts are live COUNTIFS; medians/means are computed from the same data (values shown in blue).
A4: PERSONAL (occupant-level) ANNUAL INCOME
A5: Band | B5: Canyon Ridge | C5: CR % | D5: Seasons | E5: Seasons %
A6: < $40K | B6: =COUNTIFS('CR Data'!M$5:M$460,">0",'CR Data'!M$5:M$460,"<40000") -> 26 | C6: =B6/B$13 -> 0.070080863 | D6: =COUNTIFS('Seasons Data'!K$5:K$608,">0",'Seasons Data'!L$5:L$608,"Y",'Seasons Data'!K$5:K$608,"<40000") -> 109 | E6: =D6/D$13 -> 0.2626506
A7: $40K – $60K | B7: =COUNTIFS('CR Data'!M$5:M$460,">0",'CR Data'!M$5:M$460,">=40000",'CR Data'!M$5:M$460,"<60000") -> 27 | C7: =B7/B$13 -> 0.07277628 | D7: =COUNTIFS('Seasons Data'!K$5:K$608,">0",'Seasons Data'!L$5:L$608,"Y",'Seasons Data'!K$5:K$608,">=40000",'Seasons Data'!K$5:K$608,"<60000") -> 107 | E7: =D7/D$13 -> 0.25783133
A8: $60K – $80K | B8: =COUNTIFS('CR Data'!M$5:M$460,">0",'CR Data'!M$5:M$460,">=60000",'CR Data'!M$5:M$460,"<80000") -> 37 | C8: =B8/B$13 -> 0.099730458 | D8: =COUNTIFS('Seasons Data'!K$5:K$608,">0",'Seasons Data'!L$5:L$608,"Y",'Seasons Data'!K$5:K$608,">=60000",'Seasons Data'!K$5:K$608,"<80000") -> 91 | E8: =D8/D$13 -> 0.21927711
A9: $80K – $100K | B9: =COUNTIFS('CR Data'!M$5:M$460,">0",'CR Data'!M$5:M$460,">=80000",'CR Data'!M$5:M$460,"<100000") -> 67 | C9: =B9/B$13 -> 0.18059299 | D9: =COUNTIFS('Seasons Data'!K$5:K$608,">0",'Seasons Data'!L$5:L$608,"Y",'Seasons Data'!K$5:K$608,">=80000",'Seasons Data'!K$5:K$608,"<100000") -> 40 | E9: =D9/D$13 -> 0.096385542
A10: $100K – $150K | B10: =COUNTIFS('CR Data'!M$5:M$460,">0",'CR Data'!M$5:M$460,">=100000",'CR Data'!M$5:M$460,"<150000") -> 121 | C10: =B10/B$13 -> 0.32614555 | D10: =COUNTIFS('Seasons Data'!K$5:K$608,">0",'Seasons Data'!L$5:L$608,"Y",'Seasons Data'!K$5:K$608,">=100000",'Seasons Data'!K$5:K$608,"<150000") -> 53 | E10: =D10/D$13 -> 0.12771084
A11: $150K – $200K | B11: =COUNTIFS('CR Data'!M$5:M$460,">0",'CR Data'!M$5:M$460,">=150000",'CR Data'!M$5:M$460,"<200000") -> 46 | C11: =B11/B$13 -> 0.12398922 | D11: =COUNTIFS('Seasons Data'!K$5:K$608,">0",'Seasons Data'!L$5:L$608,"Y",'Seasons Data'!K$5:K$608,">=150000",'Seasons Data'!K$5:K$608,"<200000") -> 3 | E11: =D11/D$13 -> 0.0072289157
A12: $200K+ | B12: =COUNTIFS('CR Data'!M$5:M$460,">0",'CR Data'!M$5:M$460,">=200000") -> 47 | C12: =B12/B$13 -> 0.12668464 | D12: =COUNTIFS('Seasons Data'!K$5:K$608,">0",'Seasons Data'!L$5:L$608,"Y",'Seasons Data'!K$5:K$608,">=200000") -> 12 | E12: =D12/D$13 -> 0.028915663
A13: Occupants with qualifying income | B13: =SUM(B6:B12) -> 371 | D13: =SUM(D6:D12) -> 415
A14: MEDIAN personal income | B14: 107000 | D14: 58020
A15: Average personal income | B15: 162598 | D15: 71814 | E15: CR average inflated by high construction/per-diem earners
A17: HOUSEHOLD (unit-level) ANNUAL INCOME
A18: Band | B18: Canyon Ridge | C18: CR % | D18: Seasons | E18: Seasons %
A19: < $50K | B19: =COUNTIFS('Unit Coverage Detail'!A$5:A$595,"Canyon Ridge",'Unit Coverage Detail'!C$5:C$595,">0",'Unit Coverage Detail'!C$5:C$595,"<50000") -> 1 | C19: =B19/B$25 -> 0.0038910506 | D19: =COUNTIFS('Unit Coverage Detail'!A$5:A$595,"Seasons",'Unit Coverage Detail'!C$5:C$595,">0",'Unit Coverage Detail'!C$5:C$595,"<50000") -> 41 | E19: =D19/D$25 -> 0.13993174
A20: $50K – $75K | B20: =COUNTIFS('Unit Coverage Detail'!A$5:A$595,"Canyon Ridge",'Unit Coverage Detail'!C$5:C$595,">0",'Unit Coverage Detail'!C$5:C$595,">=50000",'Unit Coverage Detail'!C$5:C$595,"<75000") -> 24 | C20: =B20/B$25 -> 0.093385214 | D20: =COUNTIFS('Unit Coverage Detail'!A$5:A$595,"Seasons",'Unit Coverage Detail'!C$5:C$595,">0",'Unit Coverage Detail'!C$5:C$595,">=50000",'Unit Coverage Detail'!C$5:C$595,"<75000") -> 87 | E20: =D20/D$25 -> 0.29692833
A21: $75K – $100K | B21: =COUNTIFS('Unit Coverage Detail'!A$5:A$595,"Canyon Ridge",'Unit Coverage Detail'!C$5:C$595,">0",'Unit Coverage Detail'!C$5:C$595,">=75000",'Unit Coverage Detail'!C$5:C$595,"<100000") -> 39 | C21: =B21/B$25 -> 0.15175097 | D21: =COUNTIFS('Unit Coverage Detail'!A$5:A$595,"Seasons",'Unit Coverage Detail'!C$5:C$595,">0",'Unit Coverage Detail'!C$5:C$595,">=75000",'Unit Coverage Detail'!C$5:C$595,"<100000") -> 65 | E21: =D21/D$25 -> 0.221843
A22: $100K – $150K | B22: =COUNTIFS('Unit Coverage Detail'!A$5:A$595,"Canyon Ridge",'Unit Coverage Detail'!C$5:C$595,">0",'Unit Coverage Detail'!C$5:C$595,">=100000",'Unit Coverage Detail'!C$5:C$595,"<150000") -> 69 | C22: =B22/B$25 -> 0.26848249 | D22: =COUNTIFS('Unit Coverage Detail'!A$5:A$595,"Seasons",'Unit Coverage Detail'!C$5:C$595,">0",'Unit Coverage Detail'!C$5:C$595,">=100000",'Unit Coverage Detail'!C$5:C$595,"<150000") -> 67 | E22: =D22/D$25 -> 0.22866894
A23: $150K – $250K | B23: =COUNTIFS('Unit Coverage Detail'!A$5:A$595,"Canyon Ridge",'Unit Coverage Detail'!C$5:C$595,">0",'Unit Coverage Detail'!C$5:C$595,">=150000",'Unit Coverage Detail'!C$5:C$595,"<250000") -> 75 | C23: =B23/B$25 -> 0.29182879 | D23: =COUNTIFS('Unit Coverage Detail'!A$5:A$595,"Seasons",'Unit Coverage Detail'!C$5:C$595,">0",'Unit Coverage Detail'!C$5:C$595,">=150000",'Unit Coverage Detail'!C$5:C$595,"<250000") -> 23 | E23: =D23/D$25 -> 0.078498294
A24: $250K+ | B24: =COUNTIFS('Unit Coverage Detail'!A$5:A$595,"Canyon Ridge",'Unit Coverage Detail'!C$5:C$595,">0",'Unit Coverage Detail'!C$5:C$595,">=250000") -> 49 | C24: =B24/B$25 -> 0.19066148 | D24: =COUNTIFS('Unit Coverage Detail'!A$5:A$595,"Seasons",'Unit Coverage Detail'!C$5:C$595,">0",'Unit Coverage Detail'!C$5:C$595,">=250000") -> 10 | E24: =D24/D$25 -> 0.034129693
A25: Households with income data | B25: =SUM(B19:B24) -> 257 | D25: =SUM(D19:D24) -> 293
A26: MEDIAN household income | B26: 144600 | D26: 80160
A27: Average household income | B27: 234723 | D27: 101716
A29: RENT COVERAGE (HH income ÷ 12 × contract rent)
A30: Bucket | B30: Canyon Ridge | C30: CR % | D30: Seasons | E30: Seasons %
A31: < 2.0x (thin) | B31: =COUNTIFS('Unit Coverage Detail'!A$5:A$595,"Canyon Ridge",'Unit Coverage Detail'!E$5:E$595,">0",'Unit Coverage Detail'!E$5:E$595,"<2") -> 2 | C31: =B31/B$37 -> 0.0078125 | D31: =COUNTIFS('Unit Coverage Detail'!A$5:A$595,"Seasons",'Unit Coverage Detail'!E$5:E$595,">0",'Unit Coverage Detail'!E$5:E$595,"<2") -> 24 | E31: =D31/D$37 -> 0.081911263
A32: 2.0x – 2.5x | B32: =COUNTIFS('Unit Coverage Detail'!A$5:A$595,"Canyon Ridge",'Unit Coverage Detail'!E$5:E$595,">0",'Unit Coverage Detail'!E$5:E$595,">=2",'Unit Coverage Detail'!E$5:E$595,"<2.5") -> 2 | C32: =B32/B$37 -> 0.0078125 | D32: =COUNTIFS('Unit Coverage Detail'!A$5:A$595,"Seasons",'Unit Coverage Detail'!E$5:E$595,">0",'Unit Coverage Detail'!E$5:E$595,">=2",'Unit Coverage Detail'!E$5:E$595,"<2.5") -> 19 | E32: =D32/D$37 -> 0.064846416
A33: 2.5x – 3.0x | B33: =COUNTIFS('Unit Coverage Detail'!A$5:A$595,"Canyon Ridge",'Unit Coverage Detail'!E$5:E$595,">0",'Unit Coverage Detail'!E$5:E$595,">=2.5",'Unit Coverage Detail'!E$5:E$595,"<3") -> 13 | C33: =B33/B$37 -> 0.05078125 | D33: =COUNTIFS('Unit Coverage Detail'!A$5:A$595,"Seasons",'Unit Coverage Detail'!E$5:E$595,">0",'Unit Coverage Detail'!E$5:E$595,">=2.5",'Unit Coverage Detail'!E$5:E$595,"<3") -> 18 | E33: =D33/D$37 -> 0.061433447
A34: 3.0x – 4.0x | B34: =COUNTIFS('Unit Coverage Detail'!A$5:A$595,"Canyon Ridge",'Unit Coverage Detail'!E$5:E$595,">0",'Unit Coverage Detail'!E$5:E$595,">=3",'Unit Coverage Detail'!E$5:E$595,"<4") -> 34 | C34: =B34/B$37 -> 0.1328125 | D34: =COUNTIFS('Unit Coverage Detail'!A$5:A$595,"Seasons",'Unit Coverage Detail'!E$5:E$595,">0",'Unit Coverage Detail'!E$5:E$595,">=3",'Unit Coverage Detail'!E$5:E$595,"<4") -> 98 | E34: =D34/D$37 -> 0.33447099
A35: 4.0x – 6.0x | B35: =COUNTIFS('Unit Coverage Detail'!A$5:A$595,"Canyon Ridge",'Unit Coverage Detail'!E$5:E$595,">0",'Unit Coverage Detail'!E$5:E$595,">=4",'Unit Coverage Detail'!E$5:E$595,"<6") -> 72 | C35: =B35/B$37 -> 0.28125 | D35: =COUNTIFS('Unit Coverage Detail'!A$5:A$595,"Seasons",'Unit Coverage Detail'!E$5:E$595,">0",'Unit Coverage Detail'!E$5:E$595,">=4",'Unit Coverage Detail'!E$5:E$595,"<6") -> 75 | E35: =D35/D$37 -> 0.2559727
A36: 6.0x+ | B36: =COUNTIFS('Unit Coverage Detail'!A$5:A$595,"Canyon Ridge",'Unit Coverage Detail'!E$5:E$595,">0",'Unit Coverage Detail'!E$5:E$595,">=6") -> 133 | C36: =B36/B$37 -> 0.51953125 | D36: =COUNTIFS('Unit Coverage Detail'!A$5:A$595,"Seasons",'Unit Coverage Detail'!E$5:E$595,">0",'Unit Coverage Detail'!E$5:E$595,">=6") -> 59 | E36: =D36/D$37 -> 0.20136519
A37: Units with rent + income | B37: =SUM(B31:B36) -> 256 | D37: =SUM(D31:D36) -> 293
A38: MEDIAN coverage multiple | B38: 6.14 | D38: 3.84
A39: Units ≥ 3.0x rent | B39: =COUNTIFS('Unit Coverage Detail'!A$5:A$595,"Canyon Ridge",'Unit Coverage Detail'!F$5:F$595,"Y") -> 239 | C39: =B39/B37 -> 0.93359375 | D39: =COUNTIFS('Unit Coverage Detail'!A$5:A$595,"Seasons",'Unit Coverage Detail'!F$5:F$595,"Y") -> 232 | E39: =D39/D37 -> 0.79180887
A41: RENT LEVELS (contract)
A42: Median contract rent / occupied unit | B42: 1975 | D42: 1714
A43: Average contract rent / occupied unit | B43: 1991 | D43: 1738
A44: Median MARKET rent (Seasons rent roll) | B44: — | D44: 1896.5
A45: Contract ÷ market (Seasons, occupied units) | B45: — | D45: 0.8879
A46: Seasons contract rents sit ~11% below its own market/asking rents (lease-up loss-to-lease & embedded concessions). Canyon Ridge demographics report has scheduled rent only (no market-rent column).

Sheet Industry Mix
A1: Employer Industry Mix — employed occupants
A2: Live COUNTIFS on the data tabs. Denominator = employed occupants (Tier Summary row 11). Micron-related industries highlighted.
A4: Industry | B4: Canyon Ridge | C4: CR % | D4: Seasons | E4: Seasons %
A5: Micron (direct) | B5: =COUNTIF('CR Data'!L$5:L$460,A5) -> 89 | C5: =B5/'Tier Summary'!C$11 -> 0.26409496 | D5: =COUNTIFS('Seasons Data'!I$5:I$608,A5,'Seasons Data'!E$5:E$608,"Y",'Seasons Data'!H$5:H$608,"<>") -> 9 | E5: =D5/'Tier Summary'!E$11 -> 0.020316027
A6: Micron fab construction | B6: =COUNTIF('CR Data'!L$5:L$460,A6) -> 122 | C6: =B6/'Tier Summary'!C$11 -> 0.3620178 | D6: =COUNTIFS('Seasons Data'!I$5:I$608,A6,'Seasons Data'!E$5:E$608,"Y",'Seasons Data'!H$5:H$608,"<>") -> 12 | E6: =D6/'Tier Summary'!E$11 -> 0.027088036
A7: Micron eng/consulting/IT | B7: =COUNTIF('CR Data'!L$5:L$460,A7) -> 17 | C7: =B7/'Tier Summary'!C$11 -> 0.050445104 | D7: =COUNTIFS('Seasons Data'!I$5:I$608,A7,'Seasons Data'!E$5:E$608,"Y",'Seasons Data'!H$5:H$608,"<>") -> 3 | E7: =D7/'Tier Summary'!E$11 -> 0.006772009
A8: Semi equipment & materials | B8: =COUNTIF('CR Data'!L$5:L$460,A8) -> 13 | C8: =B8/'Tier Summary'!C$11 -> 0.038575668 | D8: =COUNTIFS('Seasons Data'!I$5:I$608,A8,'Seasons Data'!E$5:E$608,"Y",'Seasons Data'!H$5:H$608,"<>") -> 4 | E8: =D8/'Tier Summary'!E$11 -> 0.0090293454
A9: Semiconductor (non-Micron) | B9: =COUNTIF('CR Data'!L$5:L$460,A9) -> 5 | C9: =B9/'Tier Summary'!C$11 -> 0.014836795 | D9: =COUNTIFS('Seasons Data'!I$5:I$608,A9,'Seasons Data'!E$5:E$608,"Y",'Seasons Data'!H$5:H$608,"<>") -> 2 | E9: =D9/'Tier Summary'!E$11 -> 0.0045146727
A10: Government, Military & Public Safety | B10: =COUNTIF('CR Data'!L$5:L$460,A10) -> 16 | C10: =B10/'Tier Summary'!C$11 -> 0.047477745 | D10: =COUNTIFS('Seasons Data'!I$5:I$608,A10,'Seasons Data'!E$5:E$608,"Y",'Seasons Data'!H$5:H$608,"<>") -> 32 | E10: =D10/'Tier Summary'!E$11 -> 0.072234763
A11: Retail & Food Service | B11: =COUNTIF('CR Data'!L$5:L$460,A11) -> 13 | C11: =B11/'Tier Summary'!C$11 -> 0.038575668 | D11: =COUNTIFS('Seasons Data'!I$5:I$608,A11,'Seasons Data'!E$5:E$608,"Y",'Seasons Data'!H$5:H$608,"<>") -> 61 | E11: =D11/'Tier Summary'!E$11 -> 0.13769752
A12: Healthcare & Social Services | B12: =COUNTIF('CR Data'!L$5:L$460,A12) -> 11 | C12: =B12/'Tier Summary'!C$11 -> 0.03264095 | D12: =COUNTIFS('Seasons Data'!I$5:I$608,A12,'Seasons Data'!E$5:E$608,"Y",'Seasons Data'!H$5:H$608,"<>") -> 96 | E12: =D12/'Tier Summary'!E$11 -> 0.21670429
A13: Education & Childcare | B13: =COUNTIF('CR Data'!L$5:L$460,A13) -> 10 | C13: =B13/'Tier Summary'!C$11 -> 0.029673591 | D13: =COUNTIFS('Seasons Data'!I$5:I$608,A13,'Seasons Data'!E$5:E$608,"Y",'Seasons Data'!H$5:H$608,"<>") -> 20 | E13: =D13/'Tier Summary'!E$11 -> 0.045146727
A14: Tech & Software (non-semi) | B14: =COUNTIF('CR Data'!L$5:L$460,A14) -> 10 | C14: =B14/'Tier Summary'!C$11 -> 0.029673591 | D14: =COUNTIFS('Seasons Data'!I$5:I$608,A14,'Seasons Data'!E$5:E$608,"Y",'Seasons Data'!H$5:H$608,"<>") -> 9 | E14: =D14/'Tier Summary'!E$11 -> 0.020316027
A15: Financial, Legal & Professional | B15: =COUNTIF('CR Data'!L$5:L$460,A15) -> 8 | C15: =B15/'Tier Summary'!C$11 -> 0.023738872 | D15: =COUNTIFS('Seasons Data'!I$5:I$608,A15,'Seasons Data'!E$5:E$608,"Y",'Seasons Data'!H$5:H$608,"<>") -> 33 | E15: =D15/'Tier Summary'!E$11 -> 0.074492099
A16: Wholesale, Transport & Logistics | B16: =COUNTIF('CR Data'!L$5:L$460,A16) -> 5 | C16: =B16/'Tier Summary'!C$11 -> 0.014836795 | D16: =COUNTIFS('Seasons Data'!I$5:I$608,A16,'Seasons Data'!E$5:E$608,"Y",'Seasons Data'!H$5:H$608,"<>") -> 22 | E16: =D16/'Tier Summary'!E$11 -> 0.0496614
... A28: Corporate housing entity | B28: =COUNTIF('CR Data'!L$5:L$460,A28) -> 0 | C28: =B28/'Tier Summary'!C$11 -> 0 | D28: =COUNTIFS('Seasons Data'!I$5:I$608,A28,'Seasons Data'!E$5:E$608,"Y",'Seasons Data'!H$5:H$608,"<>") -> 4 | E28: =D28/'Tier Summary'!E$11 -> 0.0090293454
A29: Total employed | B29: =SUM(B5:B28) -> 337 | D29: =SUM(D5:D28) -> 443

Sheet Lease-Up & Churn
A1: Lease-Up Timeline & Current Churn — both are 2024-opened lease-ups
A2: Canyon Ridge opened Sep-2024 (first move-ins); Seasons at Meridian opened Aug-2024. Move-in counts: CR = occupant move-ins by quarter (from CR Rent Roll Cross-Analysis 2026.06.24); Seasons = occupied-unit move-ins by quarter (07/09/2026 rent roll). Values in blue are sourced counts.
A4: Quarter | B4: CR move-ins (occupants) | C4: CR % Micron-related | D4: Seasons move-ins (units) | E4: Milestone / context
A5: 2024-Q3 | B5: 13 | C5: 0.38 | D5: 4 | E5: Canyon Ridge opens (Sep); Seasons opens (Aug)
A6: 2024-Q4 | B6: 5 | C6: 0.6 | D6: 12
A7: 2025-Q1 | B7: 17 | C7: 0.71 | D7: 39
A8: 2025-Q2 | B8: 58 | C8: 0.48 | D8: 50 | E8: Micron construction ramp; steel topping out mid-2025
A9: 2025-Q3 | B9: 69 | C9: 0.67 | D9: 66 | E9: CR peak (69 move-ins); Exyte discontinued Sep 2, 2025
A10: 2025-Q4 | B10: 48 | C10: 0.71 | D10: 66 | E10: CR sub population peaks; broker-noted Exyte-linked terminations
A11: 2026-Q1 | B11: 43 | C11: 0.77 | D11: 59 | E11: CR sub fit-out wave continues
A12: 2026-Q2 | B12: 32 | C12: 0.81 | D12: 43 | E12: 12-mo leases from mid-2025 maturing at both properties
A13: 2026-Q3 | B13: 1 | C13: 0 | D13: 3
A14: Total | B14: =SUM(B5:B13) -> 286 | D14: =SUM(D5:D13) -> 342
A16: CURRENT OCCUPANCY & CHURN SNAPSHOT
A17: Total units | B17: 287 | C17: 360
A18: Occupied units | B18: 286 | C18: 342 | E18: Seasons: 07/09/2026 rent roll; CR: 06/24/2026 roster
A19: Physical occupancy | B19: =B18/B17 -> 0.99651568 | C19: =C18/C17 -> 0.95
A20: Units on notice | B20: 24 | C20: 38 | E20: CR notice incl. both Intel units & last Exyte resident; Seasons notice units are excluded from the seller demographics export
A21: Notice % of occupied | B21: =B20/B18 -> 0.083916084 | C21: =C20/C18 -> 0.11111111
A22: Vacant units | B22: 1 | C22: 18

Sheet Micron Detail - Seasons
A1: Seasons at Meridian — Micron & Micron-related occupants (T1–T4), person level
A2: Every occupant whose standardized employer is Micron or Micron-related. Guarantors shown for reference but excluded from headline counts. Note only ~6% of employed residents are Micron-related vs 72% at Canyon Ridge.
A4: Tier | B4: Standardized Employer | C4: Unit | D4: Relationship | E4: Counts in headline | F4: Annual Salary | G4: Confidence | H4: Micron relationship & evidence
A5: T1 | B5: Micron Technology | C5: A106 | D5: Primary | E5: Yes | F5: 51180 | G5: Confirmed
A6: T1 | B6: Micron Technology | C6: B208 | D6: Guarantor | E6: No (guarantor) | F6: 276816 | G6: Confirmed
A7: T1 | B7: Micron Technology | C7: E211 | D7: Primary | E7: Yes | F7: 56700 | G7: Confirmed
A8: T1 | B8: Micron Technology | C8: G306 | D8: Primary | E8: Yes | F8: 58812 | G8: Confirmed
A9: T1 | B9: Micron Technology | C9: I108 | D9: Primary | E9: Yes | F9: 124272 | G9: Confirmed
A10: T1 | B10: Micron Technology | C10: I208 | D10: Primary | E10: Yes | F10: 96996 | G10: Confirmed
A11: T1 | B11: Micron Technology | C11: I304 | D11: Primary | E11: Yes | F11: 121608 | G11: Confirmed
A12: T1 | B12: Micron Technology | C12: I312 | D12: Roommate | E12: Yes | F12: 50400 | G12: Confirmed
A13: T1 | B13: Micron Technology | C13: J102 | D13: Primary | E13: Yes | F13: 54000 | G13: Confirmed
A14: T1 | B14: Micron Technology | C14: J313 | D14: Primary | E14: Yes | F14: 87600 | G14: Confirmed
A15: T2 | B15: Engineered Structures, Inc. (ESI) | C15: C305 | D15: Spouse | E15: Yes | F15: 133620 | G15: Confirmed | H15: ENR documents ESI building office and parking structures at Micron's Boise global HQ as part of the campus expansion; $133.6K salary fits a PM/superintendent.
A16: T2 | B16: Engineered Structures, Inc. (ESI) | C16: C305 | D16: Roommate | E16: Yes | F16: 133620 | G16: Confirmed | H16: ENR documents ESI building office and parking structures at Micron's Boise global HQ as part of the campus expansion; $133.6K salary fits a PM/superintendent.
A17: T2 | B17: Hensel Phelps | C17: G106 | D17: Primary | E17: Yes | F17: 83160 | G17: Confirmed | H17: Listed among GCs/EPC contractors performing work on Micron's Boise fab project.
A18: T2 | B18: Hoffman Construction Company | C18: A207 | D18: Primary | E18: Yes | F18: 120000 | G18: Confirmed
A19: T2 | B19: IBEW (electricians union) | C19: D101 | D19: Primary | E19: Yes | F19: 118392 | G19: Strong-inferred
A20: T2 | B20: IBEW (electricians union) | C20: D101 | D20: Spouse | E20: Yes | F20: 183312 | G20: Strong-inferred
A21: T2 | B21: JH Kelly | C21: D109 | D21: Roommate | E21: Yes | F21: 107172 | G21: Confirmed
A22: T2 | B22: Oregon Electric Group (OEG) | C22: B108 | D22: Primary | E22: Yes | F22: 120000 | G22: Strong-inferred
A23: T2 | B23: Phoenix Industrial | C23: D109 | D23: Primary | E23: Yes | F23: 72372 | G23: Strong-inferred
A24: T2 | B24: Southland Industries | C24: C306 | D24: Primary | E24: Yes | F24: 80040 | G24: Strong-inferred | H24: A national MEP giant staffing up in Boise for a mission-critical industrial project during the fab build is a strong fit for Micron ID1 mechanical scope.
A25: T2 | B25: W&W Steel Erectors (W&W|AFCO Steel) | C25: D313 | D25: Roommate | E25: Yes | F25: 118356 | G25: Strong-inferred | H25: ID1 involves ~70,000 tons of steel and W&W is the dominant US fab steel erector; an erector resident 20 miles from site during peak erection is a strong trade fit.
A26: T2 | B26: Western Partitions, Inc. (WPI) | C26: D312 | D26: Primary | E26: Yes | F26: 103200 | G26: Weak-inferred | H26: No public Micron contract, but a top-tier NW mission-critical interiors sub with a Boise-area office and a $103K resident wage is consistent with fab support-building/interiors scope.
A27: T3 | B27: Atlas Technical Consultants (OneAtlas) | C27: E205 | D27: Primary | E27: Yes | F27: 64488 | G27: Strong-inferred | H27: Boise-area Atlas job postings explicitly reference staffing for the 'Micron Triton project', indicating active testing/inspection work on the Triton site.
A28: T3 | B28: POWER Engineers (a WSP company) | C28: J208 | D28: Primary | E28: Yes | F28: 70716 | G28: Inferred | H28: Aligned to Canyon Ridge workbook: POWER Engineers classified T3 there; Idaho power-delivery engineering consultant plausibly supporting fab power infrastructure.
A29: T3 | B29: Prime Controls, LP | C29: E309 | D29: Primary | E29: Yes | F29: 124860 | G29: Inferred | H29: Aligned to Canyon Ridge workbook: Prime Controls classified T3 there (3 residents); fab FMCS/I&C specialty.
A30: T4 | B30: Critical Systems, Inc. (CSI) | C30: F313 | D30: Primary | E30: Yes | F30: 60000 | G30: Strong-inferred | H30: Not publicly named by Micron, but a Boise-HQ'd UHP gas-systems house next to Micron's campus is squarely in the fab tool-hookup/gas supply chain; two modest-wage residents fit techs/fabricators.
A31: T4 | B31: Critical Systems, Inc. (CSI) | C31: F313 | D31: Roommate | E31: Yes | F31: 45600 | G31: Strong-inferred | H31: Not publicly named by Micron, but a Boise-HQ'd UHP gas-systems house next to Micron's campus is squarely in the fab tool-hookup/gas supply chain; two modest-wage residents fit techs/fabricators.
A32: T4 | B32: Kurita America (Kurita Water Industries) | C32: D103 | D32: Primary | E32: Yes | F32: 72000 | G32: Confirmed | H32: Kurita's CEO publicly stated the company would bid to supply ultrapure water for Micron's Boise fab and hire several hundred Boise-area workers; Boise postings indicate staffing that scope.
A33: T4 | B33: Photronics, Inc. | C33: C201 | D33: Primary | E33: Yes | F33: 80004 | G33: Confirmed | H33: Facility originated as a JV with Micron with a technology license and long-term supply arrangement; Boise site supplies Micron.

Sheet Employers - Seasons
A1: Seasons at Meridian — Standardized Employer Summary (all employers)
A2: 375 raw spellings standardized to canonical employers; each classified by relationship to Micron (T1–T6). Resident counts are live COUNTIFS on the Seasons Data tab (occupants excl. guarantors). Ambiguous / Micron-plausible names were individually web-researched (July 2026).
A4: Seasons - Top Employers | B4: Residents | C4: Tier | D4: Industry | E4: What they do | F4: HQ / Boise presence | G4: Micron relationship & evidence | H4: Confidence | I4: Source
A5: St. Luke's Health System | B5: =COUNTIFS('Seasons Data'!G:G,A5,'Seasons Data'!E:E,"Y") -> 16 | C5: T6 | D5: Healthcare & Social Services | H5: Confirmed-NotMicron
A6: Saint Alphonsus (Trinity Health) | B6: =COUNTIFS('Seasons Data'!G:G,A6,'Seasons Data'!E:E,"Y") -> 14 | C6: T6 | D6: Healthcare & Social Services | H6: Confirmed-NotMicron
A7: Micron Technology | B7: =COUNTIFS('Seasons Data'!G:G,A7,'Seasons Data'!E:E,"Y") -> 9 | C7: T1 | D7: Micron (direct) | H7: Confirmed
A8: Self-employed | B8: =COUNTIFS('Seasons Data'!G:G,A8,'Seasons Data'!E:E,"Y") -> 9 | C8: T6 | D8: Self-employed / private | H8: Confirmed-NotMicron
A9: Amazon | B9: =COUNTIFS('Seasons Data'!G:G,A9,'Seasons Data'!E:E,"Y") -> 7 | C9: T6 | D9: Wholesale, Transport & Logistics | H9: Confirmed-NotMicron
A10: Retired | B10: =COUNTIFS('Seasons Data'!G:G,A10,'Seasons Data'!E:E,"Y") -> 7 | C10: — | D10: Not employed / other income | H10: Confirmed-NotMicron
A11: Albertsons | B11: =COUNTIFS('Seasons Data'!G:G,A11,'Seasons Data'!E:E,"Y") -> 6 | C11: T6 | D11: Retail & Food Service | H11: Confirmed-NotMicron
A12: Chick-fil-A | B12: =COUNTIFS('Seasons Data'!G:G,A12,'Seasons Data'!E:E,"Y") -> 6 | C12: T6 | D12: Retail & Food Service | H12: Confirmed-NotMicron
A13: Idaho College of Osteopathic Medicine (ICOM) | B13: =COUNTIFS('Seasons Data'!G:G,A13,'Seasons Data'!E:E,"Y") -> 6 | C13: T6 | D13: Healthcare & Social Services | H13: Inferred
A14: Aimbridge Hospitality | B14: =COUNTIFS('Seasons Data'!G:G,A14,'Seasons Data'!E:E,"Y") -> 5 | C14: T6 | D14: Hospitality | H14: Confirmed-NotMicron
A15: Coleman Environmental Engineering, Inc. | B15: =COUNTIFS('Seasons Data'!G:G,A15,'Seasons Data'!E:E,"Y") -> 4 | C15: T6 | D15: Engineering & Technical Services | E15: Anaheim, CA remediation and disaster-recovery GC: utility vegetation management, wildfire debris removal, soil remediation, demolition; clients include PG&E, SCE, USFS. | F15: No Idaho office found; 4-person corporate-leased Meridian unit indicates a traveling field-crew deployment. | G15: No mention of Idaho, Boise, Micron, or semiconductor work; deployment client unidentified. | H15: Weak-unverified | I15: colemanenvironmental.com
A16: Goodwill | B16: =COUNTIFS('Seasons Data'!G:G,A16,'Seasons Data'!E:E,"Y") -> 4 | C16: T6 | D16: Retail & Food Service | H16: Confirmed-NotMicron
A17: Idaho Central Credit Union | B17: =COUNTIFS('Seasons Data'!G:G,A17,'Seasons Data'!E:E,"Y") -> 4 | C17: T6 | D17: Financial, Legal & Professional | H17: Confirmed-NotMicron
A18: The AZEK Company | B18: =COUNTIFS('Seasons Data'!G:G,A18,'Seasons Data'!E:E,"Y") -> 4 | C18: T6 | D18: Manufacturing & Consumer Products | H18: Confirmed-NotMicron
A19: 'Si' (data-entry artifact) | B19: =COUNTIFS('Seasons Data'!G:G,A19,'Seasons Data'!E:E,"Y") -> 3 | C19: T6 | D19: Unknown / unresolved | E19: No Boise-area company named 'Si'; likely 'Sí'/yes on a Spanish-language application. | F19: — | G19: None; not plausibly a silicon/semiconductor reference. | H19: Weak-unverified | I19: —
A20: 84 Lumber | B20: =COUNTIFS('Seasons Data'!G:G,A20,'Seasons Data'!E:E,"Y") -> 3 | C20: T6 | D20: Construction & Trades (non-Micron) | H20: Confirmed-NotMicron
A21: Arbor Valley of Cascadia | B21: =COUNTIFS('Seasons Data'!G:G,A21,'Seasons Data'!E:E,"Y") -> 3 | C21: T6 | D21: Healthcare & Social Services | H21: Confirmed-NotMicron
A22: Dr. Yvonne Rochon Pediatric Dentistry | B22: =COUNTIFS('Seasons Data'!G:G,A22,'Seasons Data'!E:E,"Y") -> 3 | C22: T6 | D22: Healthcare & Social Services | H22: Confirmed-NotMicron
A23: Eye Care Center of Northern Colorado | B23: =COUNTIFS('Seasons Data'!G:G,A23,'Seasons Data'!E:E,"Y") -> 3 | C23: T6 | D23: Healthcare & Social Services | H23: Confirmed-NotMicron
A24: Idaho Department of Corrections | B24: =COUNTIFS('Seasons Data'!G:G,A24,'Seasons Data'!E:E,"Y") -> 3 | C24: T6 | D24: Government, Military & Public Safety | H24: Confirmed-NotMicron
A25: Idaho Survey Group LLC | B25: =COUNTIFS('Seasons Data'!G:G,A25,'Seasons Data'!E:E,"Y") -> 3 | C25: T6 | D25: Engineering & Technical Services | E25: Boise-based land surveying and construction staking firm serving ID/NV/OR. | F25: HQ Boise, ID. | G25: No Micron connection found; Micron's documented site surveyor since 2017 is a different firm (Eagle Land Surveying). | H25: Inferred | I25: idahosurvey.com
A26: Modern Wealth Management | B26: =COUNTIFS('Seasons Data'!G:G,A26,'Seasons Data'!E:E,"Y") -> 3 | C26: T6 | D26: Financial, Legal & Professional | H26: Confirmed-NotMicron
A27: Royal Coffee Co. | B27: =COUNTIFS('Seasons Data'!G:G,A27,'Seasons Data'!E:E,"Y") -> 3 | C27: T6 | D27: Retail & Food Service | H27: Confirmed-NotMicron
A28: Shea Homes | B28: =COUNTIFS('Seasons Data'!G:G,A28,'Seasons Data'!E:E,"Y") -> 3 | C28: T6 | D28: Construction & Trades (non-Micron) | H28: Confirmed-NotMicron
A29: Uber | B29: =COUNTIFS('Seasons Data'!G:G,A29,'Seasons Data'!E:E,"Y") -> 3 | C29: T6 | D29: Gig economy | H29: Confirmed-NotMicron
A30: WESCO Microscopes (Western Scientific) | B30: =COUNTIFS('Seasons Data'!G:G,A30,'Seasons Data'!E:E,"Y") -> 3 | C30: T6 | D30: Personal Services & Other Local | E30: Family-scale sales, repair, and maintenance of optical microscopes for educational, clinical, industrial users (since 1962). | F30: Relocated from California to Idaho; small Treasure Valley operation. | G30: No semiconductor or Micron connection — optical/lab microscope service shop, not fab metrology. | H30: Confirmed-NotMicron | I30: wescomicroscopes.com
A31: West Ada School District | B31: =COUNTIFS('Seasons Data'!G:G,A31,'Seasons Data'!E:E,"Y") -> 3 | C31: T6 | D31: Education & Childcare | H31: Confirmed-NotMicron
A32: Engineered Structures, Inc. (ESI) | B32: =COUNTIFS('Seasons Data'!G:G,A32,'Seasons Data'!E:E,"Y") -> 2 | C32: T2 | D32: Micron fab construction | E32: Idaho's largest privately owned GC/CM/design-build firm (founded 1973, licensed in 42 states). | F32: Headquartered in Meridian, ID — same city as the property. | G32: ENR documents ESI building office and parking structures at Micron's Boise global HQ as part of the campus expansion; $133.6K salary fits a PM/superintendent. | H32: Confirmed | I32: enr.com
A33: IBEW (electricians union) | B33: =COUNTIFS('Seasons Data'!G:G,A33,'Seasons Data'!E:E,"Y") -> 2 | C33: T2 | D33: Micron fab construction | H33: Strong-inferred
A34: Critical Systems, Inc. (CSI) | B34: =COUNTIFS('Seasons Data'!G:G,A34,'Seasons Data'!E:E,"Y") -> 2 | C34: T4 | D34: Semi equipment & materials | E34: Designs, builds, refurbishes and services ultra-high-purity gas cabinets, valve manifold boxes, gas abatement and orbital welding for semiconductor fabs (since 1998). | F34: HQ at 7000 W Victory Rd, Boise ID — ~2 miles from Micron's Federal Way campus; also MN, PA, TX, UT. | G34: Not publicly named by Micron, but a Boise-HQ'd UHP gas-systems house next to Micron's campus is squarely in the fab tool-hookup/gas supply chain; two modest-wage residents fit techs/fabricators. | H34: Strong-inferred | I34: criticalsystemsinc.com
A35: Access Behavioral Health | B35: =COUNTIFS('Seasons Data'!G:G,A35,'Seasons Data'!E:E,"Y") -> 2 | C35: T6 | D35: Healthcare & Social Services | H35: Confirmed-NotMicron
A36: Ada County | B36: =COUNTIFS('Seasons Data'!G:G,A36,'Seasons Data'!E:E,"Y") -> 2 | C36: T6 | D36: Government, Military & Public Safety | H36: Confirmed-NotMicron
A37: Aqua-Tots Swim School | B37: =COUNTIFS('Seasons Data'!G:G,A37,'Seasons Data'!E:E,"Y") -> 2 | C37: T6 | D37: Education & Childcare | H37: Confirmed-NotMicron
A38: Boise State University | B38: =COUNTIFS('Seasons Data'!G:G,A38,'Seasons Data'!E:E,"Y") -> 2 | C38: T6 | D38: Education & Childcare | H38: Confirmed-NotMicron
A39: Columbia Electric Supply (Sonepar) | B39: =COUNTIFS('Seasons Data'!G:G,A39,'Seasons Data'!E:E,"Y") -> 2 | C39: T6 | D39: Wholesale, Transport & Logistics | E39: Industrial electrical products, automation, and smart-manufacturing distribution. | F39: Branch at 8645 Westpark St, Boise; NW distributor in the Sonepar family. | G39: No supplier-of-record evidence; incidental sales to fab subs plausible but classed as ordinary local distribution. | H39: Inferred | I39: cesboise.com
A40: Crumbl | B40: =COUNTIFS('Seasons Data'!G:G,A40,'Seasons Data'!E:E,"Y") -> 2 | C40: T6 | D40: Retail & Food Service | H40: Confirmed-NotMicron
A41: DHS / TSA | B41: =COUNTIFS('Seasons Data'!G:G,A41,'Seasons Data'!E:E,"Y") -> 2 | C41: T6 | D41: Government, Military & Public Safety | H41: Confirmed-NotMicron
A42: DaBella | B42: =COUNTIFS('Seasons Data'!G:G,A42,'Seasons Data'!E:E,"Y") -> 2 | C42: T6 | D42: Construction & Trades (non-Micron) | H42: Confirmed-NotMicron
A43: DoorDash | B43: =COUNTIFS('Seasons Data'!G:G,A43,'Seasons Data'!E:E,"Y") -> 2 | C43: T6 | D43: Gig economy | H43: Confirmed-NotMicron
A44: Eagle Vision One | B44: =COUNTIFS('Seasons Data'!G:G,A44,'Seasons Data'!E:E,"Y") -> 2 | C44: T6 | D44: Healthcare & Social Services | H44: Confirmed-NotMicron
A45: Horizon Air | B45: =COUNTIFS('Seasons Data'!G:G,A45,'Seasons Data'!E:E,"Y") -> 2 | C45: T6 | D45: Aerospace & Airlines | H45: Confirmed-NotMicron
A46: IHOP | B46: =COUNTIFS('Seasons Data'!G:G,A46,'Seasons Data'!E:E,"Y") -> 2 | C46: T6 | D46: Retail & Food Service | H46: Confirmed-NotMicron
A47: Intelligent Design Mechanical Solutions (IDS HVAC) | B47: =COUNTIFS('Seasons Data'!G:G,A47,'Seasons Data'!E:E,"Y") -> 2 | C47: T6 | D47: Construction & Trades (non-Micron) | E47: Residential and commercial HVAC install/service in the Treasure Valley. | F47: Garden City, ID. | G47: None; light resi/commercial focus, no industrial/cleanroom work found. | H47: Strong-inferred | I47: idshvac.com
A48: KHP (unresolved) | B48: =COUNTIFS('Seasons Data'!G:G,A48,'Seasons Data'!E:E,"Y") -> 2 | C48: T6 | D48: Unknown / unresolved | E48: No Boise/Meridian company 'KHP' identifiable. | F48: No Idaho entity located. | G48: None found. | H48: Weak-unverified | I48: —
A49: Kirton McConkie (law) | B49: =COUNTIFS('Seasons Data'!G:G,A49,'Seasons Data'!E:E,"Y") -> 2 | C49: T6 | D49: Financial, Legal & Professional | H49: Confirmed-NotMicron
A50: Mia Studio | B50: =COUNTIFS('Seasons Data'!G:G,A50,'Seasons Data'!E:E,"Y") -> 2 | C50: T6 | D50: Personal Services & Other Local | H50: Weak-unverified
A51: Norco, Inc. | B51: =COUNTIFS('Seasons Data'!G:G,A51,'Seasons Data'!E:E,"Y") -> 2 | C51: T6 | D51: Wholesale, Transport & Logistics | E51: Largest privately owned US welding, safety, medical and industrial gas supplier; 80+ branches across 7 western states. | F51: Headquartered in Boise. | G51: No Micron contract found; bulk fab gases come from majors — plausible jobsite welding-gas role only. | H51: Inferred | I51: norco-inc.com
A52: Overland Court Senior Living | B52: =COUNTIFS('Seasons Data'!G:G,A52,'Seasons Data'!E:E,"Y") -> 2 | C52: T6 | D52: Healthcare & Social Services | H52: Confirmed-NotMicron
A53: Paragon Corporate Housing | B53: =COUNTIFS('Seasons Data'!G:G,A53,'Seasons Data'!E:E,"Y") -> 2 | C53: T6 | D53: Corporate housing entity | H53: Confirmed-NotMicron
A54: Peak Living (property mgmt) | B54: =COUNTIFS('Seasons Data'!G:G,A54,'Seasons Data'!E:E,"Y") -> 2 | C54: T6 | D54: Financial, Legal & Professional | H54: Confirmed-NotMicron
A55: Rain Networks | B55: =COUNTIFS('Seasons Data'!G:G,A55,'Seasons Data'!E:E,"Y") -> 2 | C55: T6 | D55: Tech & Software (non-semi) | H55: Confirmed-NotMicron
A56: SkyWest Airlines | B56: =COUNTIFS('Seasons Data'!G:G,A56,'Seasons Data'!E:E,"Y") -> 2 | C56: T6 | D56: Aerospace & Airlines | H56: Confirmed-NotMicron
A57: Starbucks | B57: =COUNTIFS('Seasons Data'!G:G,A57,'Seasons Data'!E:E,"Y") -> 2 | C57: T6 | D57: Retail & Food Service | H57: Confirmed-NotMicron
A58: State of Idaho | B58: =COUNTIFS('Seasons Data'!G:G,A58,'Seasons Data'!E:E,"Y") -> 2 | C58: T6 | D58: Government, Military & Public Safety | H58: Confirmed-NotMicron
A59: T-Mobile | B59: =COUNTIFS('Seasons Data'!G:G,A59,'Seasons Data'!E:E,"Y") -> 2 | C59: T6 | D59: Tech & Software (non-semi) | H59: Confirmed-NotMicron
A60: The Eye Associates | B60: =COUNTIFS('Seasons Data'!G:G,A60,'Seasons Data'!E:E,"Y") -> 2 | C60: T6 | D60: Healthcare & Social Services | H60: Confirmed-NotMicron
A61: U.S. Air Force | B61: =COUNTIFS('Seasons Data'!G:G,A61,'Seasons Data'!E:E,"Y") -> 2 | C61: T6 | D61: Government, Military & Public Safety | H61: Confirmed-NotMicron
A62: U.S. Postal Service | B62: =COUNTIFS('Seasons Data'!G:G,A62,'Seasons Data'!E:E,"Y") -> 2 | C62: T6 | D62: Government, Military & Public Safety | H62: Confirmed-NotMicron
A63: University of Alaska | B63: =COUNTIFS('Seasons Data'!G:G,A63,'Seasons Data'!E:E,"Y") -> 2 | C63: T6 | D63: Education & Childcare | H63: Confirmed-NotMicron
A64: Hensel Phelps | B64: =COUNTIFS('Seasons Data'!G:G,A64,'Seasons Data'!E:E,"Y") -> 1 | C64: T2 | D64: Micron fab construction | E64: Large employee-owned national GC active in semiconductor fab construction. | F64: Greeley, CO HQ; active Boise presence. | G64: Listed among GCs/EPC contractors performing work on Micron's Boise fab project. | H64: Confirmed | I64: getfods.com
A65: Hoffman Construction Company | B65: =COUNTIFS('Seasons Data'!G:G,A65,'Seasons Data'!E:E,"Y") -> 1 | C65: T2 | D65: Micron fab construction | H65: Confirmed
A66: JH Kelly | B66: =COUNTIFS('Seasons Data'!G:G,A66,'Seasons Data'!E:E,"Y") -> 1 | C66: T2 | D66: Micron fab construction | H66: Confirmed
A67: Oregon Electric Group (OEG) | B67: =COUNTIFS('Seasons Data'!G:G,A67,'Seasons Data'!E:E,"Y") -> 1 | C67: T2 | D67: Micron fab construction | H67: Strong-inferred
A68: Phoenix Industrial | B68: =COUNTIFS('Seasons Data'!G:G,A68,'Seasons Data'!E:E,"Y") -> 1 | C68: T2 | D68: Micron fab construction | H68: Strong-inferred
A69: Southland Industries | B69: =COUNTIFS('Seasons Data'!G:G,A69,'Seasons Data'!E:E,"Y") -> 1 | C69: T2 | D69: Micron fab construction | E69: One of the largest national MEP design-build contractors (mechanical, piping, plumbing, controls, modular fabrication). | F69: No permanent Boise division, but actively recruiting MEP PMs/engineers/safety staff in Boise/Kuna ID for a 'high-impact, mission-critical project'. | G69: A national MEP giant staffing up in Boise for a mission-critical industrial project during the fab build is a strong fit for Micron ID1 mechanical scope. | H69: Strong-inferred | I69: southlandind.com
A70: W&W Steel Erectors (W&W|AFCO Steel) | B70: =COUNTIFS('Seasons Data'!G:G,A70,'Seasons Data'!E:E,"Y") -> 1 | C70: T2 | D70: Micron fab construction | E70: Erection arm of W&W|AFCO Steel, the largest structural steel fabricator/erector in the US; erects mega-fab steel packages (e.g., 80,000 tons at TSMC Phoenix). | F70: HQ Oklahoma City; traveling erection crews, no permanent Idaho office. | G70: ID1 involves ~70,000 tons of steel and W&W is the dominant US fab steel erector; an erector resident 20 miles from site during peak erection is a strong trade fit. | H70: Strong-inferred | I70: wwafcosteel.com
A71: Western Partitions, Inc. (WPI) | B71: =COUNTIFS('Seasons Data'!G:G,A71,'Seasons Data'!E:E,"Y") -> 1 | C71: T2 | D71: Micron fab construction | E71: One of the largest US interior/exterior subs: drywall, metal studs, prefab, acoustical, fireproofing; serves mission-critical/technology markets. | F71: HQ Lake Oswego, OR; Treasure Valley office in Caldwell, ID. | G71: No public Micron contract, but a top-tier NW mission-critical interiors sub with a Boise-area office and a $103K resident wage is consistent with fab support-building/interiors scope. | H71: Weak-inferred | I71: wpibuilds.com
A72: Atlas Technical Consultants (OneAtlas) | B72: =COUNTIFS('Seasons Data'!G:G,A72,'Seasons Data'!E:E,"Y") -> 1 | C72: T3 | D72: Micron eng/consulting/IT | E72: National environmental and infrastructure consulting, testing and inspection firm (~3,500 employees). | F72: Austin, TX HQ; Boise office at 2791 S Victory View Way plus Idaho Falls/Pocatello offices. | G72: Boise-area Atlas job postings explicitly reference staffing for the 'Micron Triton project', indicating active testing/inspection work on the Triton site. | H72: Strong-inferred | I72: ziprecruiter.com / oneatlas.com
A73: POWER Engineers (a WSP company) | B73: =COUNTIFS('Seasons Data'!G:G,A73,'Seasons Data'!E:E,"Y") -> 1 | C73: T3 | D73: Micron eng/consulting/IT | E73: Idaho-founded power delivery/substation/transmission engineering consultancy, acquired by WSP in 2024; longtime Idaho Power engineering consultant. | F73: HQ Hailey, ID with Meridian/Boise offices; now part of WSP. | G73: Aligned to Canyon Ridge workbook: POWER Engineers classified T3 there; Idaho power-delivery engineering consultant plausibly supporting fab power infrastructure. | H73: Inferred | I73: wsp.com
A74: Prime Controls, LP | B74: =COUNTIFS('Seasons Data'!G:G,A74,'Seasons Data'!E:E,"Y") -> 1 | C74: T3 | D74: Micron eng/consulting/IT | E74: Systems integration / I&C (FMCS, BMS/SCADA) for mega-fabs | F74: HQ Lewisville TX; traveling fab site staff | G74: Aligned to Canyon Ridge workbook: Prime Controls classified T3 there (3 residents); fab FMCS/I&C specialty. | H74: Inferred | I74: prime-controls.com
A75: Kurita America (Kurita Water Industries) | B75: =COUNTIFS('Seasons Data'!G:G,A75,'Seasons Data'!E:E,"Y") -> 1 | C75: T4 | D75: Semi equipment & materials | E75: Global leader in ultrapure water production, treatment chemicals, and turnkey UPW operations/maintenance for semiconductor fabs. | F75: US HQ Minneapolis; Kurita job postings active in Boise, ID. | G75: Kurita's CEO publicly stated the company would bid to supply ultrapure water for Micron's Boise fab and hire several hundred Boise-area workers; Boise postings indicate staffing that scope. | H75: Confirmed | I75: idahonews.com
A76: Photronics, Inc. | B76: =COUNTIFS('Seasons Data'!G:G,A76,'Seasons Data'!E:E,"Y") -> 1 | C76: T4 | D76: Semi equipment & materials | E76: World's largest merchant photomask maker; operates an advanced photomask NanoFab in Boise. | F76: HQ Brookfield CT; Boise ID photomask facility adjacent to Micron's campus, originally the Micron-Photronics 'MP Mask' JV. | G76: Facility originated as a JV with Micron with a technology license and long-term supply arrangement; Boise site supplies Micron. | H76: Confirmed | I76: photronics.com
A77: Apple | B77: =COUNTIFS('Seasons Data'!G:G,A77,'Seasons Data'!E:E,"Y") -> 1 | C77: T5 | D77: Semiconductor (non-Micron) | H77: Confirmed-NotMicron
A78: Schweitzer Engineering Laboratories (SEL) | B78: =COUNTIFS('Seasons Data'!G:G,A78,'Seasons Data'!E:E,"Y") -> 1 | C78: T5 | D78: Semiconductor (non-Micron) | E78: Employee-owned maker of protective relays and power-system protection/automation equipment; operates its own chip fab in Moscow, ID. | F78: HQ Pullman WA; Boise office with a $25M, 170K sf Boise expansion underway. | G78: No Micron relationship — independent tech manufacturer with its own semiconductor operations. | H78: Confirmed-NotMicron | I78: selinc.com
A79: 208 Home Care | B79: =COUNTIFS('Seasons Data'!G:G,A79,'Seasons Data'!E:E,"Y") -> 1 | C79: T6 | D79: Healthcare & Social Services | H79: Confirmed-NotMicron
A80: 208 Roofing | B80: =COUNTIFS('Seasons Data'!G:G,A80,'Seasons Data'!E:E,"Y") -> 1 | C80: T6 | D80: Construction & Trades (non-Micron) | H80: Confirmed-NotMicron
A81: A Child's Heart Learning Center | B81: =COUNTIFS('Seasons Data'!G:G,A81,'Seasons Data'!E:E,"Y") -> 1 | C81: T6 | D81: Education & Childcare | H81: Confirmed-NotMicron
A82: A-1 Heating & Air | B82: =COUNTIFS('Seasons Data'!G:G,A82,'Seasons Data'!E:E,"Y") -> 1 | C82: T6 | D82: Construction & Trades (non-Micron) | H82: Confirmed-NotMicron
A83: ALLWEST Testing & Engineering, Inc. | B83: =COUNTIFS('Seasons Data'!G:G,A83,'Seasons Data'!E:E,"Y") -> 1 | C83: T6 | D83: Engineering & Technical Services | E83: Employee-owned geotechnical, construction materials testing, and special inspections firm serving the Inland Northwest. | F83: Offices in Meridian, Hayden, and Lewiston ID; Spokane/Tri-Cities WA; Missoula MT. | G83: No public evidence of Micron/Triton QA-QC work; plausible as a leading local CMT/special-inspection firm but unverified. | H83: Weak-unverified | I83: allwesttesting.com
A84: Ace Hardware | B84: =COUNTIFS('Seasons Data'!G:G,A84,'Seasons Data'!E:E,"Y") -> 1 | C84: T6 | D84: Retail & Food Service | H84: Confirmed-NotMicron
A85: Ada County Sheriff's Office | B85: =COUNTIFS('Seasons Data'!G:G,A85,'Seasons Data'!E:E,"Y") -> 1 | C85: T6 | D85: Government, Military & Public Safety | H85: Confirmed-NotMicron
A86: Advanced Heating & Cooling | B86: =COUNTIFS('Seasons Data'!G:G,A86,'Seasons Data'!E:E,"Y") -> 1 | C86: T6 | D86: Construction & Trades (non-Micron) | H86: Confirmed-NotMicron
A87: Air Methods | B87: =COUNTIFS('Seasons Data'!G:G,A87,'Seasons Data'!E:E,"Y") -> 1 | C87: T6 | D87: Healthcare & Social Services | H87: Confirmed-NotMicron
A88: Allegheny General Hospital | B88: =COUNTIFS('Seasons Data'!G:G,A88,'Seasons Data'!E:E,"Y") -> 1 | C88: T6 | D88: Healthcare & Social Services | H88: Confirmed-NotMicron
A89: Amazon Flex / Lyft | B89: =COUNTIFS('Seasons Data'!G:G,A89,'Seasons Data'!E:E,"Y") -> 1 | C89: T6 | D89: Gig economy | H89: Confirmed-NotMicron
A90: Americor | B90: =COUNTIFS('Seasons Data'!G:G,A90,'Seasons Data'!E:E,"Y") -> 1 | C90: T6 | D90: Financial, Legal & Professional | H90: Confirmed-NotMicron
A91: Apace Labor & Construction (Apace Demolition) | B91: =COUNTIFS('Seasons Data'!G:G,A91,'Seasons Data'!E:E,"Y") -> 1 | C91: T6 | D91: Construction & Trades (non-Micron) | E91: Meridian, ID contractor doing residential remodel demolition, roofing tear-off, concrete, and general remodel work. | F91: HQ Meridian, ID. | G91: None; small residential-focused local contractor. | H91: Confirmed-NotMicron | I91: apaceidaho.com
A92: Arizona Mohs Surgery | B92: =COUNTIFS('Seasons Data'!G:G,A92,'Seasons Data'!E:E,"Y") -> 1 | C92: T6 | D92: Healthcare & Social Services | H92: Confirmed-NotMicron
A93: Asbury (church/nonprofit) | B93: =COUNTIFS('Seasons Data'!G:G,A93,'Seasons Data'!E:E,"Y") -> 1 | C93: T6 | D93: Nonprofit & Religious | H93: Weak-unverified
A94: Avery's House | B94: =COUNTIFS('Seasons Data'!G:G,A94,'Seasons Data'!E:E,"Y") -> 1 | C94: T6 | D94: Healthcare & Social Services | H94: Confirmed-NotMicron
A95: Axiota Animal Health | B95: =COUNTIFS('Seasons Data'!G:G,A95,'Seasons Data'!E:E,"Y") -> 1 | C95: T6 | D95: Healthcare & Social Services | H95: Confirmed-NotMicron
A96: Axis Innovations | B96: =COUNTIFS('Seasons Data'!G:G,A96,'Seasons Data'!E:E,"Y") -> 1 | C96: T6 | D96: Financial, Legal & Professional | H96: Weak-unverified
A97: Axtell Painting | B97: =COUNTIFS('Seasons Data'!G:G,A97,'Seasons Data'!E:E,"Y") -> 1 | C97: T6 | D97: Construction & Trades (non-Micron) | H97: Confirmed-NotMicron
A98: Aztec Welding Services | B98: =COUNTIFS('Seasons Data'!G:G,A98,'Seasons Data'!E:E,"Y") -> 1 | C98: T6 | D98: Construction & Trades (non-Micron) | E98: Industrial piping, structural welding, sanitary (food & beverage) welds, tank/pipe fabrication. | F98: Caldwell/Homedale, ID. | G98: Client base is food/bev/ag; no Micron or mechanical-sub connection found. | H98: Inferred | I98: aztecwelding.com
A99: BB Bridal | B99: =COUNTIFS('Seasons Data'!G:G,A99,'Seasons Data'!E:E,"Y") -> 1 | C99: T6 | D99: Retail & Food Service | H99: Confirmed-NotMicron
A100: BHI, Inc. | B100: =COUNTIFS('Seasons Data'!G:G,A100,'Seasons Data'!E:E,"Y") -> 1 | C100: T6 | D100: Construction & Trades (non-Micron) | E100: Vernal, UT-based national EPC and heavy-civil GC in energy, infrastructure, building and mining markets. | F100: No Boise office identified; national footprint reaches the Intermountain West (identity ambiguous). | G100: No evidence of Micron Boise/Triton involvement found. | H100: Weak-unverified | I100: bhico.com
A101: Bad Boy Burgers | B101: =COUNTIFS('Seasons Data'!G:G,A101,'Seasons Data'!E:E,"Y") -> 1 | C101: T6 | D101: Retail & Food Service | H101: Confirmed-NotMicron
...

Sheet Employers - Canyon Ridge
A1: Canyon Ridge — Standardized Employer Summary (all 151 employers)
A2: Carried over verbatim from Canyon Ridge Employer / Micron Analysis (2026.06.24). Counts are occupant-level (Primary + Co-Applicant).
A4: Canyon Ridge - Top Employers | B4: Residents | C4: Tier | D4: Category | E4: What they do | F4: HQ / Boise presence | G4: Micron relationship & evidence | H4: Confidence | I4: Source
A5: Micron Technology | B5: 89 | C5: T1 | D5: Micron (direct employer) | E5: DRAM & NAND memory/storage chip designer & manufacturer | F5: Boise, ID (HQ, 8000 S Federal Way) | G5: THE employer/anchor. ~$50B "Triton" Boise expansion: two new DRAM fabs, first wafers ~2H2027, ~17,000 projected ID jobs. Property is adjacent worker housing. | H5: Confirmed | I5: micron.com/us-expansion/id
A6: Oregon Electric Group (OEG) | B6: 12 | C6: T2 | D6: Micron construction subcontractor (building the fabs) | E6: Electrical contractor (mission-critical/high-tech/industrial) | F6: Portland, OR (MDU Construction Services); IBEW 291 signatory | G6: Variants incl. "Oregon Electric"/"Oregon electric group"; IBEW 291 dispatch on Micron PLA; fab electrical fit. | H6: Strong-inferred | I6: oeg.us.com; ibew291.org
A7: Hoffman Structures, Inc. | B7: 10 | C7: T2 | D7: Micron construction subcontractor (building the fabs) | E7: Structural/concrete self-perform affiliate of Hoffman Construction | F7: Portland, OR | G7: In-house concrete arm of Hoffman; concrete scope on Triton via parent GC role (inferred). | H7: Strong-inferred | I7: wikipedia/Hoffman Construction
A8: Performance Contracting, Inc. (PCI) | B8: 10 | C8: T2 | D8: Micron construction subcontractor (building the fabs) | E8: Specialty contractor: cleanroom build-out & insulation for microelectronics | F8: Lenexa, KS; Boise location | G8: Cleanroom/microelectronics specialty + Boise presence; classic fab cleanroom sub. | H8: Strong-inferred | I8: performancecontracting.com
A9: Phoenix Industrial | B9: 9 | C9: T2 | D9: Micron construction subcontractor (building the fabs) | E9: Heavy-industrial GC (civil, steel, process piping, electrical); a MasTec company | F9: Vancouver, WA (MasTec subsidiary); Boise job postings | G9: MasTec-owned ("Mas tec - phoenix industrial" per a resident); Boise hiring + industrial scope fit the fab build. | H9: Strong-inferred | I9: phxind.com/about
A10: Hoffman Construction Company | B10: 8 | C10: T2 | D10: Micron construction subcontractor (building the fabs) | E10: General contractor (largest in Pacific NW) | F10: Portland, OR (Boise offices) | G10: CONFIRMED: became GC of the Micron Triton build ~Sept 2025 after Exyte was discontinued. | H10: Confirmed | I10: boisedev.com 2025/11/24
A11: Trew Contracting Solutions | B11: 8 | C11: T2 | D11: Micron construction subcontractor (building the fabs) | E11: Site/civil & general contracting (TCS) labor | F11: Idaho | G11: Idaho site contractor (variants "Tcs construction"/"TCS, LLC"); resident laborers/yard foreman/project engineer on the build. | H11: Inferred | I11: —
A12: United States Air Force | B12: 7 | C12: T6 | D12: Unrelated / local | E12: U.S. military service branch | F12: Mountain Home AFB (~40mi SE) & Idaho ANG, Gowen Field | G12: Military. No Micron tie. | H12: Confirmed-NotMicron | I12: af.mil
A13: JH Kelly | B13: 4 | C13: T2 | D13: Micron construction subcontractor (building the fabs) | E13: Industrial mechanical contractor / self-perform GC | F13: Longview, WA; Boise jobsites | G13: CONFIRMED: dedicated project page "Micron Project Triton F08B"; ~97,000 lf process piping installed. | H13: Confirmed | I13: jhkelly.com/projects/micron-project-triton-f08b
A14: SME Steel Contractors | B14: 4 | C14: T2 | D14: Micron construction subcontractor (building the fabs) | E14: Structural steel fabricator/erector (SME Industries) | F14: West Jordan, UT (Western US) | G14: Steel erection trade; major Western steel contractor on large fab/industrial builds. Resident ironworkers/journeymen. | H14: Strong-inferred | I14: smesteel.com
A15: Suntec Concrete | B15: 4 | C15: T2 | D15: Micron construction subcontractor (building the fabs) | E15: Large structural/cast-in-place concrete contractor | F15: Phoenix, AZ | G15: Major Southwest concrete contractor active on semiconductor megaprojects; resident cement masons/finishers/laborers. | H15: Strong-inferred | I15: suntecconcrete.com
A16: St. Luke's Health System | B16: 4 | C16: T6 | D16: Unrelated / local | E16: Idaho's largest health system (hospitals) | F16: Boise, ID | G16: Local healthcare. No Micron tie. | H16: Confirmed-NotMicron | I16: stlukesonline.org
... A155: Yardi Systems | B155: 1 | C155: T6 | D155: Unrelated / local | E155: Property-management software | F155: Santa Barbara, CA | G155: Software. No Micron tie. | H155: Confirmed-NotMicron | I155: yardi.com

Sheet Unit Coverage Detail
A1: Unit-level household income, rent & coverage — both properties
A2: One row per unit with demographic data. HH Income = sum of qualifying occupant incomes (excl. guarantors, copied records, ≥$1M outliers). Rent: Canyon Ridge = scheduled rent (Entrata); Seasons = contract rent (rentres) from 07/09/2026 rent roll. Multiple = HH income ÷ (12 × rent).
A4: Property | B4: Unit | C4: HH Income | D4: Contract Rent | E4: Income Multiple | F4: ≥3x Rent | G4: Micron-related unit (T1–T4) | H4: Micron direct unit (T1)
A5: Canyon Ridge | B5: A-101 | C5: 105000 | D5: 1725 | E5: =IF(AND(ISNUMBER(C5),ISNUMBER(D5)),C5/(12*D5),"") -> 5.0724638 | F5: =IF(E5="","",IF(E5>=3,"Y","N")) -> Y | G5: Y | H5: Y
A6: Canyon Ridge | B6: A-102 | C6: 8310000 | D6: 2560 | E6: =IF(AND(ISNUMBER(C6),ISNUMBER(D6)),C6/(12*D6),"") -> 270.50781 | F6: =IF(E6="","",IF(E6>=3,"Y","N")) -> Y | G6: Y | H6: N
A7: Canyon Ridge | B7: A-103 | C7: 391820 | D7: 2375 | E7: =IF(AND(ISNUMBER(C7),ISNUMBER(D7)),C7/(12*D7),"") -> 13.74807 | F7: =IF(E7="","",IF(E7>=3,"Y","N")) -> Y | G7: Y | H7: N
A8: Canyon Ridge | B8: A-104 | C8: 182500 | D8: 1840 | E8: =IF(AND(ISNUMBER(C8),ISNUMBER(D8)),C8/(12*D8),"") -> 8.2653986 | F8: =IF(E8="","",IF(E8>=3,"Y","N")) -> Y | G8: Y | H8: Y
A9: Canyon Ridge | B9: A-105 | C9: 216000 | D9: 2115 | E9: =IF(AND(ISNUMBER(C9),ISNUMBER(D9)),C9/(12*D9),"") -> 8.5106383 | F9: =IF(E9="","",IF(E9>=3,"Y","N")) -> Y | G9: Y | H9: N
A10: Canyon Ridge | B10: A-106 | D10: 1842 | E10: =IF(AND(ISNUMBER(C10),ISNUMBER(D10)),C10/(12*D10),"") | F10: =IF(E10="","",IF(E10>=3,"Y","N")) | G10: N | H10: N
A11: Canyon Ridge | B11: A-107 | C11: 146000 | D11: 1525 | E11: =IF(AND(ISNUMBER(C11),ISNUMBER(D11)),C11/(12*D11),"") -> 7.9781421 | F11: =IF(E11="","",IF(E11>=3,"Y","N")) -> Y | G11: Y | H11: N
A12: Canyon Ridge | B12: A-108 | D12: 1868 | E12: =IF(AND(ISNUMBER(C12),ISNUMBER(D12)),C12/(12*D12),"") | F12: =IF(E12="","",IF(E12>=3,"Y","N")) | G12: N | H12: N
A13: Canyon Ridge | B13: A-109 | C13: 144600 | D13: 1740 | E13: =IF(AND(ISNUMBER(C13),ISNUMBER(D13)),C13/(12*D13),"") -> 6.9252874 | F13: =IF(E13="","",IF(E13>=3,"Y","N")) -> Y | G13: Y | H13: N
A14: Canyon Ridge | B14: A-110 | C14: 65000 | D14: 2250 | E14: =IF(AND(ISNUMBER(C14),ISNUMBER(D14)),C14/(12*D14),"") -> 2.4074074 | F14: =IF(E14="","",IF(E14>=3,"Y","N")) -> N | G14: N | H14: N
A15: Canyon Ridge | B15: A-112 | C15: 62000 | D15: 1895 | E15: =IF(AND(ISNUMBER(C15),ISNUMBER(D15)),C15/(12*D15),"") -> 2.7264732 | F15: =IF(E15="","",IF(E15>=3,"Y","N")) -> N | G15: N | H15: N
A16: Canyon Ridge | B16: A-113 | C16: 401000 | D16: 2610 | E16: =IF(AND(ISNUMBER(C16),ISNUMBER(D16)),C16/(12*D16),"") -> 12.803321 | F16: =IF(E16="","",IF(E16>=3,"Y","N")) -> Y | G16: Y | H16: N
A17: Canyon Ridge | B17: A-114 | C17: 87312 | D17: 1865 | E17: =IF(AND(ISNUMBER(C17),ISNUMBER(D17)),C17/(12*D17),"") -> 3.9013405 | F17: =IF(E17="","",IF(E17>=3,"Y","N")) -> Y | G17: N | H17: N
A18: Canyon Ridge | B18: A-115 | C18: 129380.2 | D18: 2285 | E18: =IF(AND(ISNUMBER(C18),ISNUMBER(D18)),C18/(12*D18),"") -> 4.718461 | F18: =IF(E18="","",IF(E18>=3,"Y","N")) -> Y | G18: N | H18: N
A19: Canyon Ridge | B19: A-116 | D19: 2185 | E19: =IF(AND(ISNUMBER(C19),ISNUMBER(D19)),C19/(12*D19),"") | F19: =IF(E19="","",IF(E19>=3,"Y","N")) | G19: N | H19: N
A20: Canyon Ridge | B20: A-201 | D20: 1975 | E20: =IF(AND(ISNUMBER(C20),ISNUMBER(D20)),C20/(12*D20),"") | F20: =IF(E20="","",IF(E20>=3,"Y","N")) | G20: N | H20: N
A21: Canyon Ridge | B21: A-202 | C21: 180000 | D21: 2345 | E21: =IF(AND(ISNUMBER(C21),ISNUMBER(D21)),C21/(12*D21),"") -> 6.3965885 | F21: =IF(E21="","",IF(E21>=3,"Y","N")) -> Y | G21: N | H21: N
A22: Canyon Ridge | B22: A-203 | C22: 81608.04 | D22: 1795 | E22: =IF(AND(ISNUMBER(C22),ISNUMBER(D22)),C22/(12*D22),"") -> 3.7886741 | F22: =IF(E22="","",IF(E22>=3,"Y","N")) -> Y | G22: N | H22: N
A23: Canyon Ridge | B23: A-204 | C23: 130000 | D23: 1895 | E23: =IF(AND(ISNUMBER(C23),ISNUMBER(D23)),C23/(12*D23),"") -> 5.7167986 | F23: =IF(E23="","",IF(E23>=3,"Y","N")) -> Y | G23: Y | H23: N
A24: Canyon Ridge | B24: A-205 | C24: 168400 | D24: 1850 | E24: =IF(AND(ISNUMBER(C24),ISNUMBER(D24)),C24/(12*D24),"") -> 7.5855856 | F24: =IF(E24="","",IF(E24>=3,"Y","N")) -> Y | G24: N | H24: N
A25: Canyon Ridge | B25: A-206 | D25: 1863 | E25: =IF(AND(ISNUMBER(C25),ISNUMBER(D25)),C25/(12*D25),"") | F25: =IF(E25="","",IF(E25>=3,"Y","N")) | G25: N | H25: N
A26: Canyon Ridge | B26: A-207 | C26: 78250 | D26: 1495 | E26: =IF(AND(ISNUMBER(C26),ISNUMBER(D26)),C26/(12*D26),"") -> 4.3617614 | F26: =IF(E26="","",IF(E26>=3,"Y","N")) -> Y | G26: Y | H26: N
A27: Canyon Ridge | B27: A-208 | D27: 1850 | E27: =IF(AND(ISNUMBER(C27),ISNUMBER(D27)),C27/(12*D27),"") | F27: =IF(E27="","",IF(E27>=3,"Y","N")) | G27: N | H27: N
A28: Canyon Ridge | B28: A-209 | D28: 2000 | E28: =IF(AND(ISNUMBER(C28),ISNUMBER(D28)),C28/(12*D28),"") | F28: =IF(E28="","",IF(E28>=3,"Y","N")) | G28: N | H28: N
A29: Canyon Ridge | B29: A-210 | C29: 328000 | D29: 1895 | E29: =IF(AND(ISNUMBER(C29),ISNUMBER(D29)),C29/(12*D29),"") -> 14.423923 | F29: =IF(E29="","",IF(E29>=3,"Y","N")) -> Y | G29: Y | H29: Y
A30: Canyon Ridge | B30: A-211 | C30: 50000 | D30: 2155 | E30: =IF(AND(ISNUMBER(C30),ISNUMBER(D30)),C30/(12*D30),"") -> 1.933488 | F30: =IF(E30="","",IF(E30>=3,"Y","N")) -> N | G30: N | H30: N
A31: Canyon Ridge | B31: A-212 | C31: 206000 | D31: 1995 | E31: =IF(AND(ISNUMBER(C31),ISNUMBER(D31)),C31/(12*D31),"") -> 8.6048454 | F31: =IF(E31="","",IF(E31>=3,"Y","N")) -> Y | G31: Y | H31: Y
A32: Canyon Ridge | B32: A-213 | C32: 176800 | D32: 2495 | E32: =IF(AND(ISNUMBER(C32),ISNUMBER(D32)),C32/(12*D32),"") -> 5.9051436 | F32: =IF(E32="","",IF(E32>=3,"Y","N")) -> Y | G32: Y | H32: N
A33: Canyon Ridge | B33: A-214 | C33: 432000 | D33: 2410 | E33: =IF(AND(ISNUMBER(C33),ISNUMBER(D33)),C33/(12*D33),"") -> 14.937759 | F33: =IF(E33="","",IF(E33>=3,"Y","N")) -> Y | G33: Y | H33: N
A34: Canyon Ridge | B34: A-215 | C34: 183000 | D34: 2325 | E34: =IF(AND(ISNUMBER(C34),ISNUMBER(D34)),C34/(12*D34),"") -> 6.5591398 | F34: =IF(E34="","",IF(E34>=3,"Y","N")) -> Y | G34: Y | H34: Y
A35: Canyon Ridge | B35: A-216 | C35: 143000 | D35: 2275 | E35: =IF(AND(ISNUMBER(C35),ISNUMBER(D35)),C35/(12*D35),"") -> 5.2380952 | F35: =IF(E35="","",IF(E35>=3,"Y","N")) -> Y | G35: Y | H35: N
A36: Canyon Ridge | B36: A-301 | C36: 125000 | D36: 1925 | E36: =IF(AND(ISNUMBER(C36),ISNUMBER(D36)),C36/(12*D36),"") -> 5.4112554 | F36: =IF(E36="","",IF(E36>=3,"Y","N")) -> Y | G36: Y | H36: N
A37: Canyon Ridge | B37: A-302 | D37: 2520 | E37: =IF(AND(ISNUMBER(C37),ISNUMBER(D37)),C37/(12*D37),"") | F37: =IF(E37="","",IF(E37>=3,"Y","N")) | G37: N | H37: N
A38: Canyon Ridge | B38: A-303 | C38: 290000 | D38: 2510 | E38: =IF(AND(ISNUMBER(C38),ISNUMBER(D38)),C38/(12*D38),"") -> 9.6281541 | F38: =IF(E38="","",IF(E38>=3,"Y","N")) -> Y | G38: Y | H38: N
A39: Canyon Ridge | B39: A-304 | C39: 321500 | D39: 2170 | E39: =IF(AND(ISNUMBER(C39),ISNUMBER(D39)),C39/(12*D39),"") -> 12.34639 | F39: =IF(E39="","",IF(E39>=3,"Y","N")) -> Y | G39: Y | H39: Y
A40: Canyon Ridge | B40: A-305 | C40: 80400 | D40: 2185 | E40: =IF(AND(ISNUMBER(C40),ISNUMBER(D40)),C40/(12*D40),"") -> 3.0663616 | F40: =IF(E40="","",IF(E40>=3,"Y","N")) -> Y | G40: Y | H40: Y
A41: Canyon Ridge | B41: A-306 | D41: 1885 | E41: =IF(AND(ISNUMBER(C41),ISNUMBER(D41)),C41/(12*D41),"") | F41: =IF(E41="","",IF(E41>=3,"Y","N")) | G41: N | H41: N
A42: Canyon Ridge | B42: A-307 | C42: 83000 | D42: 1650 | E42: =IF(AND(ISNUMBER(C42),ISNUMBER(D42)),C42/(12*D42),"") -> 4.1919192 | F42: =IF(E42="","",IF(E42>=3,"Y","N")) -> Y | G42: Y | H42: Y
A43: Canyon Ridge | B43: A-308 | D43: 1905 | E43: =IF(AND(ISNUMBER(C43),ISNUMBER(D43)),C43/(12*D43),"") | F43: =IF(E43="","",IF(E43>=3,"Y","N")) | G43: N | H43: N
A44: Canyon Ridge | B44: A-309 | C44: 406000 | D44: 2050 | E44: =IF(AND(ISNUMBER(C44),ISNUMBER(D44)),C44/(12*D44),"") -> 16.504065 | F44: =IF(E44="","",IF(E44>=3,"Y","N")) -> Y | G44: Y | H44: Y
A45: Canyon Ridge | B45: A-310 | C45: 230000 | D45: 1920 | E45: =IF(AND(ISNUMBER(C45),ISNUMBER(D45)),C45/(12*D45),"") -> 9.9826389 | F45: =IF(E45="","",IF(E45>=3,"Y","N")) -> Y | G45: Y | H45: Y
A46: Canyon Ridge | B46: A-311 | C46: 350000 | D46: 2000 | E46: =IF(AND(ISNUMBER(C46),ISNUMBER(D46)),C46/(12*D46),"") -> 14.583333 | F46: =IF(E46="","",IF(E46>=3,"Y","N")) -> Y | G46: Y | H46: Y
A47: Canyon Ridge | B47: A-312 | C47: 96000 | D47: 1850 | E47: =IF(AND(ISNUMBER(C47),ISNUMBER(D47)),C47/(12*D47),"") -> 4.3243243 | F47: =IF(E47="","",IF(E47>=3,"Y","N")) -> Y | G47: Y | H47: Y
A48: Canyon Ridge | B48: A-313 | C48: 296400 | D48: 2495 | E48: =IF(AND(ISNUMBER(C48),ISNUMBER(D48)),C48/(12*D48),"") -> 9.8997996 | F48: =IF(E48="","",IF(E48>=3,"Y","N")) -> Y | G48: Y | H48: N
A49: Canyon Ridge | B49: A-314 | C49: 120000 | D49: 1945 | E49: =IF(AND(ISNUMBER(C49),ISNUMBER(D49)),C49/(12*D49),"") -> 5.1413882 | F49: =IF(E49="","",IF(E49>=3,"Y","N")) -> Y | G49: Y | H49: Y
A50: Canyon Ridge | B50: A-315 | C50: 90000 | D50: 2375 | E50: =IF(AND(ISNUMBER(C50),ISNUMBER(D50)),C50/(12*D50),"") -> 3.1578947 | F50: =IF(E50="","",IF(E50>=3,"Y","N")) -> Y | G50: Y | H50: Y
A51: Canyon Ridge | B51: A-401 | C51: 63000 | D51: 2160 | E51: =IF(AND(ISNUMBER(C51),ISNUMBER(D51)),C51/(12*D51),"") -> 2.4305556 | F51: =IF(E51="","",IF(E51>=3,"Y","N")) -> N | G51: Y | H51: N
A52: Canyon Ridge | B52: A-402 | C52: 258000 | D52: 2330 | E52: =IF(AND(ISNUMBER(C52),ISNUMBER(D52)),C52/(12*D52),"") -> 9.2274678 | F52: =IF(E52="","",IF(E52>=3,"Y","N")) -> Y | G52: Y | H52: Y
A53: Canyon Ridge | B53: A-403 | C53: 72000 | D53: 2105 | E53: =IF(AND(ISNUMBER(C53),ISNUMBER(D53)),C53/(12*D53),"") -> 2.8503563 | F53: =IF(E53="","",IF(E53>=3,"Y","N")) -> N | G53: N | H53: N
A54: Canyon Ridge | B54: A-404 | C54: 71616 | D54: 2175 | E54: =IF(AND(ISNUMBER(C54),ISNUMBER(D54)),C54/(12*D54),"") -> 2.743908 | F54: =IF(E54="","",IF(E54>=3,"Y","N")) -> N | G54: N | H54: N
A55: Canyon Ridge | B55: A-405 | C55: 100440 | D55: 1875 | E55: =IF(AND(ISNUMBER(C55),ISNUMBER(D55)),C55/(12*D55),"") -> 4.464 | F55: =IF(E55="","",IF(E55>=3,"Y","N")) -> Y | G55: N | H55: N
... A62: Canyon Ridge | B62: A-412 | C62: 553600 | D62: 2300 | E62: =IF(AND(ISNUMBER(C62),ISNUMBER(D62)),C62/(12*D62),"") -> 20.057971 | F62: =IF(E62="","",IF(E62>=3,"Y","N")) -> Y | G62: Y | H62: N
A63: Canyon Ridge | B63: A-413 | D63: 2500 | E63: =IF(AND(ISNUMBER(C63),ISNUMBER(D63)),C63/(12*D63),"") | F63: =IF(E63="","",IF(E63>=3,"Y","N")) | G63: N | H63: N
A64: Canyon Ridge | B64: A-414 | C64: 98404.8 | D64: 2065 | E64: =IF(AND(ISNUMBER(C64),ISNUMBER(D64)),C64/(12*D64),"") -> 3.971138 | F64: =IF(E64="","",IF(E64>=3,"Y","N")) -> Y | G64: Y | H64: N
A65: Canyon Ridge | B65: A-415 | C65: 90000 | D65: 2180 | E65: =IF(AND(ISNUMBER(C65),ISNUMBER(D65)),C65/(12*D65),"") -> 3.440367 | F65: =IF(E65="","",IF(E65>=3,"Y","N")) -> Y | G65: N | H65: N
A66: Canyon Ridge | B66: A-416 | C66: 228800 | D66: 2340 | E66: =IF(AND(ISNUMBER(C66),ISNUMBER(D66)),C66/(12*D66),"") -> 8.1481481 | F66: =IF(E66="","",IF(E66>=3,"Y","N")) -> Y | G66: Y | H66: N
A67: Canyon Ridge | B67: B-101 | C67: 156000 | D67: 2400 | E67: =IF(AND(ISNUMBER(C67),ISNUMBER(D67)),C67/(12*D67),"") -> 5.4166667 | F67: =IF(E67="","",IF(E67>=3,"Y","N")) -> Y | G67: Y | H67: N
A68: Canyon Ridge | B68: B-102 | C68: 147000 | D68: 2280 | E68: =IF(AND(ISNUMBER(C68),ISNUMBER(D68)),C68/(12*D68),"") -> 5.372807 | F68: =IF(E68="","",IF(E68>=3,"Y","N")) -> Y | G68: Y | H68: Y
A69: Canyon Ridge | B69: B-103 | C69: 72000 | D69: 2005 | E69: =IF(AND(ISNUMBER(C69),ISNUMBER(D69)),C69/(12*D69),"") -> 2.9925187 | F69: =IF(E69="","",IF(E69>=3,"Y","N")) -> N | G69: Y | H69: N
A70: Canyon Ridge | B70: B-104 | D70: 1855 | E70: =IF(AND(ISNUMBER(C70),ISNUMBER(D70)),C70/(12*D70),"") | F70: =IF(E70="","",IF(E70>=3,"Y","N")) | G70: N | H70: N
A71: Canyon Ridge | B71: B-105 | D71: 1855 | E71: =IF(AND(ISNUMBER(C71),ISNUMBER(D71)),C71/(12*D71),"") | F71: =IF(E71="","",IF(E71>=3,"Y","N")) | G71: N | H71: N
A72: Canyon Ridge | B72: B-106 | C72: 130000 | D72: 2005 | E72: =IF(AND(ISNUMBER(C72),ISNUMBER(D72)),C72/(12*D72),"") -> 5.4031588 | F72: =IF(E72="","",IF(E72>=3,"Y","N")) -> Y | G72: Y | H72: Y
A73: Canyon Ridge | B73: B-107 | D73: 2105 | E73: =IF(AND(ISNUMBER(C73),ISNUMBER(D73)),C73/(12*D73),"") | F73: =IF(E73="","",IF(E73>=3,"Y","N")) | G73: N | H73: N
A74: Canyon Ridge | B74: B-108 | C74: 108000 | D74: 2355 | E74: =IF(AND(ISNUMBER(C74),ISNUMBER(D74)),C74/(12*D74),"") -> 3.8216561 | F74: =IF(E74="","",IF(E74>=3,"Y","N")) -> Y | G74: Y | H74: Y
A75: Canyon Ridge | B75: B-109 | C75: 240000 | D75: 2240 | E75: =IF(AND(ISNUMBER(C75),ISNUMBER(D75)),C75/(12*D75),"") -> 8.9285714 | F75: =IF(E75="","",IF(E75>=3,"Y","N")) -> Y | G75: Y | H75: N
A76: Canyon Ridge | B76: B-110 | C76: 376804 | D76: 1895 | E76: =IF(AND(ISNUMBER(C76),ISNUMBER(D76)),C76/(12*D76),"") -> 16.570097 | F76: =IF(E76="","",IF(E76>=3,"Y","N")) -> Y | G76: Y | H76: N
A77: Canyon Ridge | B77: B-111 | D77: 1855 | E77: =IF(AND(ISNUMBER(C77),ISNUMBER(D77)),C77/(12*D77),"") | F77: =IF(E77="","",IF(E77>=3,"Y","N")) | G77: N | H77: N
A78: Canyon Ridge | B78: B-112 | C78: 53790 | D78: 1785 | E78: =IF(AND(ISNUMBER(C78),ISNUMBER(D78)),C78/(12*D78),"") -> 2.5112045 | F78: =IF(E78="","",IF(E78>=3,"Y","N")) -> N | G78: N | H78: N
A79: Canyon Ridge | B79: B-113 | C79: 302900 | D79: 2005 | E79: =IF(AND(ISNUMBER(C79),ISNUMBER(D79)),C79/(12*D79),"") -> 12.58936 | F79: =IF(E79="","",IF(E79>=3,"Y","N")) -> Y | G79: Y | H79: N
A80: Canyon Ridge | B80: B-114 | C80: 117000 | D80: 2010 | E80: =IF(AND(ISNUMBER(C80),ISNUMBER(D80)),C80/(12*D80),"") -> 4.8507463 | F80: =IF(E80="","",IF(E80>=3,"Y","N")) -> Y | G80: Y | H80: N
A81: Canyon Ridge | B81: B-115 | C81: 110000 | D81: 2005 | E81: =IF(AND(ISNUMBER(C81),ISNUMBER(D81)),C81/(12*D81),"") -> 4.5719036 | F81: =IF(E81="","",IF(E81>=3,"Y","N")) -> Y | G81: Y | H81: N
A82: Canyon Ridge | B82: B-116 | C82: 127000 | D82: 2070 | E82: =IF(AND(ISNUMBER(C82),ISNUMBER(D82)),C82/(12*D82),"") -> 5.1127214 | F82: =IF(E82="","",IF(E82>=3,"Y","N")) -> Y | G82: N | H82: N
A83: Canyon Ridge | B83: B-117 | C83: 87300 | D83: 1670 | E83: =IF(AND(ISNUMBER(C83),ISNUMBER(D83)),C83/(12*D83),"") -> 4.3562874 | F83: =IF(E83="","",IF(E83>=3,"Y","N")) -> Y | G83: Y | H83: Y
A84: Canyon Ridge | B84: B-118 | C84: 249600 | D84: 2005 | E84: =IF(AND(ISNUMBER(C84),ISNUMBER(D84)),C84/(12*D84),"") -> 10.374065 | F84: =IF(E84="","",IF(E84>=3,"Y","N")) -> Y | G84: Y | H84: N
A85: Canyon Ridge | B85: B-119 | C85: 153448 | D85: 2380 | E85: =IF(AND(ISNUMBER(C85),ISNUMBER(D85)),C85/(12*D85),"") -> 5.3728291 | F85: =IF(E85="","",IF(E85>=3,"Y","N")) -> Y | G85: Y | H85: N
A86: Canyon Ridge | B86: B-120 | C86: 3350000 | D86: 1570 | E86: =IF(AND(ISNUMBER(C86),ISNUMBER(D86)),C86/(12*D86),"") -> 177.81316 | F86: =IF(E86="","",IF(E86>=3,"Y","N")) -> Y | G86: Y | H86: Y
A87: Canyon Ridge | B87: B-121 | C87: 107000 | D87: 1880 | E87: =IF(AND(ISNUMBER(C87),ISNUMBER(D87)),C87/(12*D87),"") -> 4.7429078 | F87: =IF(E87="","",IF(E87>=3,"Y","N")) -> Y | G87: Y | H87: N
A88: Canyon Ridge | B88: B-122 | D88: 2380 | E88: =IF(AND(ISNUMBER(C88),ISNUMBER(D88)),C88/(12*D88),"") | F88: =IF(E88="","",IF(E88>=3,"Y","N")) | G88: N | H88: N
A89: Canyon Ridge | B89: B-201 | C89: 200000 | D89: 2570 | E89: =IF(AND(ISNUMBER(C89),ISNUMBER(D89)),C89/(12*D89),"") -> 6.4850843 | F89: =IF(E89="","",IF(E89>=3,"Y","N")) -> Y | G89: Y | H89: N
A90: Canyon Ridge | B90: B-202 | C90: 131382 | D90: 2275 | E90: =IF(AND(ISNUMBER(C90),ISNUMBER(D90)),C90/(12*D90),"") -> 4.8125275 | F90: =IF(E90="","",IF(E90>=3,"Y","N")) -> Y | G90: Y | H90: N
A91: Canyon Ridge | B91: B-203 | C91: 78000 | D91: 2050 | E91: =IF(AND(ISNUMBER(C91),ISNUMBER(D91)),C91/(12*D91),"") -> 3.1707317 | F91: =IF(E91="","",IF(E91>=3,"Y","N")) -> Y | G91: N | H91: N
A92: Canyon Ridge | B92: B-204 | D92: 1845 | E92: =IF(AND(ISNUMBER(C92),ISNUMBER(D92)),C92/(12*D92),"") | F92: =IF(E92="","",IF(E92>=3,"Y","N")) | G92: N | H92: N
A93: Canyon Ridge | B93: B-205 | D93: 1845 | E93: =IF(AND(ISNUMBER(C93),ISNUMBER(D93)),C93/(12*D93),"") | F93: =IF(E93="","",IF(E93>=3,"Y","N")) | G93: N | H93: N
A94: Canyon Ridge | B94: B-206 | C94: 138000 | D94: 1895 | E94: =IF(AND(ISNUMBER(C94),ISNUMBER(D94)),C94/(12*D94),"") -> 6.0686016 | F94: =IF(E94="","",IF(E94>=3,"Y","N")) -> Y | G94: Y | H94: N
A95: Canyon Ridge | B95: B-207 | C95: 96000 | D95: 2050 | E95: =IF(AND(ISNUMBER(C95),ISNUMBER(D95)),C95/(12*D95),"") -> 3.902439 | F95: =IF(E95="","",IF(E95>=3,"Y","N")) -> Y | G95: Y | H95: N
A96: Canyon Ridge | B96: B-208 | C96: 204000 | D96: 1875 | E96: =IF(AND(ISNUMBER(C96),ISNUMBER(D96)),C96/(12*D96),"") -> 9.0666667 | F96: =IF(E96="","",IF(E96>=3,"Y","N")) -> Y | G96: Y | H96: Y
A97: Canyon Ridge | B97: B-209 | C97: 210000 | D97: 2050 | E97: =IF(AND(ISNUMBER(C97),ISNUMBER(D97)),C97/(12*D97),"") -> 8.5365854 | F97: =IF(E97="","",IF(E97>=3,"Y","N")) -> Y | G97: Y | H97: Y
A98: Canyon Ridge | B98: B-210 | C98: 249398 | D98: 1975 | E98: =IF(AND(ISNUMBER(C98),ISNUMBER(D98)),C98/(12*D98),"") -> 10.523122 | F98: =IF(E98="","",IF(E98>=3,"Y","N")) -> Y | G98: Y | H98: Y
A99: Canyon Ridge | B99: B-211 | D99: 1850 | E99: =IF(AND(ISNUMBER(C99),ISNUMBER(D99)),C99/(12*D99),"") | F99: =IF(E99="","",IF(E99>=3,"Y","N")) | G99: N | H99: N
A100: Canyon Ridge | B100: B-212 | D100: 1850 | E100: =IF(AND(ISNUMBER(C100),ISNUMBER(D100)),C100/(12*D100),"") | F100: =IF(E100="","",IF(E100>=3,"Y","N")) | G100: N | H100: N
A101: Canyon Ridge | B101: B-213 | C101: 126400 | D101: 2100 | E101: =IF(AND(ISNUMBER(C101),ISNUMBER(D101)),C101/(12*D101),"") -> 5.015873 | F101: =IF(E101="","",IF(E101>=3,"Y","N")) -> Y | G101: N | H101: N
A102: Canyon Ridge | B102: B-214 | C102: 221000 | D102: 1875 | E102: =IF(AND(ISNUMBER(C102),ISNUMBER(D102)),C102/(12*D102),"") -> 9.8222222 | F102: =IF(E102="","",IF(E102>=3,"Y","N")) -> Y | G102: Y | H102: Y
A103: Canyon Ridge | B103: B-215 | C103: 63720 | D103: 1795 | E103: =IF(AND(ISNUMBER(C103),ISNUMBER(D103)),C103/(12*D103),"") -> 2.9582173 | F103: =IF(E103="","",IF(E103>=3,"Y","N")) -> N | G103: N | H103: N
A104: Canyon Ridge | B104: B-216 | D104: 2250 | E104: =IF(AND(ISNUMBER(C104),ISNUMBER(D104)),C104/(12*D104),"") | F104: =IF(E104="","",IF(E104>=3,"Y","N")) | G104: N | H104: N
A105: Canyon Ridge | B105: B-217 | C105: 107000 | D105: 1845 | E105: =IF(AND(ISNUMBER(C105),ISNUMBER(D105)),C105/(12*D105),"") -> 4.8328817 | F105: =IF(E105="","",IF(E105>=3,"Y","N")) -> Y | G105: Y | H105: N
A106: Canyon Ridge | B106: B-218 | C106: 155800 | D106: 2110 | E106: =IF(AND(ISNUMBER(C106),ISNUMBER(D106)),C106/(12*D106),"") -> 6.1532385 | F106: =IF(E106="","",IF(E106>=3,"Y","N")) -> Y | G106: Y | H106: N
A107: Canyon Ridge | B107: B-219 | C107: 288883 | D107: 2475 | E107: =IF(AND(ISNUMBER(C107),ISNUMBER(D107)),C107/(12*D107),"") -> 9.7267003 | F107: =IF(E107="","",IF(E107>=3,"Y","N")) -> Y | G107: Y | H107: N
...

Sheet Seasons Data
A1: Seasons at Meridian — Demographics (standardized & classified)
A2: Source: seller "Demographics Report w/Roommates" 07/10/2026 (Status=Current — excludes the 38 units on notice), de-duplicated to one row per person (pet rows collapsed). Employer standardization & T1–T6 tiers added by this analysis.
A4: Unit | B4: Tenant Code | C4: Name | D4: Relationship | E4: Resident (excl. guarantor) | F4: Raw Company (as entered) | G4: Standardized Employer | H4: Tier | I4: Industry | J4: Confidence | K4: Annual Salary | L4: Income OK | M4: Income Flag | N4: DOB | O4: Marital
A5: A101 | B5: t0035267 | C5: Ramirez, Emely | D5: Primary | E5: Y | F5: drybar | G5: Drybar | H5: T6 | I5: Personal Services & Other Local | J5: Confirmed-NotMicron | K5: 24000 | L5: Y | N5: 02/06/1994
A6: A101 | B6: r0035291 | C6: dilone, franxesca | D6: Roommate | E6: Y | F6: st Alphonso | G6: Saint Alphonsus (Trinity Health) | H6: T6 | I6: Healthcare & Social Services | J6: Confirmed-NotMicron | K6: 128100 | L6: Y | N6: 12/21/1974
A7: A102 | B7: t0038493 | C7: Fielder, Matthew | D7: Primary | E7: Y | F7: GardaWorld | G7: GardaWorld | H7: T6 | I7: Government, Military & Public Safety | J7: Confirmed-NotMicron | K7: 51780 | L7: Y | N7: 02/19/1983 | O7: Married
A8: A102 | B8: r0038541 | C8: Fielder, Shanae | D8: Spouse | E8: Y | F8: Ulta Beauty | G8: Ulta Beauty | H8: T6 | I8: Retail & Food Service | J8: Confirmed-NotMicron | K8: 76056 | L8: Y | N8: 04/17/1990 | O8: Married
A9: A104 | B9: t0036159 | C9: Bain, Nancy | D9: Primary | E9: Y | F9: Retired | G9: Retired | I9: Not employed / other income | J9: Confirmed-NotMicron | K9: 48120 | L9: Y | N9: 06/22/1951
A10: A106 | B10: t0035645 | C10: Hanna, Dominic | D10: Primary | E10: Y | F10: Micron Technology | G10: Micron Technology | H10: T1 | I10: Micron (direct) | J10: Confirmed | K10: 51180 | L10: Y | N10: 05/22/2003
A11: A106 | B11: r0035820 | C11: Evans, Hannah | D11: Roommate | E11: Y | F11: Great Harvest Bakery Company | G11: Great Harvest Bread Co. | H11: T6 | I11: Retail & Food Service | J11: Confirmed-NotMicron | K11: 29004 | L11: Y | N11: 01/22/2007
A12: A107 | B12: t0030452 | C12: Orchard, Heather | D12: Primary | E12: Y | F12: Epionce | G12: Epionce (Episciences) | H12: T6 | I12: Healthcare & Social Services | J12: Confirmed-NotMicron | K12: 69996 | L12: Y | N12: 08/12/1988
A13: A108 | B13: t0035973 | C13: Knox, Katrina | D13: Primary | E13: Y | F13: St Luke's Medical Center | G13: St. Luke's Health System | H13: T6 | I13: Healthcare & Social Services | J13: Confirmed-NotMicron | K13: 59340 | L13: Y | N13: 11/13/1972
A14: A109 | B14: t0034222 | C14: Edens, Gavin | D14: Primary | E14: Y | F14: US Army | G14: U.S. Army | H14: T6 | I14: Government, Military & Public Safety | J14: Confirmed-NotMicron | K14: 78228 | L14: Y | N14: 09/06/1999 | O14: Married
A15: A109 | B15: r0034315 | C15: Edens, Amanda | D15: Spouse | E15: Y | F15: Barbara Morgan stem Academy | G15: Barbara Morgan STEM Academy (West Ada) | H15: T6 | I15: Education & Childcare | J15: Confirmed-NotMicron | K15: 21360 | L15: Y | N15: 12/03/1999 | O15: Married
A16: A110 | B16: t0036419 | C16: Dent, Zackary | D16: Primary | E16: Y | F16: Liberty Energy | G16: Liberty Energy | H16: T6 | I16: Energy & Utilities | J16: Confirmed-NotMicron | K16: 112596 | L16: Y | N16: 04/01/2002 | O16: Single
A17: A111 | B17: t0035171 | C17: Zuniga, Jonathan | D17: Primary | E17: Y | F17: Barak Group Inc. DBA Jani-King | G17: Jani-King (Barak Group) | H17: T6 | I17: Personal Services & Other Local | J17: Confirmed-NotMicron | K17: 72924 | L17: Y | N17: 03/28/1999 | O17: Single
A18: A112 | B18: t0040841 | C18: Hart, Angela | D18: Primary | E18: Y | F18: Life Care center of Boise | G18: Life Care Center of Boise | H18: T6 | I18: Healthcare & Social Services | J18: Confirmed-NotMicron | K18: 78336 | L18: Y | N18: 06/21/1970 | O18: Single
A19: A112 | B19: r0040962 | C19: Hart, Charity | D19: Roommate | E19: Y | F19: NA | I19: (blank) | K19: 0 | L19: N | M19: No income stated | N19: 09/04/2001
A20: A202 | B20: t0029908 | C20: McKenzie, Alexandra | D20: Primary | E20: Y | F20: Arbor Valley of Cascadia | G20: Arbor Valley of Cascadia | H20: T6 | I20: Healthcare & Social Services | J20: Confirmed-NotMicron | K20: 48000 | L20: Y | N20: 02/22/2001
A21: A202 | B21: r0030032 | C21: McKenzie, Brandon | D21: Roommate | E21: Y | I21: (blank) | K21: 0 | L21: N | M21: No income stated | N21: 10/19/2009
A22: A202 | B22: r0030083 | C22: McKenzie, Eli | D22: Roommate | E22: Y | I22: (blank) | K22: 0 | L22: N | M22: No income stated | N22: 10/19/2009
A23: A202 | B23: r0030033 | C23: McKenzie, Laura | D23: Roommate | E23: Y | I23: (blank) | K23: 0 | L23: N | M23: No income stated | N23: 10/19/2009
A24: A202 | B24: r0030080 | C24: McKenzie, Riley | D24: Other | E24: Y | I24: (blank) | K24: 0 | L24: N | M24: No income stated | N24: 10/19/2009
A25: A203 | B25: t0038410 | C25: Brown, Dakotah | D25: Primary | E25: Y | F25: Boise VA Medical Center | G25: Boise VA Medical Center | H25: T6 | I25: Healthcare & Social Services | J25: Confirmed-NotMicron | K25: 94248 | L25: Y | N25: 11/21/1987 | O25: Single
A26: A204 | B26: t0028992 | C26: Campagni, Kristine | D26: Primary | E26: Y | F26: na | I26: (blank) | K26: 150564 | L26: Y | N26: 08/07/1965
A27: A205 | B27: t0031017 | C27: Saffery Hoopii, Michael | D27: Primary | E27: Y | F27: NA | I27: (blank) | K27: 40800 | L27: Y | N27: 08/28/1986
A28: A205 | B28: r0037696 | C28: Kamaunu-Hoopii, Rylan | D28: Roommate | E28: Y | F28: Goodwill | G28: Goodwill | H28: T6 | I28: Retail & Food Service | J28: Confirmed-NotMicron | K28: 38400 | L28: N | M28: Copy of another occupant (same unit+DOB+salary) — excluded | N28: 03/06/2001
A29: A205 | B29: r0039455 | C29: Kepaa, Tristen | D29: Roommate | E29: Y | F29: Goodwill | G29: Goodwill | H29: T6 | I29: Retail & Food Service | J29: Confirmed-NotMicron | K29: 38400 | L29: N | M29: Copy of another occupant (same unit+DOB+salary) — excluded | N29: 03/06/2001
A30: A205 | B30: r0039454 | C30: Kepaa-Kamaunu-Hoopii, Azaesha-Lei | D30: Other | E30: Y | F30: Goodwill | G30: Goodwill | H30: T6 | I30: Retail & Food Service | J30: Confirmed-NotMicron | K30: 38400 | L30: N | M30: Copy of another occupant (same unit+DOB+salary) — excluded | N30: 03/06/2001
A31: A205 | B31: r0031174 | C31: Valentine-decoite, Michelle | D31: Spouse | E31: Y | F31: Goodwill | G31: Goodwill | H31: T6 | I31: Retail & Food Service | J31: Confirmed-NotMicron | K31: 38400 | L31: Y | N31: 03/06/2001
A32: A206 | B32: t0036235 | C32: Holloman, Lukas | D32: Primary | E32: Y | F32: Horizon Air | G32: Horizon Air | H32: T6 | I32: Aerospace & Airlines | J32: Confirmed-NotMicron | K32: 97692 | L32: Y | N32: 04/11/2003 | O32: Single
A33: A207 | B33: t0034692 | C33: Brading, Amy | D33: Primary | E33: Y | F33: Hoffman Construction | G33: Hoffman Construction Company | H33: T2 | I33: Micron fab construction | J33: Confirmed | K33: 120000 | L33: Y | N33: 02/23/2000 | O33: Single
A34: A208 | B34: t0035813 | C34: Croner, Dylan | D34: Primary | E34: Y | F34: haven behavioral health | G34: Haven Behavioral Health | H34: T6 | I34: Healthcare & Social Services | J34: Confirmed-NotMicron | K34: 55200 | L34: Y | N34: 01/04/2002 | O34: Single
A35: A209 | B35: t0035239 | C35: Bonner, Emily | D35: Primary | E35: Y | F35: Tin Roof Tacos | G35: Tin Roof Tacos | H35: T6 | I35: Retail & Food Service | J35: Confirmed-NotMicron | K35: 66000 | L35: Y | N35: 05/11/2002 | O35: Single
A36: A209 | B36: r0035873 | C36: Soofi, Saleem | D36: Spouse | E36: Y | F36: 208 roofing | G36: 208 Roofing | H36: T6 | I36: Construction & Trades (non-Micron) | J36: Confirmed-NotMicron | K36: 144000 | L36: Y | N36: 10/30/1998
A37: A210 | B37: t0037724 | C37: Gorman, Edward | D37: Primary | E37: Y | F37: Construction | G37: Construction (unspecified) | H37: T6 | I37: Construction & Trades (non-Micron) | J37: Weak-unverified | K37: 52800 | L37: Y | N37: 12/15/2000
A38: A210 | B38: r0037690 | C38: McDonald, Madelyne | D38: Roommate | E38: Y | I38: (blank) | K38: 0 | L38: N | M38: No income stated | N38: 09/15/2006 | O38: Married
A39: A211 | B39: t0031285 | C39: Valdez, Jaime | D39: Primary | E39: Y | F39: Aztec Welding Services | G39: Aztec Welding Services | H39: T6 | I39: Construction & Trades (non-Micron) | J39: Inferred | K39: 72000 | L39: Y | N39: 07/25/1996
A40: A212 | B40: t0034758 | C40: WARNER, PAYDEN | D40: Primary | E40: Y | F40: Asbury | G40: Asbury (church/nonprofit) | H40: T6 | I40: Nonprofit & Religious | J40: Weak-unverified | K40: 43104 | L40: Y | N40: 06/15/2001
A41: A212 | B41: r0036610 | C41: Hefner, Jayden | D41: Roommate | E41: Y | F41: Udelhoven | G41: Udelhoven Oilfield System Services | H41: T6 | I41: Energy & Utilities | J41: Confirmed-NotMicron | K41: 136608 | L41: N | M41: Copy of another occupant (same unit+DOB+salary) — excluded | N41: 01/03/1973 | O41: Single
A42: A212 | B42: r0034830 | C42: Warner, Steven | D42: Guarantor | E42: N | F42: Udelhoven | G42: Udelhoven Oilfield System Services | H42: T6 | I42: Energy & Utilities | J42: Confirmed-NotMicron | K42: 136608 | L42: N | M42: Guarantor — excluded from income/occupant stats | N42: 01/03/1973 | O42: Single
A43: A213 | B43: t0035698 | C43: Apostu, Silviu | D43: Primary | E43: Y | F43: Transportation | G43: Transportation (unspecified) | H43: T6 | I43: Wholesale, Transport & Logistics | J43: Weak-unverified | K43: 144000 | L43: Y | N43: 10/12/1987 | O43: Married
A44: A213 | B44: r0035872 | C44: Apostu, Andrei | D44: Other | E44: Y | F44: NA | I44: (blank) | K44: 0 | L44: N | M44: No income stated | N44: 02/04/1993 | O44: Married
A45: A213 | B45: r0035871 | C45: Apostu, Elena | D45: Other | E45: Y | F45: NA | I45: (blank) | K45: 0 | L45: N | M45: No income stated | N45: 02/04/1993 | O45: Married
A46: A213 | B46: r0035870 | C46: Apostu, Gianina | D46: Roommate | E46: Y | F46: NA | I46: (blank) | K46: 0 | L46: N | M46: No income stated | N46: 02/04/1993 | O46: Married
A47: A301 | B47: t0034549 | C47: Magana, Roberto | D47: Primary | E47: Y | F47: Apace Construction | G47: Apace Labor & Construction (Apace Demolition) | H47: T6 | I47: Construction & Trades (non-Micron) | J47: Confirmed-NotMicron | K47: 43200 | L47: Y | N47: 07/07/2003
A48: A301 | B48: r0034636 | C48: Perez Ceron, Fatima | D48: Spouse | E48: Y | F48: NA | I48: (blank) | K48: 39840 | L48: Y | N48: 10/08/2005
A49: A302 | B49: t0038089 | C49: Dante, Christopher | D49: Primary | E49: Y | F49: Ada County Sheriffs Office | G49: Ada County Sheriff's Office | H49: T6 | I49: Government, Military & Public Safety | J49: Confirmed-NotMicron | K49: 53568 | L49: Y | N49: 10/28/1989
A50: A302 | B50: r0038019 | C50: Dante, Devin | D50: Other | E50: Y | F50: Modern Wealth Management | G50: Modern Wealth Management | H50: T6 | I50: Financial, Legal & Professional | J50: Confirmed-NotMicron | K50: 48000 | L50: N | M50: Copy of another occupant (same unit+DOB+salary) — excluded | N50: 09/30/1989
A51: A302 | B51: r0038020 | C51: Dante, Khyson | D51: Other | E51: Y | F51: Modern Wealth Management | G51: Modern Wealth Management | H51: T6 | I51: Financial, Legal & Professional | J51: Confirmed-NotMicron | K51: 48000 | L51: N | M51: Copy of another occupant (same unit+DOB+salary) — excluded | N51: 09/30/1989
A52: A302 | B52: r0038018 | C52: Dante, Natalie | D52: Spouse | E52: Y | F52: Modern Wealth Management | G52: Modern Wealth Management | H52: T6 | I52: Financial, Legal & Professional | J52: Confirmed-NotMicron | K52: 48000 | L52: Y | N52: 09/30/1989
A53: A305 | B53: t0032547 | C53: Harris, Johnny | D53: Primary | E53: Y | F53: retired | G53: Retired | I53: Not employed / other income | J53: Confirmed-NotMicron | K53: 48924 | L53: Y | N53: 01/08/1970 | O53: Single
A54: A305 | B54: r0032678 | C54: HARRIS, ZACHARY | D54: Other | E54: Y | I54: (blank) | K54: 0 | L54: N | M54: No income stated | N54: 07/29/1998
A55: A306 | B55: t0035738 | C55: Dunlap, Lillyan | D55: Primary | E55: Y | F55: Idaho Central Credit Union | G55: Idaho Central Credit Union | H55: T6 | I55: Financial, Legal & Professional | J55: Confirmed-NotMicron | K55: 48000 | L55: Y | N55: 04/23/2005
A56: A307 | B56: t0029257 | C56: Sleyko, Nicholas | D56: Primary | E56: Y | F56: BANC OF CALIFORNIA | G56: Banc of California | H56: T6 | I56: Financial, Legal & Professional | J56: Confirmed-NotMicron | K56: 744000 | L56: Y | N56: 10/14/1981
A57: A307 | B57: r0029997 | C57: Sleyko, Astrid Marguerite | D57: Other | E57: Y | F57: Dr. Yvonne Rochon Pediatric Dentist | G57: Dr. Yvonne Rochon Pediatric Dentistry | H57: T6 | I57: Healthcare & Social Services | J57: Confirmed-NotMicron | K57: 744000 | L57: N | M57: Copy of another occupant (same unit+DOB+salary) — excluded | N57: 03/05/1982
A58: A307 | B58: r0029297 | C58: Sleyko, Jennifer | D58: Spouse | E58: Y | F58: Dr. Yvonne Rochon Pediatric Dentist | G58: Dr. Yvonne Rochon Pediatric Dentistry | H58: T6 | I58: Healthcare & Social Services | J58: Confirmed-NotMicron | K58: 744000 | L58: Y | N58: 03/05/1982
A59: A307 | B59: r0029996 | C59: Sleyko, Penelope Jean | D59: Other | E59: Y | F59: Dr. Yvonne Rochon Pediatric Dentist | G59: Dr. Yvonne Rochon Pediatric Dentistry | H59: T6 | I59: Healthcare & Social Services | J59: Confirmed-NotMicron | K59: 744000 | L59: N | M59: Copy of another occupant (same unit+DOB+salary) — excluded | N59: 03/05/1982
A60: A310 | B60: t0029775 | C60: Walborn, Leah | D60: Primary | E60: Y | F60: NA | I60: (blank) | K60: 9600 | L60: Y | N60: 02/01/2002
A61: A312 | B61: t0037719 | C61: Schmitt, Madeline | D61: Primary | E61: Y | F61: Spavia Day Spa | G61: Spavia Day Spa | H61: T6 | I61: Personal Services & Other Local | J61: Confirmed-NotMicron | K61: 28800 | L61: Y | N61: 09/04/2002
A62: A312 | B62: r0037685 | C62: Zombeck, Travis | D62: Roommate | E62: Y | F62: Money metal exchange | G62: Money Metals Exchange | H62: T6 | I62: Retail & Food Service | J62: Confirmed-NotMicron | K62: 46272 | L62: Y | N62: 03/16/2002 | O62: Single
A63: A313 | B63: t0031035 | C63: Bockstedt III, Paul | D63: Primary | E63: Y | F63: NA | I63: (blank) | K63: 0 | L63: N | M63: No income stated | N63: 05/18/1993
A64: B101 | B64: t0029806 | C64: Dobson, Joseph | D64: Primary | E64: Y | F64: Coyne Powersports | G64: Coyne Powersports | H64: T6 | I64: Retail & Food Service | J64: Confirmed-NotMicron | K64: 146400 | L64: Y | N64: 10/10/1986
A65: B101 | B65: r0030026 | C65: Dobson, Carol | D65: Roommate | E65: Y | I65: (blank) | K65: 0 | L65: N | M65: No income stated | N65: 03/08/2013
A66: B101 | B66: r0030228 | C66: Dobson, Kooper | D66: Other | E66: Y | I66: (blank) | K66: 0 | L66: N | M66: No income stated | N66: 03/08/2013
A67: B102 | B67: t0035749 | C67: Pardew, Scott | D67: Primary | E67: Y | F67: Laser Land Leveling | G67: Laser Land Leveling | H67: T6 | I67: Construction & Trades (non-Micron) | J67: Confirmed-NotMicron | K67: 96372 | L67: Y | N67: 08/12/1992 | O67: Single
A68: B102 | B68: r0037823 | C68: Degrange, Nichole | D68: Roommate | E68: Y | F68: St. Lukes Meridian Medical Center | G68: St. Luke's Health System | H68: T6 | I68: Healthcare & Social Services | J68: Confirmed-NotMicron | K68: 50400 | L68: Y | N68: 05/21/1994
A69: B103 | B69: t0031260 | C69: Dustin, Kevin | D69: Primary | E69: Y | F69: V2V | G69: V2V Management Solutions | H69: T6 | I69: Financial, Legal & Professional | J69: Inferred | K69: 240000 | L69: Y | N69: 02/01/1975
A70: B104 | B70: t0038091 | C70: Kreider, Jeanette | D70: Primary | E70: Y | F70: Retired | G70: Retired | I70: Not employed / other income | J70: Confirmed-NotMicron | K70: 73200 | L70: Y | N70: 07/10/1944 | O70: Single
A71: B104 | B71: r0038479 | C71: Wattles, Gary | D71: Roommate | E71: Y | F71: Northern Illinois Methodist Conference | G71: Northern Illinois Methodist Conference | H71: T6 | I71: Nonprofit & Religious | J71: Confirmed-NotMicron | K71: 61656 | L71: Y | N71: 04/04/1935
A72: B107 | B72: t0033236 | C72: Bourgoin, Amy | D72: Primary | E72: Y | F72: Department of the Interior | G72: U.S. Department of the Interior | H72: T6 | I72: Government, Military & Public Safety | J72: Confirmed-NotMicron | K72: 69396 | L72: Y | N72: 01/18/1985 | O72: Single
A73: B107 | B73: r0033380 | C73: Bourgoin, Nicole Allison | D73: Other | E73: Y | I73: (blank) | K73: 0 | L73: N | M73: No income stated | N73: 12/13/2017
A74: B108 | B74: t0039911 | C74: Vanin, Aleksey | D74: Primary | E74: Y | F74: OEG | G74: Oregon Electric Group (OEG) | H74: T2 | I74: Micron fab construction | J74: Strong-inferred | K74: 120000 | L74: Y | N74: 10/15/1974 | O74: Single
A75: B109 | B75: t0030390 | C75: Leguizamon Ramirez, Diocelina | D75: Primary | E75: Y | F75: Jose Herrera | G75: Jose Herrera (private employer) | H75: T6 | I75: Self-employed / private | J75: Weak-unverified | K75: 60000 | L75: Y | N75: 02/06/1993
A76: B109 | B76: r0030576 | C76: Herrera Ramirez, Jose | D76: Spouse | E76: Y | I76: (blank) | K76: 0 | L76: N | M76: No income stated
A77: B109 | B77: r0030663 | C77: Herrera, Joseph | D77: Other | E77: Y | I77: (blank) | K77: 0 | L77: N | M77: No income stated
A78: B110 | B78: t0030047 | C78: Huntsman, Raymond | D78: Primary | E78: Y | F78: St. Luke's | G78: St. Luke's Health System | H78: T6 | I78: Healthcare & Social Services | J78: Confirmed-NotMicron | K78: 49200 | L78: Y | N78: 12/07/1998
A79: B111 | B79: t0035706 | C79: Worley, Jeffrey | D79: Primary | E79: Y | F79: albertsons | G79: Albertsons | H79: T6 | I79: Retail & Food Service | J79: Confirmed-NotMicron | K79: 88800 | L79: Y | N79: 01/05/1984 | O79: Single
A80: B112 | B80: t0041225 | C80: Housing, Paragon Corporate | D80: Primary | E80: Y | F80: Paragon Corporate Lease | G80: Paragon Corporate Housing | H80: T6 | I80: Corporate housing entity | J80: Confirmed-NotMicron | K80: 120000 | L80: Y | N80: 05/30/1996
A81: B113 | B81: t0034397 | C81: Warden, Brooke | D81: Primary | E81: Y | F81: Roundhouse | G81: Roundhouse | H81: T6 | I81: Hospitality | J81: Confirmed-NotMicron | K81: 40800 | L81: Y | N81: 08/14/1999
A82: B201 | B82: t0039802 | C82: Mcgirr, Brent | D82: Primary | E82: Y | F82: Phillips 66 | G82: Phillips 66 | H82: T6 | I82: Energy & Utilities | J82: Confirmed-NotMicron | K82: 130056 | L82: Y | N82: 03/15/1990 | O82: Single
A83: B203 | B83: t0037754 | C83: Dalpini, Anne | D83: Primary | E83: Y | F83: Mountain Care Pharmacy | G83: Mountain Care Pharmacy | H83: T6 | I83: Healthcare & Social Services | J83: Confirmed-NotMicron | K83: 72816 | L83: Y | N83: 06/30/1983 | O83: Single
A84: B204 | B84: t0033388 | C84: McKellip, Sherry | D84: Primary | E84: Y | I84: (blank) | K84: 58440 | L84: Y | N84: 10/09/1959 | O84: Single
A85: B205 | B85: t0035120 | C85: Boisselle, Harley | D85: Primary | E85: Y | F85: Trinity Assisted Living | G85: Trinity Assisted Living | H85: T6 | I85: Healthcare & Social Services | J85: Confirmed-NotMicron | K85: 45252 | L85: Y | N85: 11/18/2003 | O85: Single
A86: B205 | B86: r0035177 | C86: Langton, Carson | D86: Spouse | E86: Y | F86: Advanced heating and cooling | G86: Advanced Heating & Cooling | H86: T6 | I86: Construction & Trades (non-Micron) | J86: Confirmed-NotMicron | K86: 26400 | L86: Y | N86: 11/12/2004 | O86: Single
A87: B208 | B87: t0037959 | C87: Fischer, Kennedi | D87: Primary | E87: Y | F87: St. Lukes Hospital | G87: St. Luke's Health System | H87: T6 | I87: Healthcare & Social Services | J87: Confirmed-NotMicron | K87: 41892 | L87: Y | N87: 11/28/2003 | O87: Single
A88: B208 | B88: r0037902 | C88: Fischer, Mark | D88: Guarantor | E88: N | F88: Micron Technology | G88: Micron Technology | H88: T1 | I88: Micron (direct) | J88: Confirmed | K88: 276816 | L88: N | M88: Guarantor — excluded from income/occupant stats | N88: 04/07/1967 | O88: Married
A89: B209 | B89: t0030710 | C89: Cornejo, Jacqueline | D89: Primary | E89: Y | F89: Jason Champagne 2 Idaho PLLC | G89: Jason Champagne Law | H89: T6 | I89: Financial, Legal & Professional | J89: Confirmed-NotMicron | K89: 36000 | L89: Y | N89: 12/09/2002
A90: B209 | B90: r0030875 | C90: Andrade Castaneda, Adolfo | D90: Spouse | E90: Y | F90: Builder Services Group Inc. | G90: Builder Services Group | H90: T6 | I90: Construction & Trades (non-Micron) | J90: Confirmed-NotMicron | K90: 66852 | L90: Y | N90: 03/01/2003
A91: B210 | B91: t0037517 | C91: Kelley, Jessica | D91: Primary | E91: Y | F91: Central District Health | G91: Central District Health | H91: T6 | I91: Healthcare & Social Services | J91: Confirmed-NotMicron | K91: 61128 | L91: Y | N91: 07/03/1995 | O91: Single
A92: B301 | B92: t0037520 | C92: Goodman, Rollin | D92: Primary | E92: Y | F92: Mark Guho Construction | G92: Guho Corp / Mark Guho Construction | H92: T6 | I92: Construction & Trades (non-Micron) | J92: Inferred | K92: 85020 | L92: Y | N92: 08/31/1993 | O92: Single
A93: B301 | B93: r0037460 | C93: Walters, Sydney | D93: Spouse | E93: Y | F93: Idaho Health Neighborhood Center | G93: Idaho Health Neighborhood Center | H93: T6 | I93: Healthcare & Social Services | J93: Confirmed-NotMicron | K93: 0 | L93: N | M93: No income stated | N93: 10/30/2002
A94: B302 | B94: t0040032 | C94: Hoke, Karey | D94: Primary | E94: Y | F94: Saint Alphonsus | G94: Saint Alphonsus (Trinity Health) | H94: T6 | I94: Healthcare & Social Services | J94: Confirmed-NotMicron | K94: 116040 | L94: Y | N94: 07/09/1990
A95: B302 | B95: r0039990 | C95: Martin, James | D95: Roommate | E95: Y | F95: Treasure Valley Intervention | G95: Treasure Valley Intervention | H95: T6 | I95: Healthcare & Social Services | J95: Confirmed-NotMicron | K95: 63504 | L95: Y | N95: 01/25/1995 | O95: Single
A96: B304 | B96: t0037906 | C96: Sullivan, Leah | D96: Primary | E96: Y | F96: The Payroll Factory | G96: The Payroll Factory | H96: T6 | I96: Financial, Legal & Professional | J96: Confirmed-NotMicron | K96: 57204 | L96: Y | N96: 12/22/1998
A97: B304 | B97: r0037855 | C97: Sullivan, James | D97: Roommate | E97: Y | F97: Novonesis | G97: Novonesis | H97: T6 | I97: Manufacturing & Consumer Products | J97: Confirmed-NotMicron | K97: 210000 | L97: Y | N97: 08/18/2001 | O97: Married
A98: B307 | B98: t0028450 | C98: Environmental Engineering, Coleman | D98: Primary | E98: Y | F98: Coleman Environmental Engineering | G98: Coleman Environmental Engineering, Inc. | H98: T6 | I98: Engineering & Technical Services | J98: Weak-unverified | K98: 2492892 | L98: N | M98: Corporate/entry outlier ≥$1M — excluded | N98: 11/04/1979
A99: B307 | B99: r0030179 | C99: Morrow, Giovanna | D99: Roommate | E99: Y | F99: Coleman Environmental Engineering | G99: Coleman Environmental Engineering, Inc. | H99: T6 | I99: Engineering & Technical Services | J99: Weak-unverified | K99: 264000 | L99: N | M99: Copy of another occupant (same unit+DOB+salary) — excluded | N99: 11/04/1979 | O99: Married
A100: B307 | B100: r0028532 | C100: Morrow, Jacob | D100: Roommate | E100: Y | F100: Coleman Environmental Engineering | G100: Coleman Environmental Engineering, Inc. | H100: T6 | I100: Engineering & Technical Services | J100: Weak-unverified | K100: 264000 | L100: Y | N100: 11/04/1979 | O100: Married
A101: B307 | B101: r0028540 | C101: Morrow, Kenna | D101: Spouse | E101: Y | F101: Coleman Environmental Engineering | G101: Coleman Environmental Engineering, Inc. | H101: T6 | I101: Engineering & Technical Services | J101: Weak-unverified | K101: 264000 | L101: N | M101: Copy of another occupant (same unit+DOB+salary) — excluded | N101: 11/04/1979 | O101: Married
...

Sheet Name Map - Seasons
A1: Seasons at Meridian — Raw employer text → standardized employer
A2: Every distinct raw string in the seller demographics export and how it was standardized/classified.
A4: Raw text (as entered) | B4: Standardized Employer | C4: Tier | D4: Confidence
A5: 1.Magic Valley Electric, 2. HRC Fire | B5: Magic Valley Electric / HRC Fire | C5: T6 | D5: Inferred
A6: 208 Home Care | B6: 208 Home Care | C6: T6 | D6: Confirmed-NotMicron
A7: 208 roofing | B7: 208 Roofing | C7: T6 | D7: Confirmed-NotMicron
A8: 84 Lumber | B8: 84 Lumber | C8: T6 | D8: Confirmed-NotMicron
A9: A Child's Heart Learning Center and Nursery | B9: A Child's Heart Learning Center | C9: T6 | D9: Confirmed-NotMicron
A10: A-1 Heating and Air | B10: A-1 Heating & Air | C10: T6 | D10: Confirmed-NotMicron
A11: Access Behavioral Halth Services | B11: Access Behavioral Health | C11: T6 | D11: Confirmed-NotMicron
A12: Access Behavioral Health | B12: Access Behavioral Health | C12: T6 | D12: Confirmed-NotMicron
A13: Ace Hardware | B13: Ace Hardware | C13: T6 | D13: Confirmed-NotMicron
A14: Ada County | B14: Ada County | C14: T6 | D14: Confirmed-NotMicron
A15: Ada County Sheriffs Office | B15: Ada County Sheriff's Office | C15: T6 | D15: Confirmed-NotMicron
... A379: WPI | B379: Western Partitions, Inc. (WPI) | C379: T2 | D379: Weak-inferred

Sheet CR Data
A1: Canyon Ridge — Resident data (from Employer / Micron Analysis workbook 2026.06.24)
A2: Source: Entrata "Resident Data 3.0" as of 06/24/2026 (Primary + Co-Applicant occupants; lease statuses Future/Current/Notice). Standardized employers & tiers carried over from the Canyon Ridge Micron analysis; industry coding added by this analysis.
A4: Unit | B4: Name | C4: Occupant Type | D4: Lease Status | E4: Scheduled Rent | F4: Lease Start | G4: Lease End | H4: Occupation | I4: Raw Employer | J4: Standardized Employer | K4: Tier | L4: Industry | M4: Annual Income
A5: A-101 | B5: Deshmukh, Hrishikesh Bipin | C5: Primary | D5: Current | E5: 1725 | F5: 2026-02-18 | G5: 2027-03-17 | H5: Engineer | I5: Micron Technology | J5: Micron Technology | K5: T1 | L5: Micron (direct) | M5: 105000
A6: A-102 | B6: Applegate, Bradley | C6: Primary | D6: Current | E6: 2560 | F6: 2026-05-29 | G6: 2027-08-28 | H6: Engineer | I6: Phoenix Industrial | J6: Phoenix Industrial | K6: T2 | L6: Micron fab construction | M6: 250000
A7: A-102 | B7: Villarreal, John | C7: Co-Applicant | D7: Current | E7: 2560 | F7: 2026-05-29 | G7: 2027-08-28 | H7: Construction | I7: Phoenix Industrial | J7: Phoenix Industrial | K7: T2 | L7: Micron fab construction | M7: 8060000
A8: A-103 | B8: Leyva, Javier | C8: Primary | D8: Current | E8: 2375 | F8: 2026-06-06 | G8: 2027-06-05 | H8: Construction | I8: Prime controls | J8: Prime Controls | K8: T3 | L8: Micron eng/consulting/IT | M8: 184340
A9: A-103 | B9: Leyva Sr, Javier | C9: Co-Applicant | D9: Current | E9: 2375 | F9: 2026-06-06 | G9: 2027-06-05 | H9: Construction | I9: Prime controls | J9: Prime Controls | K9: T3 | L9: Micron eng/consulting/IT | M9: 207480
A10: A-104 | B10: Koch, Sebastian | C10: Primary | D10: Current | E10: 1840 | F10: 2026-05-03 | G10: 2027-06-02 | H10: Engineer | I10: Micron | J10: Micron Technology | K10: T1 | L10: Micron (direct) | M10: 100000
A11: A-104 | B11: Blank, Thomas | C11: Co-Applicant | D11: Current | E11: 1840 | F11: 2026-05-03 | G11: 2027-06-02 | H11: Engineer | I11: Jesse Bair | J11: Jesse Bair (self-employed) | K11: T6 | L11: Self-employed / private | M11: 82500
A12: A-105 | B12: Ostermiller, Sonora | C12: Primary | D12: Current | E12: 2115 | F12: 2026-02-07 | G12: 2027-04-06 | H12: Unemployed/Dependent | L12: (blank)
A13: A-105 | B13: Hayden, Brian | C13: Co-Applicant | D13: Current | E13: 2115 | F13: 2026-02-07 | G13: 2027-04-06 | H13: Construction | I13: MC Company | J13: MC Company | K13: T2 | L13: Micron fab construction | M13: 216000
A14: A-106 | B14: Corporate Housing, Paragon | C14: Primary | D14: Current | E14: 1842 | F14: 2025-10-17 | G14: 2026-10-16 | L14: (blank)
A15: A-107 | B15: Jacobs, John | C15: Primary | D15: Current | E15: 1525 | F15: 2025-12-10 | G15: 2027-02-09 | H15: Construction | I15: Pipefitters UA local 296 | J15: Pipefitters UA Local 296 | K15: T2 | L15: Micron fab construction | M15: 146000
A16: A-108 | B16: Corporate Housing, Paragon | C16: Primary | D16: Current | E16: 1868 | F16: 2025-10-17 | G16: 2026-10-16 | L16: (blank)
A17: A-109 | B17: Sanchez, Patricia Naomi | C17: Primary | D17: Notice | E17: 1740 | F17: 2025-06-01 | G17: 2026-07-31 | H17: Construction | I17: Performance Contracting Group | J17: Performance Contracting, Inc. (PCI) | K17: T2 | L17: Micron fab construction | M17: 84600
A18: A-109 | B18: Echchad, Kawtar | C18: Co-Applicant | D18: Notice | E18: 1740 | F18: 2025-06-01 | G18: 2026-07-31 | H18: Student | L18: (blank) | M18: 60000
A19: A-110 | B19: Wiggins, Layton | C19: Primary | D19: Current | E19: 2250 | F19: 2026-06-08 | G19: 2027-06-07 | H19: Transporation/Utilities | I19: Skywest Airlines | J19: SkyWest Airlines | K19: T6 | L19: Aerospace & Airlines | M19: 65000
A20: A-110 | B20: Chichester, Jack | C20: Co-Applicant | D20: Current | E20: 2250 | F20: 2026-06-08 | G20: 2027-06-07 | H20: Unemployed/Dependent | L20: (blank)
A21: A-112 | B21: Weimer, Derek | C21: Primary | D21: Current | E21: 1895 | F21: 2026-02-28 | G21: 2027-03-27 | H21: Administrative | I21: Bogus Basin Mountain Recreation Association | J21: Bogus Basin Mountain Recreation Association | K21: T6 | L21: Hospitality | M21: 62000
A22: A-113 | B22: Brooks, Austin | C22: Primary | D22: Current | E22: 2610 | F22: 2025-06-13 | G22: 2026-08-12 | H22: Engineer | I22: Trew Contracting Solutions | J22: Trew Contracting Solutions | K22: T2 | L22: Micron fab construction | M22: 193000
A23: A-113 | B23: Brooks, Byron | C23: Co-Applicant | D23: Current | E23: 2610 | F23: 2025-06-13 | G23: 2026-08-12 | H23: Construction | I23: Trew Contracting Solutions | J23: Trew Contracting Solutions | K23: T2 | L23: Micron fab construction | M23: 208000
A24: A-114 | B24: Weber, Austin | C24: Primary | D24: Current | E24: 1865 | F24: 2026-04-28 | G24: 2027-04-27 | H24: Military | I24: US Air Force | J24: United States Air Force | K24: T6 | L24: Government, Military & Public Safety | M24: 87312
A25: A-115 | B25: Montoya, Jorge | C25: Primary | D25: Current | E25: 2285 | F25: 2026-04-21 | G25: 2027-06-20 | H25: Engineer | I25: Samsung Austin Semiconductor | J25: Samsung Austin Semiconductor | K25: T5 | L25: Semiconductor (non-Micron) | M25: 113675
A26: A-115 | B26: Gomez, Mayela | C26: Co-Applicant | D26: Current | E26: 2285 | F26: 2026-04-21 | G26: 2027-06-20 | H26: Administrative | I26: Kireys Mobile Grooming | J26: Kirey's Mobile Grooming | K26: T6 | L26: Personal Services & Other Local | M26: 15705.2
A27: A-116 | B27: Corporate Housing, Paragon | C27: Primary | D27: Current | E27: 2185 | F27: 2025-11-27 | G27: 2026-12-26 | L27: (blank)
A28: A-201 | B28: Corporate Housing, Paragon | C28: Primary | D28: Current | E28: 1975 | F28: 2025-11-18 | G28: 2026-12-17 | L28: (blank)
A29: A-202 | B29: Pandey, neeraj | C29: Primary | D29: Current | E29: 2345 | F29: 2025-09-05 | G29: 2026-10-04 | H29: Corporate Apt | I29: Clearwater Analytics | J29: Clearwater Analytics | K29: T6 | L29: Tech & Software (non-semi) | M29: 180000
A30: A-202 | B30: Pandey, Manisha | C30: Co-Applicant | D30: Current | E30: 2345 | F30: 2025-09-05 | G30: 2026-10-04 | H30: Full-Time Homemaker | L30: (blank)
A31: A-203 | B31: Donnelly, Travis | C31: Primary | D31: Current | E31: 1795 | F31: 2025-09-27 | G31: 2026-09-26 | H31: Military | I31: United States Air Force | J31: United States Air Force | K31: T6 | L31: Government, Military & Public Safety | M31: 81608.04
A32: A-204 | B32: Pena, Jessica | C32: Primary | D32: Current | E32: 1895 | F32: 2026-02-08 | G32: 2027-04-07 | H32: Full-Time Homemaker | L32: (blank)
A33: A-204 | B33: Pena, Noe | C33: Co-Applicant | D33: Current | E33: 1895 | F33: 2026-02-08 | G33: 2027-04-07 | H33: Construction | I33: Prime Control | J33: Prime Controls | K33: T3 | L33: Micron eng/consulting/IT | M33: 130000
A34: A-205 | B34: Roms, Heather | C34: Primary | D34: Notice | E34: 1850 | F34: 2025-06-03 | G34: 2026-08-02 | H34: Medical Services | I34: Kaiser Permanente | J34: Kaiser Permanente | K34: T6 | L34: Healthcare & Social Services | M34: 108000
A35: A-205 | B35: Roms, Lilly | C35: Co-Applicant | D35: Notice | E35: 1850 | F35: 2025-06-03 | G35: 2026-08-02 | H35: Student | L35: (blank)
A36: A-205 | B36: Smith, Kaidence | C36: Co-Applicant | D36: Notice | E36: 1850 | F36: 2025-06-03 | G36: 2026-08-02 | H36: Engineer | I36: Schnabel Engineering | J36: Schnabel Engineering | K36: T6 | L36: Engineering & Technical Services | M36: 60400
A37: A-206 | B37: Corporate Housing, Paragon | C37: Primary | D37: Current | E37: 1863 | F37: 2025-10-12 | G37: 2026-08-11 | L37: (blank)
A38: A-207 | B38: Gavelovskyy, Veniamin | C38: Primary | D38: Current | E38: 1495 | F38: 2025-12-04 | G38: 2026-12-03 | H38: Construction | I38: Performance contracting inc | J38: Performance Contracting, Inc. (PCI) | K38: T2 | L38: Micron fab construction | M38: 78250
A39: A-208 | B39: Corporate Housing, Paragon | C39: Primary | D39: Current | E39: 1850 | F39: 2025-12-11 | G39: 2027-01-10 | L39: (blank)
A40: A-209 | B40: Semitech, Fine | C40: Primary | D40: Current | E40: 2000 | F40: 2025-11-04 | G40: 2026-08-03 | L40: (blank)
A41: A-210 | B41: Patil, Vijaykumar | C41: Primary | D41: Current | E41: 1895 | F41: 2026-02-15 | G41: 2027-02-14 | H41: Engineer | I41: Micron | J41: Micron Technology | K41: T1 | L41: Micron (direct) | M41: 328000
A42: A-210 | B42: Patil, Kanchan | C42: Co-Applicant | D42: Current | E42: 1895 | F42: 2026-02-15 | G42: 2027-02-14 | H42: Unemployed/Dependent | L42: (blank)
A43: A-211 | B43: Martin, Christopher | C43: Primary | D43: Current | E43: 2155 | F43: 2026-06-20 | G43: 2027-06-19 | H43: Services | I43: Baron Properties | J43: Baron Properties | K43: T6 | L43: Financial, Legal & Professional | M43: 50000
A44: A-212 | B44: Palanisamy, Nivin Krishnan | C44: Primary | D44: Current | E44: 1995 | F44: 2025-10-20 | G44: 2026-10-19 | H44: Engineer | I44: ASM America | J44: ASM America | K44: T4 | L44: Semi equipment & materials | M44: 94000
A45: A-212 | B45: Jha, Ujjawal | C45: Co-Applicant | D45: Current | E45: 1995 | F45: 2025-10-20 | G45: 2026-10-19 | H45: Engineer | I45: Micron | J45: Micron Technology | K45: T1 | L45: Micron (direct) | M45: 112000
A46: A-213 | B46: Heinsma, Noah | C46: Primary | D46: Current | E46: 2495 | F46: 2026-02-05 | G46: 2027-04-04 | H46: Construction | L46: (blank)
A47: A-213 | B47: Gordon, Mikel | C47: Co-Applicant | D47: Current | E47: 2495 | F47: 2026-02-05 | G47: 2027-04-04 | H47: Construction | L47: (blank)
A48: A-213 | B48: Holt, Timothy | C48: Co-Applicant | D48: Current | E48: 2495 | F48: 2026-02-05 | G48: 2027-04-04 | H48: Construction | I48: Hoffman structures | J48: Hoffman Structures, Inc. | K48: T2 | L48: Micron fab construction | M48: 176800
A49: A-214 | B49: Brooks, Samuel | C49: Primary | D49: Current | E49: 2410 | F49: 2026-06-22 | G49: 2027-06-21 | H49: Construction | I49: Oregon electric group | J49: Oregon Electric Group (OEG) | K49: T2 | L49: Micron fab construction | M49: 216000
A50: A-214 | B50: Pine, Axl | C50: Co-Applicant | D50: Current | E50: 2410 | F50: 2026-06-22 | G50: 2027-06-21 | H50: Construction | I50: OEG | J50: Oregon Electric Group (OEG) | K50: T2 | L50: Micron fab construction | M50: 216000
A51: A-215 | B51: Ramesh, Sivaramakrishnan | C51: Primary | D51: Current | E51: 2325 | F51: 2026-04-01 | G51: 2026-09-30 | H51: Engineer | I51: Micron Technology Inc. | J51: Micron Technology | K51: T1 | L51: Micron (direct) | M51: 183000
A52: A-215 | B52: Venkateswaran, Vaijeyanthi | C52: Co-Applicant | D52: Current | E52: 2325 | F52: 2026-04-01 | G52: 2026-09-30 | H52: Unemployed/Dependent | L52: (blank)
A53: A-216 | B53: Pinkham, Philip | C53: Primary | D53: Current | E53: 2275 | F53: 2026-02-20 | G53: 2027-04-19 | H53: Construction | I53: Murray Plumbing and Heating Corporation | J53: Murray Plumbing and Heating Corporation | K53: T2 | L53: Micron fab construction | M53: 143000
A54: A-216 | B54: Pinkham, Julie | C54: Co-Applicant | D54: Current | E54: 2275 | F54: 2026-02-20 | G54: 2027-04-19 | H54: Full-Time Homemaker | L54: (blank)
A55: A-301 | B55: Jacques, Brandon | C55: Primary | D55: Current | E55: 1925 | F55: 2026-01-05 | G55: 2027-01-04 | H55: Construction | I55: Acco Engineered Systems | J55: ACCO Engineered Systems | K55: T2 | L55: Micron fab construction | M55: 125000
A56: A-302 | B56: Services, Wolff | C56: Primary | D56: Current | E56: 2520 | F56: 2025-06-27 | G56: 2026-06-26 | L56: (blank)
A57: A-303 | B57: Pena, Michael | C57: Primary | D57: Current | E57: 2510 | F57: 2026-06-09 | G57: 2027-06-08 | H57: Construction | I57: Murray company | J57: Murray Company | K57: T2 | L57: Micron fab construction | M57: 182000
A58: A-303 | B58: Todachine, Michael | C58: Co-Applicant | D58: Current | E58: 2510 | F58: 2026-06-09 | G58: 2027-06-08 | H58: Construction | I58: Murray Company | J58: Murray Company | K58: T2 | L58: Micron fab construction | M58: 108000
A59: A-304 | B59: Tan, Choon Suan | C59: Primary | D59: Notice | E59: 2170 | F59: 2025-03-22 | G59: 2026-05-06 | H59: High Tech/Telcomm/Internet | I59: Micron Technology | J59: Micron Technology | K59: T1 | L59: Micron (direct) | M59: 139000
A60: A-304 | B60: Hon, Pei Ling | C60: Co-Applicant | D60: Notice | E60: 2170 | F60: 2025-03-22 | G60: 2026-05-06 | H60: Manufacturing | I60: Micron Technology | J60: Micron Technology | K60: T1 | L60: Micron (direct) | M60: 182500
A61: A-305 | B61: Sengupta, Aneesha | C61: Primary | D61: Current | E61: 2185 | F61: 2026-05-22 | G61: 2027-05-21 | H61: Engineer | I61: Micron Technology | J61: Micron Technology | K61: T1 | L61: Micron (direct) | M61: 80400
A62: A-305 | B62: Mandapati, Neha Lakshmi | C62: Co-Applicant | D62: Current | E62: 2185 | F62: 2026-05-22 | G62: 2027-05-21 | H62: Engineer | L62: (blank)
A63: A-306 | B63: Corporate Housing, Paragon | C63: Primary | D63: Current | E63: 1885 | F63: 2025-12-11 | G63: 2027-01-10 | L63: (blank)
A64: A-307 | B64: Bangon, Tommy | C64: Primary | D64: Current | E64: 1650 | F64: 2025-10-20 | G64: 2026-10-19 | H64: Engineer | I64: Micron Technology Inc. | J64: Micron Technology | K64: T1 | L64: Micron (direct) | M64: 83000
A65: A-308 | B65: Corporate Housing, Paragon | C65: Primary | D65: Current | E65: 1905 | F65: 2025-12-10 | G65: 2026-12-09 | L65: (blank)
A66: A-309 | B66: Reddipalli, Dundi Sai Avinash | C66: Primary | D66: Current | E66: 2050 | F66: 2025-10-18 | G66: 2026-10-17 | H66: Manufacturing | I66: Micron Technology | J66: Micron Technology | K66: T1 | L66: Micron (direct) | M66: 96000
A67: A-309 | B67: Bala, Sai Chandra | C67: Co-Applicant | D67: Current | E67: 2050 | F67: 2025-10-18 | G67: 2026-10-17 | H67: Engineer | I67: Micron | J67: Micron Technology | K67: T1 | L67: Micron (direct) | M67: 90000
A68: A-309 | B68: Penmetsa, Jaswanth Venkata | C68: Co-Applicant | D68: Current | E68: 2050 | F68: 2025-10-18 | G68: 2026-10-17 | H68: Student | L68: (blank) | M68: 120000
A69: A-309 | B69: Vatsavai, Ramya Madhunika | C69: Co-Applicant | D69: Current | E69: 2050 | F69: 2025-10-18 | G69: 2026-10-17 | H69: Engineer | L69: (blank) | M69: 100000
A70: A-310 | B70: Vatturi, Jyothi | C70: Primary | D70: Notice | E70: 1920 | F70: 2026-04-09 | G70: 2027-04-08 | H70: Engineer | I70: Micron technologies | J70: Micron Technology | K70: T1 | L70: Micron (direct) | M70: 130000
A71: A-310 | B71: Ninganure, Rajashekhar | C71: Co-Applicant | D71: Notice | E71: 1920 | F71: 2026-04-09 | G71: 2027-04-08 | H71: Engineer | I71: Microchip | J71: Microchip Technology | K71: T5 | L71: Semiconductor (non-Micron) | M71: 100000
A72: A-311 | B72: Ooi, Phaik Khim | C72: Primary | D72: Current | E72: 2000 | F72: 2026-03-21 | G72: 2027-04-20 | H72: Full-Time Homemaker | L72: (blank) | M72: 175000
A73: A-311 | B73: Lai, Yuen Kong | C73: Co-Applicant | D73: Current | E73: 2000 | F73: 2026-03-21 | G73: 2027-04-20 | H73: Construction | I73: Micron | J73: Micron Technology | K73: T1 | L73: Micron (direct) | M73: 175000
A74: A-312 | B74: Thurairatnam, Rahul | C74: Primary | D74: Current | E74: 1850 | F74: 2025-12-15 | G74: 2026-12-14 | H74: Engineer | I74: Micron Technology Inc. | J74: Micron Technology | K74: T1 | L74: Micron (direct) | M74: 96000
A75: A-313 | B75: Notah, Isaiah | C75: Primary | D75: Current | E75: 2495 | F75: 2026-03-16 | G75: 2027-04-15 | H75: Construction | I75: WW STEEL ERECTORS | J75: WW Steel Erectors | K75: T2 | L75: Micron fab construction | M75: 114400
A76: A-313 | B76: Pierce, Nathan | C76: Co-Applicant | D76: Current | E76: 2495 | F76: 2026-03-16 | G76: 2027-04-15 | H76: Construction | I76: SME steel | J76: SME Steel Contractors | K76: T2 | L76: Micron fab construction | M76: 182000
A77: A-314 | B77: KURRI, NAGI REDDY | C77: Primary | D77: Current | E77: 1945 | F77: 2026-03-22 | G77: 2027-03-21 | H77: Engineer | I77: Micron Technology Inc | J77: Micron Technology | K77: T1 | L77: Micron (direct) | M77: 120000
A78: A-315 | B78: Krishnasamy, Yuvadarshini | C78: Primary | D78: Current | E78: 2375 | F78: 2026-04-04 | G78: 2027-04-03 | H78: Engineer | L78: (blank)
A79: A-315 | B79: Akkaladevi, Veena Sahithi | C79: Co-Applicant | D79: Current | E79: 2375 | F79: 2026-04-04 | G79: 2027-04-03 | H79: Engineer | I79: Micron Technology | J79: Micron Technology | K79: T1 | L79: Micron (direct) | M79: 90000
A80: A-401 | B80: Kinnee, Stroud | C80: Primary | D80: Current | E80: 2160 | F80: 2026-04-11 | G80: 2027-04-10 | H80: Construction | I80: OEG | J80: Oregon Electric Group (OEG) | K80: T2 | L80: Micron fab construction | M80: 63000
A81: A-402 | B81: Kanukuntla, Pallav | C81: Primary | D81: Current | E81: 2330 | F81: 2025-10-05 | G81: 2026-10-04 | H81: Engineer | I81: Micron Technology Inc. | J81: Micron Technology | K81: T1 | L81: Micron (direct) | M81: 135000
A82: A-402 | B82: Sanapa Prabhakar, Likhita | C82: Co-Applicant | D82: Current | E82: 2330 | F82: 2025-10-05 | G82: 2026-10-04 | H82: Engineer | I82: Micron | J82: Micron Technology | K82: T1 | L82: Micron (direct) | M82: 123000
A83: A-403 | B83: Anderson, David | C83: Primary | D83: Current | E83: 2105 | F83: 2026-03-28 | G83: 2027-03-27 | H83: Construction | I83: Barrier Building | J83: Barrier Building | K83: T6 | L83: Construction & Trades (non-Micron) | M83: 72000
A84: A-404 | B84: Avella, Marci | C84: Primary | D84: Current | E84: 2175 | F84: 2026-01-31 | G84: 2027-03-30 | H84: Medical Services | I84: St lukes | J84: St. Luke's Health System | K84: T6 | L84: Healthcare & Social Services | M84: 57600
A85: A-404 | B85: Semmens, Eric | C85: Co-Applicant | D85: Current | E85: 2175 | F85: 2026-01-31 | G85: 2027-03-30 | H85: Manufacturing | I85: Clemens sales | J85: Clemens Sales | K85: T6 | L85: Manufacturing & Consumer Products | M85: 14016
A86: A-405 | B86: Howard, Yvonne | C86: Primary | D86: Current | E86: 1875 | F86: 2025-06-15 | G86: 2026-07-14 | H86: Administrative | I86: Idaho National Guard | J86: Idaho National Guard | K86: T6 | L86: Government, Military & Public Safety | M86: 100440
A87: A-406 | B87: MATHEW, IDIKULA | C87: Primary | D87: Current | E87: 1725 | F87: 2025-12-26 | G87: 2026-12-25 | H87: Engineer | I87: Micron | J87: Micron Technology | K87: T1 | L87: Micron (direct) | M87: 120000
A88: A-406 | B88: Punnapuzha James, Anu | C88: Co-Applicant | D88: Current | E88: 1725 | F88: 2025-12-26 | G88: 2026-12-25 | H88: Unemployed/Dependent | L88: (blank)
A89: A-407 | B89: Vaith, Graham | C89: Primary | D89: Current | E89: 1655 | F89: 2025-10-23 | G89: 2026-10-22 | H89: Engineer | I89: Micron | J89: Micron Technology | K89: T1 | L89: Micron (direct) | M89: 95000
A90: A-408 | B90: McCall, Devin | C90: Primary | D90: Current | E90: 1775 | F90: 2025-12-26 | G90: 2026-12-25 | H90: Engineer | I90: Micron Technology, Inc. | J90: Micron Technology | K90: T1 | L90: Micron (direct) | M90: 80000
A91: A-409 | B91: haim, elior | C91: Primary | D91: Current | E91: 2005 | F91: 2025-09-21 | G91: 2026-11-20 | H91: Engineer | I91: ASML | J91: ASML | K91: T4 | L91: Semi equipment & materials | M91: 75000
A92: A-409 | B92: Nakav, Israel Reuven | C92: Co-Applicant | D92: Current | E92: 2005 | F92: 2025-09-21 | G92: 2026-11-20 | H92: Engineer | I92: ASML | J92: ASML | K92: T4 | L92: Semi equipment & materials | M92: 75000
A93: A-410 | B93: Bhosale, Sharwari | C93: Primary | D93: Future | E93: 0 | F93: 2026-07-14 | G93: 2027-07-13 | H93: Engineer | I93: Micron Technology | J93: Micron Technology | K93: T1 | L93: Micron (direct) | M93: 108000
A94: A-410 | B94: Jesenko, Ian | C94: Primary | D94: Notice | E94: 2300 | F94: 2025-05-21 | G94: 2026-06-20 | H94: Military | I94: The Sparrow | J94: The Sparrow | K94: T6 | L94: Hospitality | M94: 50000
A95: A-410 | B95: Jay, Akshitaa | C95: Co-Applicant | D95: Future | E95: 0 | F95: 2026-07-14 | G95: 2027-07-13 | H95: Engineer | I95: Micron Technology | J95: Micron Technology | K95: T1 | L95: Micron (direct) | M95: 93070
A96: A-410 | B96: Quintela, Diego | C96: Co-Applicant | D96: Notice | E96: 2300 | F96: 2025-05-21 | G96: 2026-06-20 | H96: Finance/Insurance/RealEstate | I96: US BANK | J96: U.S. Bank | K96: T6 | L96: Financial, Legal & Professional | M96: 33000
A97: A-411 | B97: Polamreddy, Venkata Sai Harshavardhan Reddy | C97: Primary | D97: Current | E97: 1925 | F97: 2026-06-15 | G97: 2027-06-14 | H97: Engineer | I97: Micron Technology Inc | J97: Micron Technology | K97: T1 | L97: Micron (direct) | M97: 112000
A98: A-411 | B98: Inamala, Srestha | C98: Co-Applicant | D98: Current | E98: 1925 | F98: 2026-06-15 | G98: 2027-06-14 | H98: Full-Time Homemaker | L98: (blank)
A99: A-412 | B99: Coronado, Jason | C99: Primary | D99: Notice | E99: 2300 | F99: 2025-05-02 | G99: 2026-06-01 | H99: Construction | I99: SUNTEC CONCRETE | J99: Suntec Concrete | K99: T2 | L99: Micron fab construction | M99: 132000
A100: A-412 | B100: Gerhard, Joseph | C100: Primary | D100: Future | E100: 0 | F100: 2026-07-10 | G100: 2027-07-09 | H100: Construction | I100: Acco | J100: ACCO Engineered Systems | K100: T2 | L100: Micron fab construction | M100: 301600
A101: A-412 | B101: Rodriguez, Efrain | C101: Co-Applicant | D101: Notice | E101: 2300 | F101: 2025-05-02 | G101: 2026-06-01 | H101: Construction | I101: Suntec concrete | J101: Suntec Concrete | K101: T2 | L101: Micron fab construction | M101: 120000
...
