Workbook

Sheet UW Comparison
B2: TMG UW COMPARISON — BOISE MSA
B3: Canyon Ridge (288u, SE Boise · Direct · model 6.2026) vs. Seasons at Meridian (360u, Meridian · JV · model 7.26) · 5-yr hold · 4.75% exit cap · values as of Jul 2026
B4: Blue = hard-coded from model — relink via 'Link Map' tab. Black = formula (recalcs off this sheet). Δ = CR vs SaM: dollars/counts as % difference, rates as bps, multiples as Δx.
B6: Metric | C6: Canyon Ridge | D6: Seasons at Meridian | E6: Δ CR vs SaM | F6: Notes
B8: PROPERTY SNAPSHOT
B9: Location | C9: Boise · 2552 E Gowen Rd | D9: Meridian · 2700 E Overland Rd | F9: Both Ada County, Boise MSA
B10: Year Built | C10: 2024 | D10: 2024 | F10: Both 2024 deliveries — new-vintage, in/near lease-up
B11: Units | C11: 288 | D11: 360 | E11: =IFERROR(C11/D11-1,"")
B12: Avg Unit SF | C12: 888.9375 | D12: 932.45833 | E12: =IFERROR(C12/D12-1,"")
B13: Total NRSF | C13: =C11*C12 | D13: =D11*D12 | E13: =IFERROR(C13/D13-1,"")
B14: Deal Structure | C14: Direct | D14: JV | F14: Drives investor-level return comparability (see Returns)
B15: Seller | C15: — | D15: Carlyle Group
B16: Target Close | C16: Aug 31, 2026 | D16: Oct 31, 2026
B18: MARKET — 3-MILE DEMOGRAPHICS
B19: Avg Household Income | C19: 142348 | D19: 108532.27 | E19: =IFERROR(C19/D19-1,"") | F19: Placer.ai
B20: Median Home Value | C20: 671987 | D20: 570090.81 | E20: =IFERROR(C20/D20-1,"") | F20: Placer.ai
B21: Avg Market Rent | E21: =IFERROR(C21/D21-1,"") | F21: CoStar — to be added
B23: PRICING & BASIS
B24: Whisper / Guidance Price | C24: 110000000 | D24: 125000000 | E24: =IFERROR(C24/D24-1,"")
B25: TMG Purchase Price | C25: 95000000 | D25: 110000000 | E25: =IFERROR(C25/D25-1,"")
B26: per Unit | C26: =C25/C11 | D26: =D25/D11 | E26: =IFERROR(C26/D26-1,"")
B27: per SF | C27: =C25/C13 | D27: =D25/D13 | E27: =IFERROR(C27/D27-1,"")
B28: Discount to Whisper | C28: =C25/C24-1 | D28: =D25/D24-1 | E28: =IF(OR(C28="",D28=""),"",(C28-D28)*10000)
B29: Budgeted CapEx per Unit | C29: 6885.4167 | D29: 7138.8889 | E29: =IFERROR(C29/D29-1,"") | F29: 5-yr program incl. $250/U/yr reserves; $0 value-add capex in either base UW
B30: TMG Total Basis | C30: 97345481 | D30: 1.1300603e+08 | E30: =IFERROR(C30/D30-1,"") | F30: Price + closing + financing fees + capex
B31: per Unit | C31: =C30/C11 | D31: =D30/D11 | E31: =IFERROR(C31/D31-1,"")
B32: per SF | C32: =C30/C13 | D32: =D30/D13 | E32: =IFERROR(C32/D32-1,"")
B34: RENTS & OCCUPANCY
B35: In-Place Contract Rent ($/mo) | C35: 1994.8244 | D35: 1735.1513 | E35: =IFERROR(C35/D35-1,"")
B36: per SF | C36: =C35/C12 | D36: =D35/D12 | E36: =IFERROR(C36/D36-1,"")
B37: T12 Market Rent ($/mo) | C37: 2008.6724 | D37: 1743.2632 | E37: =IFERROR(C37/D37-1,"") | F37: Hellodata
B38: T3 Market Rent ($/mo) | C38: 2201.1689 | D38: 1837.6891 | E38: =IFERROR(C38/D38-1,"") | F38: Hellodata
B39: per SF | C39: =C38/C12 | D39: =D38/D12 | E39: =IFERROR(C39/D39-1,"")
B40: TMG Y1 Market Rent ($/mo) | C40: 2052.0281 | D40: 1761.1786 | E40: =IFERROR(C40/D40-1,"")
B41: In-Place vs T3 Market (LTL) | C41: =C35/C38-1 | D41: =D35/D38-1 | E41: =IF(OR(C41="",D41=""),"",(C41-D41)*10000) | F41: Loss-to-lease = mark-to-market upside embedded in T3 rents
B42: T12 Physical Occupancy | C42: 0.77093296 | D42: 0.80318463 | E42: =IF(OR(C42="",D42=""),"",(C42-D42)*10000) | F42: Both in lease-up during T12 — T3 is the cleaner read
B43: T3 Physical Occupancy | C43: 0.97863474 | D43: 0.94946822 | E43: =IF(OR(C43="",D43=""),"",(C43-D43)*10000)
B44: T3 Economic Occupancy | C44: 0.92632513 | D44: 0.91926151 | E44: =IF(OR(C44="",D44=""),"",(C44-D44)*10000)
B45: TMG Y1 Economic Occupancy | C45: 0.93652778 | D45: 0.91972222 | E45: =IF(OR(C45="",D45=""),"",(C45-D45)*10000) | F45: Y1 physical UW'd at 94.5% for both
B46: T3 Concessions (% of GPR) | C46: 0.042014977 | D46: 0.019174393 | E46: =IF(OR(C46="",D46=""),"",(C46-D46)*10000) | F46: Burn-off tailwind as lease-up concessions roll off
B48: REVENUE & EXPENSES (TMG YEAR 1)
B49: T3 Revenue (annualized) | C49: 7283176.9 | D49: 7840420 | E49: =IFERROR(C49/D49-1,"")
B50: TMG Y1 Revenue | C50: 7619346 | D50: 7882781.8 | E50: =IFERROR(C50/D50-1,"")
B51: Y1 Other Income ($/U/mo) | C51: 276.62385 | D51: 212.98675 | E51: =IFERROR(C51/D51-1,"") | F51: Other income + RUBS + parking + revenue share
B52: Y1 OpEx per Unit (incl. reserves) | C52: 9181.519 | D52: 6876.7522 | E52: =IFERROR(C52/D52-1,"")
B53: RE Taxes per Unit | C53: 2926.6232 | D53: 1295.0009 | E53: =IFERROR(C53/D53-1,"") | F53: CR taxable value is 46% of price → UW reassesses taxes ~2.1x; SaM already assessed at 85%
B54: Insurance per Unit | C54: 550 | D54: 620 | E54: =IFERROR(C54/D54-1,"")
B55: All Other OpEx per Unit | C55: =C52-C53-C54 | D55: =D52-D53-D54 | E55: =IFERROR(C55/D55-1,"")
B56: Y1 Expense Ratio | C56: 0.33759819 | D56: 0.30263819 | E56: =IF(OR(C56="",D56=""),"",(C56-D56)*10000)
B57: Current Taxable Value | C57: 43839100 | D57: 92993300 | E57: =IFERROR(C57/D57-1,"") | F57: Reassessment risk sits with CR — already fully underwritten above
B59: NOI & YIELD (UNLEVERED)
B60: Stabilized NOI (T3 Rev @ TMG Y1 Exp) | C60: =C49-C52*C11 | D60: =D49-D52*D11 | E60: =IFERROR(C60/D60-1,"") | F60: Cleanest apples-to-apples: actual T3 revenue against TMG's Y1 expense load
B61: Cap Rate on Price | C61: =C60/C25 | D61: =D60/D25 | E61: =IF(OR(C61="",D61=""),"",(C61-D61)*10000)
B62: TMG Y1 NOI (net of reserves) | C62: 4975068.6 | D62: 5407151 | E62: =IFERROR(C62/D62-1,"")
B63: Cap Rate on Price | C63: =C62/C25 | D63: =D62/D25 | E63: =IF(OR(C63="",D63=""),"",(C63-D63)*10000)
B64: Y1 Economic Cap (w/ CapEx Adj) | C64: 0.05194592 | D64: 0.048845527 | E64: =IF(OR(C64="",D64=""),"",(C64-D64)*10000) | F64: Y1 yield net of full budgeted capex load
B65: Unlevered Return on Cost | C65: 0.057547614 | D65: 0.05729045 | E65: =IF(OR(C65="",D65=""),"",(C65-D65)*10000) | F65: Stabilized ANOI / total basis
B67: VALUE-ADD PROGRAM — Inputs staged in both models — $0 VA capex in base UW; upside lever only
B68: Units Upgraded (%) | C68: 0.5 | D68: 0.17 | E68: =IF(OR(C68="",D68=""),"",(C68-D68)*10000)
B69: Cost per Unit | C69: 15000 | D69: 15000 | E69: =IFERROR(C69/D69-1,"")
B70: Rent Premium ($/U/mo) | C70: 200 | D70: 250 | E70: =IFERROR(C70/D70-1,"")
B71: Target Return on Cost | C71: 0.16 | D71: 0.2 | E71: =IF(OR(C71="",D71=""),"",(C71-D71)*10000)
B73: FINANCING (NEW DEBT)
B74: Loan Proceeds | C74: 63164484 | D74: 71500000 | E74: =IFERROR(C74/D74-1,"")
B75: per Unit | C75: =C74/C11 | D75: =D74/D11 | E75: =IFERROR(C75/D75-1,"")
B76: LTV | C76: 0.6648893 | D76: 0.65 | E76: =IF(OR(C76="",D76=""),"",(C76-D76)*10000)
B77: LTC | C77: 0.65012782 | D77: 0.63583108 | E77: =IF(OR(C77="",D77=""),"",(C77-D77)*10000)
B78: All-In Rate | C78: 0.053229167 | D78: 0.053736111 | E78: =IF(OR(C78="",D78=""),"",(C78-D78)*10000)
B79: I/O Period (months) | C79: 36 | D79: 60 | E79: =C79-D79 | F79: SaM I/O covers the full 5-yr hold; CR amortizes from Y4
B80: Y1 DSCR | C80: 1.2387879 | D80: 1.114619 | E80: =C80-D80
B82: GROWTH & EXIT (5-YR HOLD)
B83: TMG Y6 Market Rent ($/mo) | C83: 2437.1657 | D83: 2101.7836 | E83: =IFERROR(C83/D83-1,"")
B84: T12 → Y6 Market Rent CAGR | C84: =(C83/C37)^(1/6)-1 | D84: =(D83/D37)^(1/6)-1 | E84: =IF(OR(C84="",D84=""),"",(C84-D84)*10000)
B85: Y1 → Y6 NOI CAGR | C85: 0.02783763 | D85: 0.037364282 | E85: =IF(OR(C85="",D85=""),"",(C85-D85)*10000) | F85: Gross of reserves
B86: Exit Cap Rate | C86: 0.0475 | D86: 0.0475 | E86: =IF(OR(C86="",D86=""),"",(C86-D86)*10000)
B87: Y1 Cap → Exit Cap Spread | C87: =(C63-C86)*10000 | D87: =(D63-D86)*10000 | E87: =C87-D87 | F87: Entry-yield cushion over exit cap
B88: TMG Exit NOI (F12, adj.) | C88: 5602000.1 | D88: 6474166.2 | E88: =IFERROR(C88/D88-1,"") | F88: Fwd-12 NOI at exit incl. mgmt-fee & buyer tax-reassessment adjustments
B89: Stab. NOI → Exit NOI CAGR | C89: =(C88/C60)^(1/6)-1 | D89: =(D88/D60)^(1/6)-1 | E89: =IF(OR(C89="",D89=""),"",(C89-D89)*10000)
B90: Gross Exit Value | C90: =C88/C86 | D90: =D88/D86 | E90: =IFERROR(C90/D90-1,"")
B91: per Unit | C91: =C90/C11 | D91: =D90/D11 | E91: =IFERROR(C91/D91-1,"")
B92: per SF | C92: =C90/C13 | D92: =D90/D13 | E92: =IFERROR(C92/D92-1,"")
B93: Implied Appreciation CAGR | C93: 0.044203586 | D93: 0.043805328 | E93: =IF(OR(C93="",D93=""),"",(C93-D93)*10000) | F93: Purchase price → gross exit value
B94: Hold / Exit | C94: 5 yrs · Aug 2031 | D94: 5 yrs · Oct 2031
B96: 5-YEAR RETURNS (PROPERTY LEVEL)
B97: Unlevered IRR | C97: 0.088710192 | D97: 0.086262182 | E97: =IF(OR(C97="",D97=""),"",(C97-D97)*10000)
B98: Unlevered Equity Multiple | C98: 1.4724946 | D98: 1.4579235 | E98: =C98-D98
B99: Levered IRR | C99: 0.13275456 | D99: 0.12369734 | E99: =IF(OR(C99="",D99=""),"",(C99-D99)*10000)
B100: Levered Equity Multiple | C100: 1.765757 | D100: 1.7029924 | E100: =C100-D100
B101: Avg Levered Cash Yield | C101: 0.047582139 | D101: 0.04982432 | E101: =IF(OR(C101="",D101=""),"",(C101-D101)*10000) | F101: SaM higher despite lower IRR — full-hold I/O
B102: Investor / TMG IRR | C102: 0.099823672 | D102: 0.12369734 | F102: NOT comparable: CR = investor net-of-promote (Direct); SaM = TMG position in JV
B104: Sources: TMG acquisition models (Canyon Ridge UWv2 6.2026 · Seasons at Meridian v02 7.26), Hellodata market rents, Placer.ai demographics. All growth/exit/return figures are TMG UW, not actuals.

Sheet Link Map
B2: LINK MAP — WHERE EVERY HARD-CODED VALUE COMES FROM
B3: Replace each blue value on 'UW Comparison' with an external link to the cell below. CAUTION: the two models are different template versions — Assumptions-sheet addresses differ between them (returns block is column M on Canyon Ridge but column L on Seasons; pricing cells also differ). 'Cash Flow (Annual)' addresses are identical in both.
B4: [CR] = Canyon_Ridge_UWv2 (TMG Acquisition Model 6.2026).xlsm [SaM] = TMG_Acquisitions_model_7.26 Seasons_at_Meridian_v02.xlsm
B6: Metric | C6: Cells | D6: Canyon Ridge source [CR] | E6: Seasons source [SaM] | F6: Definition
B7: Location | C7: C9 / D9 | D7: Assumptions!C5 | E7: Assumptions!C4
B8: Year Built | C8: C10 / D10 | D8: Assumptions!C7 | E8: Assumptions!C6
B9: Units | C9: C11 / D11 | D9: Assumptions!F100 | E9: Assumptions!F100
B10: Avg Unit SF | C10: C12 / D12 | D10: Assumptions!H100 | E10: Assumptions!H100
B11: Total NRSF | C11: C13 / D13 | D11: formula — do not link | E11: formula — do not link | F11: =Units × Avg SF
B12: Deal Structure | C12: C14 / D14 | D12: Assumptions!E4 | E12: Assumptions!E3
B13: Seller | C13: C15 / D15 | D13: Assumptions!E7 (blank in model) | E13: Assumptions!E6
B14: Target Close | C14: C16 / D16 | D14: Assumptions!C33 | E14: Assumptions!H4
B15: Avg Household Income | C15: C19 / D19 | D15: External — Placer.ai | E15: External — Placer.ai
B16: Median Home Value | C16: C20 / D20 | D16: External — Placer.ai | E16: External — Placer.ai
B17: Avg Market Rent | C17: C21 / D21 | D17: External — CoStar | E17: External — CoStar
B18: Whisper / Guidance Price | C18: C24 / D24 | D18: Assumptions!C35 | E18: Assumptions!H6
B19: TMG Purchase Price | C19: C25 / D25 | D19: Assumptions!C34 | E19: Assumptions!H5
B20: per Unit | C20: C26 / D26 | D20: formula — do not link | E20: formula — do not link
B21: per SF | C21: C27 / D27 | D21: formula — do not link | E21: formula — do not link
B22: Discount to Whisper | C22: C28 / D28 | D22: formula — do not link | E22: formula — do not link
B23: Budgeted CapEx per Unit | C23: C29 / D29 | D23: Assumptions!G46 | E23: Assumptions!G46
... B37: TMG Y1 Economic Occupancy | C37: C45 / D45 | D37: 'Cash Flow (Annual)'!K15 | E37: 'Cash Flow (Annual)'!K15
B38: T3 Concessions (% of GPR) | C38: C46 / D46 | D38: =-'Cash Flow (Annual)'!I25 / 'Cash Flow (Annual)'!I16 | E38: =-'Cash Flow (Annual)'!I25 / 'Cash Flow (Annual)'!I16
B39: T3 Revenue (annualized) | C39: C49 / D49 | D39: 'Cash Flow (Annual)'!I35 | E39: 'Cash Flow (Annual)'!I35
B40: TMG Y1 Revenue | C40: C50 / D50 | D40: 'Cash Flow (Annual)'!K35 | E40: 'Cash Flow (Annual)'!K35
B41: Y1 Other Income ($/U/mo) | C41: C51 / D51 | D41: =SUM('Cash Flow (Annual)'!K29:K32)/Units/12 | E41: =SUM('Cash Flow (Annual)'!K29:K32)/Units/12
B42: Y1 OpEx per Unit (incl. reserves) | C42: C52 / D52 | D42: =('Cash Flow (Annual)'!K53+'Cash Flow (Annual)'!K63)/Units | E42: =('Cash Flow (Annual)'!K53+'Cash Flow (Annual)'!K63)/Units
B43: RE Taxes per Unit | C43: C53 / D53 | D43: ='Cash Flow (Annual)'!K50/Units | E43: ='Cash Flow (Annual)'!K50/Units
B44: Insurance per Unit | C44: C54 / D54 | D44: ='Cash Flow (Annual)'!K49/Units | E44: ='Cash Flow (Annual)'!K49/Units
B45: All Other OpEx per Unit | C45: C55 / D55 | D45: formula — do not link | E45: formula — do not link
B46: Y1 Expense Ratio | C46: C56 / D56 | D46: 'Cash Flow (Annual)'!K55 | E46: 'Cash Flow (Annual)'!K55
B47: Current Taxable Value | C47: C57 / D57 | D47: Assumptions!K42 | E47: Assumptions!K42
B48: Stabilized NOI (T3 Rev @ TMG Y1 Exp) | C48: C60 / D60 | D48: formula — do not link | E48: formula — do not link
B49: Cap Rate on Price | C49: C61 / D61 | D49: formula — do not link | E49: formula — do not link
B50: TMG Y1 NOI (net of reserves) | C50: C62 / D62 | D50: ='Cash Flow (Annual)'!K59-'Cash Flow (Annual)'!K63 | E50: ='Cash Flow (Annual)'!K59-'Cash Flow (Annual)'!K63
B51: Cap Rate on Price | C51: C63 / D63 | D51: formula — do not link | E51: formula — do not link
B52: Y1 Economic Cap (w/ CapEx Adj) | C52: C64 / D64 | D52: Assumptions!E41 | E52: Assumptions!E35
B53: Unlevered Return on Cost | C53: C65 / D65 | D53: Assumptions!K39 | E53: Assumptions!K39
B54: Units Upgraded (%) | C54: C68 / D68 | D54: Assumptions!G32 | E54: Assumptions!G32
B55: Cost per Unit | C55: C69 / D69 | D55: Assumptions!G35 | E55: Assumptions!G35
B56: Rent Premium ($/U/mo) | C56: C70 / D70 | D56: Assumptions!G36 | E56: Assumptions!G36
B57: Target Return on Cost | C57: C71 / D71 | D57: Assumptions!G39 | E57: Assumptions!G39
B58: Loan Proceeds | C58: C74 / D74 | D58: Assumptions!I33 | E58: Assumptions!I33
B59: per Unit | C59: C75 / D75 | D59: formula — do not link | E59: formula — do not link
B60: LTV | C60: C76 / D76 | D60: Assumptions!I38 | E60: Assumptions!I38
B61: LTC | C61: C77 / D77 | D61: Assumptions!I39 | E61: Assumptions!I39
B62: All-In Rate | C62: C78 / D78 | D62: Assumptions!I37 | E62: Assumptions!I37
... B66: T12 → Y6 Market Rent CAGR | C66: C84 / D84 | D66: formula — do not link | E66: formula — do not link
B67: Y1 → Y6 NOI CAGR | C67: C85 / D85 | D67: =('Cash Flow (Annual)'!P59/'Cash Flow (Annual)'!K59)^(1/5)-1 | E67: =('Cash Flow (Annual)'!P59/'Cash Flow (Annual)'!K59)^(1/5)-1
B68: Exit Cap Rate | C68: C86 / D86 | D68: Assumptions!M33 | E68: Assumptions!M33
B69: Y1 Cap → Exit Cap Spread | C69: C87 / D87 | D69: formula — do not link | E69: formula — do not link
B70: TMG Exit NOI (F12, adj.) | C70: C88 / D88 | D70: =SUM(Assumptions!M36:M38) | E70: =SUM(Assumptions!M36:M38)
B71: Stab. NOI → Exit NOI CAGR | C71: C89 / D89 | D71: formula — do not link | E71: formula — do not link
B72: Gross Exit Value | C72: C90 / D90 | D72: formula — do not link | E72: formula — do not link
B73: per Unit | C73: C91 / D91 | D73: formula — do not link | E73: formula — do not link
B74: per SF | C74: C92 / D92 | D74: formula — do not link | E74: formula — do not link
B75: Implied Appreciation CAGR | C75: C93 / D93 | D75: Assumptions!M43 | E75: Assumptions!M43
B76: Hold / Exit | C76: C94 / D94 | D76: Assumptions!M32, Assumptions!M44 | E76: Assumptions!M32, Assumptions!M44
B77: Unlevered IRR | C77: C97 / D97 | D77: Assumptions!M12 | E77: Assumptions!L12
B78: Unlevered Equity Multiple | C78: C98 / D98 | D78: Assumptions!M15 | E78: Assumptions!L15
B79: Levered IRR | C79: C99 / D99 | D79: Assumptions!M17 | E79: Assumptions!L17
B80: Levered Equity Multiple | C80: C100 / D100 | D80: Assumptions!M20 | E80: Assumptions!L20
B81: Avg Levered Cash Yield | C81: C101 / D101 | D81: Assumptions!M21 | E81: Assumptions!L21
B82: Investor / TMG IRR | C82: C102 / D102 | D82: Assumptions!M22 | E82: Assumptions!L22
